Workbook

Sheet Executive Summary
A1: Chronic Care Cascade Pilot — Cost Model Overview
A3: Pilot purpose
A4: Demonstrate that a trusted intermediary can reuse existing standards-based clinical data and infrastructure to produce a governed diabetes dataset for state public health surveillance and CMS-aligned digital quality measurement, while reducing duplicative reporting and making data quality transparent.
A8: What one modeled pilot site includes | D8: Key modeling boundaries
A9: Primary participant | B9: 1 state PHA | D9: Included | E9: Participant labor, vendor fees, ODCs, participant indirects, site evaluation support, 7.5% contingency
A10: Provider participants | B10: 10 FQHCs and 2 other outpatient healthcare organizations | D10: Excluded | E10: Pre-award charter development, NP/prime administration, independent evaluation, post-pilot operations
A11: Technical diversity | B11: 5 source-system/vendor configurations; 2 shared FQHC configurations | D11: Infrastructure posture | E11: Existing interfaces, platforms, matching, trust, de-identification, monitoring, and analytics are configured—not rebuilt
A12: Intermediary structure | B12: One of three models defined on the Scenario Definitions sheet | D12: Optional add-ons | E12: UDS+ interface; chronic-care referral analysis; new medication-dispensing connection
A13: Core outputs | B13: PHA diabetes surveillance product and CMS122 | D13: Primary user | E13: State PHA; other federal and quality uses are secondary to the site cost build
A14: Operating window | B14: 12-month funded pilot with 9 months of live exchange (6-month sensitivity) | D14: Clinical scope | E14: Diabetes, priced as narrow A1c-focused and broad longitudinal cascade variants
A16: How to use this workbook
A17: 1 | B17: Select the target scenario (intermediary model and dataset scope) on the "Scenario Definitions" sheet.
A18: 2 | B18: Adjust cost-sensitive quantities and assumptions on the "Assumptions & Inputs" sheet.
A20: Source basis: Chronic Pilot Overview; Draft Chronic Care Cascade Pilot Data Flow Architectures; Tech Brief: PHIG B4 Chronic Care Cascade Pilot; and the approved scope assumptions developed for this cost model.
A23: Estimate maturity: provisional bottom-up model. Labor rates, unit hours, vendor fees, participant indirect rates, and benchmark citations require validation before use as a procurement or funding commitment.
A27: Pro Forma Cost Summary
A29: Selected Scenario | B29: Estimating Case | C29: Low | D29: Base | E29: High
A30: ='Scenario Definitions'!C5 -> 2A | B30: =_xlfn.XLOOKUP($A$30, ScenarioTable[Scenario ID], ScenarioTable[Intermediary Model]) -> HIE/HDU with HCCN | C30: =SUMIF('Cost Build-Up'!$AE$5:$AE$77,1,'Cost Build-Up'!$BH$5:$BH$77)+SUM('Optional Add-Ons Build-Up'!$W$5:$W$16) -> 1492378.3 | D30: =SUMIF('Cost Build-Up'!$AE$5:$AE$77,1,'Cost Build-Up'!$BI$5:$BI$77)+SUM('Optional Add-Ons Build-Up'!$X$5:$X$16) -> 3094276.4 | E30: =SUMIF('Cost Build-Up'!$AE$5:$AE$77,1,'Cost Build-Up'!$BJ$5:$BJ$77)+SUM('Optional Add-Ons Build-Up'!$Y$5:$Y$16) -> 8028489.6
B32: Metric | C32: Low | D32: Base | E32: High
B33: Sponsor-funded cost before contingency | C33: =SUMIF('Cost Build-Up'!$AE$5:$AE$77,1,'Cost Build-Up'!$AT$5:$AT$77)+SUMIF('Cost Build-Up'!$AE$5:$AE$77,1,'Cost Build-Up'!$AW$5:$AW$77)+SUMIF('Cost Build-Up'!$AE$5:$AE$77,1,'Cost Build-Up'!$BA$5:$BA$77) -> 1433402 | D33: =SUMIF('Cost Build-Up'!$AE$5:$AE$77,1,'Cost Build-Up'!$AU$5:$AU$77)+SUMIF('Cost Build-Up'!$AE$5:$AE$77,1,'Cost Build-Up'!$AX$5:$AX$77)+SUMIF('Cost Build-Up'!$AE$5:$AE$77,1,'Cost Build-Up'!$BB$5:$BB$77) -> 2911271.7 | E33: =SUMIF('Cost Build-Up'!$AE$5:$AE$77,1,'Cost Build-Up'!$AV$5:$AV$77)+SUMIF('Cost Build-Up'!$AE$5:$AE$77,1,'Cost Build-Up'!$AY$5:$AY$77)+SUMIF('Cost Build-Up'!$AE$5:$AE$77,1,'Cost Build-Up'!$BC$5:$BC$77) -> 7123349.3
B34: Contingency | C34: =SUMIF('Cost Build-Up'!$AE$5:$AE$77,1,'Cost Build-Up'!$BE$5:$BE$77) -> 58976.25 | D34: =SUMIF('Cost Build-Up'!$AE$5:$AE$77,1,'Cost Build-Up'!$BF$5:$BF$77) -> 183004.65 | E34: =SUMIF('Cost Build-Up'!$AE$5:$AE$77,1,'Cost Build-Up'!$BG$5:$BG$77) -> 905140.28
B35: Sponsor-funded cost including contingency | C35: =C33+C34+SUM('Optional Add-Ons Build-Up'!$W$5:$W$16) -> 1492378.3 | D35: =D33+D34+SUM('Optional Add-Ons Build-Up'!$X$5:$X$16) -> 3094276.4 | E35: =E33+E34+SUM('Optional Add-Ons Build-Up'!$Y$5:$Y$16) -> 8028489.6
B36: Unreimbursed in-kind cost | C36: 0 | D36: 0 | E36: 0
B37: Total economic cost | C37: =C35+C36 -> 1492378.3 | D37: =D35+D36 -> 3094276.4 | E37: =E35+E36 -> 8028489.6
B38: One-time implementation and evaluation | C38: =SUMIFS('Cost Build-Up'!$BH$5:$BH$77,'Cost Build-Up'!$D$5:$D$77,"<>Pilot operations and support",'Cost Build-Up'!$AE$5:$AE$77,1) -> 1141936.3 | D38: =SUMIFS('Cost Build-Up'!$BI$5:$BI$77,'Cost Build-Up'!$D$5:$D$77,"<>Pilot operations and support",'Cost Build-Up'!$AE$5:$AE$77,1) -> 2320041.1 | E38: =SUMIFS('Cost Build-Up'!$BJ$5:$BJ$77,'Cost Build-Up'!$D$5:$D$77,"<>Pilot operations and support",'Cost Build-Up'!$AE$5:$AE$77,1) -> 6429867.6
B39: Recurring pilot operations | C39: =SUMIFS('Cost Build-Up'!$BH$5:$BH$77,'Cost Build-Up'!$D$5:$D$77,"Pilot operations and support",'Cost Build-Up'!$AE$5:$AE$77,1) -> 350442 | D39: =SUMIFS('Cost Build-Up'!$BI$5:$BI$77,'Cost Build-Up'!$D$5:$D$77,"Pilot operations and support",'Cost Build-Up'!$AE$5:$AE$77,1) -> 774235.25 | E39: =SUMIFS('Cost Build-Up'!$BJ$5:$BJ$77,'Cost Build-Up'!$D$5:$D$77,"Pilot operations and support",'Cost Build-Up'!$AE$5:$AE$77,1) -> 1598622
B40: Monthly pilot operating run rate | C40: =IFERROR(C39/VLOOKUP("IN-18",'Assumptions & Inputs'!$A$31:$F$69,3,FALSE),0) -> 58407 | D40: =IFERROR(D39/VLOOKUP("IN-18",'Assumptions & Inputs'!$A$31:$F$69,4,FALSE),0) -> 86026.139 | E40: =IFERROR(E39/VLOOKUP("IN-18",'Assumptions & Inputs'!$A$31:$F$69,5,FALSE),0) -> 177624.67
B42: Organization Group | C42: Low | D42: Base | E42: High
B43: State PHA | C43: =SUMIFS('Cost Build-Up'!$BH$5:$BH$77,'Cost Build-Up'!$C$5:$C$77,$B43,'Cost Build-Up'!$AE$5:$AE$77,1) -> 212139.9 | D43: =SUMIFS('Cost Build-Up'!$BI$5:$BI$77,'Cost Build-Up'!$C$5:$C$77,$B43,'Cost Build-Up'!$AE$5:$AE$77,1) -> 375621.1 | E43: =SUMIFS('Cost Build-Up'!$BJ$5:$BJ$77,'Cost Build-Up'!$C$5:$C$77,$B43,'Cost Build-Up'!$AE$5:$AE$77,1) -> 927010.2
B44: HIE/HDU Intermediary | C44: =SUMIFS('Cost Build-Up'!$BH$5:$BH$77,'Cost Build-Up'!$C$5:$C$77,$B44,'Cost Build-Up'!$AE$5:$AE$77,1) -> 788159.4 | D44: =SUMIFS('Cost Build-Up'!$BI$5:$BI$77,'Cost Build-Up'!$C$5:$C$77,$B44,'Cost Build-Up'!$AE$5:$AE$77,1) -> 1523946.9 | E44: =SUMIFS('Cost Build-Up'!$BJ$5:$BJ$77,'Cost Build-Up'!$C$5:$C$77,$B44,'Cost Build-Up'!$AE$5:$AE$77,1) -> 3568234
B45: HCCN | C45: =SUMIFS('Cost Build-Up'!$BH$5:$BH$77,'Cost Build-Up'!$C$5:$C$77,$B45,'Cost Build-Up'!$AE$5:$AE$77,1) -> 262464.22 | D45: =SUMIFS('Cost Build-Up'!$BI$5:$BI$77,'Cost Build-Up'!$C$5:$C$77,$B45,'Cost Build-Up'!$AE$5:$AE$77,1) -> 578428.5 | E45: =SUMIFS('Cost Build-Up'!$BJ$5:$BJ$77,'Cost Build-Up'!$C$5:$C$77,$B45,'Cost Build-Up'!$AE$5:$AE$77,1) -> 1484093.5
B46: Healthcare Organizations & FQHCs | C46: =SUMIFS('Cost Build-Up'!$BH$5:$BH$77,'Cost Build-Up'!$C$5:$C$77,$B46,'Cost Build-Up'!$AE$5:$AE$77,1) -> 229614.75 | D46: =SUMIFS('Cost Build-Up'!$BI$5:$BI$77,'Cost Build-Up'!$C$5:$C$77,$B46,'Cost Build-Up'!$AE$5:$AE$77,1) -> 616279.85 | E46: =SUMIFS('Cost Build-Up'!$BJ$5:$BJ$77,'Cost Build-Up'!$C$5:$C$77,$B46,'Cost Build-Up'!$AE$5:$AE$77,1) -> 2049151.9
B48: Lifecycle Workstream | C48: Low | D48: Base | E48: High
B49: Implementation management | C49: =SUMIFS('Cost Build-Up'!$BH$5:$BH$77,'Cost Build-Up'!$D$5:$D$77,$B49,'Cost Build-Up'!$AE$5:$AE$77,1) -> 202089 | D49: =SUMIFS('Cost Build-Up'!$BI$5:$BI$77,'Cost Build-Up'!$D$5:$D$77,$B49,'Cost Build-Up'!$AE$5:$AE$77,1) -> 303779 | E49: =SUMIFS('Cost Build-Up'!$BJ$5:$BJ$77,'Cost Build-Up'!$D$5:$D$77,$B49,'Cost Build-Up'!$AE$5:$AE$77,1) -> 610476
B50: Governance, legal, privacy, and security | C50: =SUMIFS('Cost Build-Up'!$BH$5:$BH$77,'Cost Build-Up'!$D$5:$D$77,$B50,'Cost Build-Up'!$AE$5:$AE$77,1) -> 150347.4 | D50: =SUMIFS('Cost Build-Up'!$BI$5:$BI$77,'Cost Build-Up'!$D$5:$D$77,$B50,'Cost Build-Up'!$AE$5:$AE$77,1) -> 307886.7 | E50: =SUMIFS('Cost Build-Up'!$BJ$5:$BJ$77,'Cost Build-Up'!$D$5:$D$77,$B50,'Cost Build-Up'!$AE$5:$AE$77,1) -> 1106709.2
B51: Data specification and mapping | C51: =SUMIFS('Cost Build-Up'!$BH$5:$BH$77,'Cost Build-Up'!$D$5:$D$77,$B51,'Cost Build-Up'!$AE$5:$AE$77,1) -> 92238.075 | D51: =SUMIFS('Cost Build-Up'!$BI$5:$BI$77,'Cost Build-Up'!$D$5:$D$77,$B51,'Cost Build-Up'!$AE$5:$AE$77,1) -> 191686.25 | E51: =SUMIFS('Cost Build-Up'!$BJ$5:$BJ$77,'Cost Build-Up'!$D$5:$D$77,$B51,'Cost Build-Up'!$AE$5:$AE$77,1) -> 483784.3
B52: Configuration and integration | C52: =SUMIFS('Cost Build-Up'!$BH$5:$BH$77,'Cost Build-Up'!$D$5:$D$77,$B52,'Cost Build-Up'!$AE$5:$AE$77,1) -> 379185.15 | D52: =SUMIFS('Cost Build-Up'!$BI$5:$BI$77,'Cost Build-Up'!$D$5:$D$77,$B52,'Cost Build-Up'!$AE$5:$AE$77,1) -> 734896.25 | E52: =SUMIFS('Cost Build-Up'!$BJ$5:$BJ$77,'Cost Build-Up'!$D$5:$D$77,$B52,'Cost Build-Up'!$AE$5:$AE$77,1) -> 1790295.9
B53: Testing and remediation | C53: =SUMIFS('Cost Build-Up'!$BH$5:$BH$77,'Cost Build-Up'!$D$5:$D$77,$B53,'Cost Build-Up'!$AE$5:$AE$77,1) -> 149182.27 | D53: =SUMIFS('Cost Build-Up'!$BI$5:$BI$77,'Cost Build-Up'!$D$5:$D$77,$B53,'Cost Build-Up'!$AE$5:$AE$77,1) -> 391268.4 | E53: =SUMIFS('Cost Build-Up'!$BJ$5:$BJ$77,'Cost Build-Up'!$D$5:$D$77,$B53,'Cost Build-Up'!$AE$5:$AE$77,1) -> 1262982.1
B54: Onboarding and training | C54: =SUMIFS('Cost Build-Up'!$BH$5:$BH$77,'Cost Build-Up'!$D$5:$D$77,$B54,'Cost Build-Up'!$AE$5:$AE$77,1) -> 45847.125 | D54: =SUMIFS('Cost Build-Up'!$BI$5:$BI$77,'Cost Build-Up'!$D$5:$D$77,$B54,'Cost Build-Up'!$AE$5:$AE$77,1) -> 124268.5 | E54: =SUMIFS('Cost Build-Up'!$BJ$5:$BJ$77,'Cost Build-Up'!$D$5:$D$77,$B54,'Cost Build-Up'!$AE$5:$AE$77,1) -> 372939
B55: Pilot operations and support | C55: =SUMIFS('Cost Build-Up'!$BH$5:$BH$77,'Cost Build-Up'!$D$5:$D$77,$B55,'Cost Build-Up'!$AE$5:$AE$77,1) -> 350442 | D55: =SUMIFS('Cost Build-Up'!$BI$5:$BI$77,'Cost Build-Up'!$D$5:$D$77,$B55,'Cost Build-Up'!$AE$5:$AE$77,1) -> 774235.25 | E55: =SUMIFS('Cost Build-Up'!$BJ$5:$BJ$77,'Cost Build-Up'!$D$5:$D$77,$B55,'Cost Build-Up'!$AE$5:$AE$77,1) -> 1598622
B56: Evaluation, playbook, and closeout | C56: =SUMIFS('Cost Build-Up'!$BH$5:$BH$77,'Cost Build-Up'!$D$5:$D$77,$B56,'Cost Build-Up'!$AE$5:$AE$77,1) -> 123047.25 | D56: =SUMIFS('Cost Build-Up'!$BI$5:$BI$77,'Cost Build-Up'!$D$5:$D$77,$B56,'Cost Build-Up'!$AE$5:$AE$77,1) -> 266256 | E56: =SUMIFS('Cost Build-Up'!$BJ$5:$BJ$77,'Cost Build-Up'!$D$5:$D$77,$B56,'Cost Build-Up'!$AE$5:$AE$77,1) -> 802681
A58: Optional Components
A59: Add-On ID | B59: Component | C59: Active? | D59: Base Increment | E59: Trigger
A60: ADD-01 | B60: UDS+ interface and support | C60: ='Optional Add-Ons Build-Up'!K5 -> No | D60: ='Optional Add-Ons Build-Up'!N5+'Optional Add-Ons Build-Up'!Q5 -> 370000 | E60: Included only when UDS+ is in charter and no adequate pathway exists
A61: ADD-02 | B61: Closed-loop chronic-care referral analysis | C61: ='Optional Add-Ons Build-Up'!K6 -> No | D61: ='Optional Add-Ons Build-Up'!N6+'Optional Add-Ons Build-Up'!Q6 -> 135000 | E61: Requires an operational referral platform and governance model
A62: ADD-03 | B62: New MedicationDispense connection | C62: ='Optional Add-Ons Build-Up'!K7 -> No | D62: ='Optional Add-Ons Build-Up'!N7+'Optional Add-Ons Build-Up'!Q7 -> 420000 | E62: Required only when broad scope needs dispensing data not already available
A63: ADD-10 | B63: Formal security authorization or penetration testing | C63: ='Optional Add-Ons Build-Up'!K14 -> No | D63: ='Optional Add-Ons Build-Up'!N14+'Optional Add-Ons Build-Up'!Q14 -> 330000 | E63: Required by PHA/intermediary security authority
A65: Key Estimate Caveats
A66: Planning estimate | B66: This model is intended for comparison and planning, not as a vendor quote or procurement commitment.
A67: Existing-platform reuse | B67: Base scope assumes existing exchange, matching, trust, de-identification, monitoring, and analytics capabilities are configured rather than rebuilt.
A68: Rates and indirects | B68: Labor rates, vendor fees, and participant indirect rates remain provisional and require validation.
A69: Excluded costs | B69: NP/prime administration, independent evaluation, pre-award chartering, and post-pilot operations are excluded.
A70: Add-on treatment | B70: Ordinary scale variables are handled through inputs; only ADD-01, ADD-02, ADD-03, and ADD-10 remain separate optional components.

Sheet Scenario Definitions
A1: Scenario Definitions
A2: Scenario convention: the letter identifies dataset scope (A = narrow A1c-focused; B = broad longitudinal cascade). The number identifies the intermediary operating model.
B5: Selected Scenario | C5: 2A
A7: Scenario ID | B7: Intermediary Model | C7: Provider Structure | D7: Dataset Scope | E7: Operations | F7: Key Distinction | G7: Low Total | H7: Base Total | I7: High Total
A8: 1A | B8: HIE/HDU without HCCN | C8: 10 FQHCs + 2 healthcare organizations connect without HCCN consolidation | D8: Narrow A1c-focused | E8: 9 months | F8: Most source connections; no HCCN managed-services layer | G8: =SUM('Cost Build-Up'!$BU$5:$BU$77) -> 1229914.1 | H8: =SUM('Cost Build-Up'!$BV$5:$BV$77) -> 2587667.9 | I8: =SUM('Cost Build-Up'!$BW$5:$BW$77) -> 6714496.1
A9: 1B | B9: HIE/HDU without HCCN | C9: Same as 1A | D9: Broad longitudinal diabetes cascade | E9: 9 months | F9: Adds broader data, mapping, analytics, and validation | G9: =SUM('Cost Build-Up'!$BX$5:$BX$77) -> 1285904.6 | H9: =SUM('Cost Build-Up'!$BY$5:$BY$77) -> 2702027.9 | I9: =SUM('Cost Build-Up'!$BZ$5:$BZ$77) -> 7013848.6
A10: 2A | B10: HIE/HDU with HCCN | C10: HCCN consolidates 10 FQHCs; 2 healthcare organizations connect directly | D10: Narrow A1c-focused | E10: 9 months | F10: HCCN adds managed services and reduces production interfaces | G10: =SUM('Cost Build-Up'!$CA$5:$CA$77) -> 1492378.3 | H10: =SUM('Cost Build-Up'!$CB$5:$CB$77) -> 3094276.4 | I10: =SUM('Cost Build-Up'!$CC$5:$CC$77) -> 8028489.6
A11: 2B | B11: HIE/HDU with HCCN | C11: Same as 2A | D11: Broad longitudinal diabetes cascade | E11: 9 months | F11: Broad scope plus two intermediary/aggregation layers | G11: =SUM('Cost Build-Up'!$CD$5:$CD$77) -> 1548368.8 | H11: =SUM('Cost Build-Up'!$CE$5:$CE$77) -> 3208636.4 | I11: =SUM('Cost Build-Up'!$CF$5:$CF$77) -> 8327842.1
A12: 3A | B12: HCCN acting as intermediary | C12: HCCN ingests 10 FQHCs and 2 healthcare organizations; no HIE/HDU | D12: Narrow A1c-focused | E12: 9 months | F12: HCCN performs full intermediary, trust, and PHA delivery functions | G12: =SUM('Cost Build-Up'!$CG$5:$CG$77) -> 977031.38 | H12: =SUM('Cost Build-Up'!$CH$5:$CH$77) -> 2187904.5 | I12: =SUM('Cost Build-Up'!$CI$5:$CI$77) -> 5846278.1
A13: 3B | B13: HCCN acting as intermediary | C13: Same as 3A | D13: Broad longitudinal diabetes cascade | E13: 9 months | F13: Broad scope delivered entirely through HCCN intermediary model | G13: =SUM('Cost Build-Up'!$CJ$5:$CJ$77) -> 1033021.9 | H13: =SUM('Cost Build-Up'!$CK$5:$CK$77) -> 2302264.5 | I13: =SUM('Cost Build-Up'!$CL$5:$CL$77) -> 6145630.6
A15: Separately priced add-ons and sensitivities
A16: These packages are excluded from the base scenario unless their trigger occurs.
A18: Add-On ID | B18: Item | C18: Trigger | D18: Applies To | E18: Model Treatment | F18: Key Cost Driver | G18: Low Total | H18: Base Total | I18: High Total
A19: ADD-01 | B19: UDS+ interface | C19: Charter includes UDS+ and no adequate existing pathway is available | D19: Any scenario | E19: Optional add-on | F19: May require a new interface, mapping, authentication, and HRSA validation | G19: =SUM('Optional Add-Ons Build-Up'!M5, 'Optional Add-Ons Build-Up'!P5) -> 170000 | H19: =SUM('Optional Add-Ons Build-Up'!N5, 'Optional Add-Ons Build-Up'!Q5) -> 370000 | I19: =SUM('Optional Add-Ons Build-Up'!O5, 'Optional Add-Ons Build-Up'!R5) -> 750000
A20: ADD-02 | B20: Closed-loop chronic-care referral analysis | C20: Charter includes referral add-on and an existing referral platform/governance model is operational | D20: Any scenario with existing referral infrastructure | E20: Optional add-on | F20: Marginal workflow, data, and evaluation configuration only | G20: =SUM('Optional Add-Ons Build-Up'!M6, 'Optional Add-Ons Build-Up'!P6) -> 60000 | H20: =SUM('Optional Add-Ons Build-Up'!N6, 'Optional Add-Ons Build-Up'!Q6) -> 135000 | I20: =SUM('Optional Add-Ons Build-Up'!O6, 'Optional Add-Ons Build-Up'!R6) -> 320000
A21: ADD-03 | B21: New medication-dispensing connection | C21: Broad scope requires dispensing data not already available | D21: Broad-scope scenarios if existing data are unavailable | E21: Optional add-on | F21: New pharmacy/payer interface and data-use work | G21: =SUM('Optional Add-Ons Build-Up'!M7, 'Optional Add-Ons Build-Up'!P7) -> 175000 | H21: =SUM('Optional Add-Ons Build-Up'!N7, 'Optional Add-Ons Build-Up'!Q7) -> 420000 | I21: =SUM('Optional Add-Ons Build-Up'!O7, 'Optional Add-Ons Build-Up'!R7) -> 950000
A22: ADD-04 | B22: Additional non-FQHC healthcare organization | C22: Participant count exceeds two | D22: Any scenario | E22: Marginal unit | F22: Onboarding, legal, validation, training, and support | G22: =SUM('Optional Add-Ons Build-Up'!M8, 'Optional Add-Ons Build-Up'!P8) -> 30000 | H22: =SUM('Optional Add-Ons Build-Up'!N8, 'Optional Add-Ons Build-Up'!Q8) -> 65000 | I22: =SUM('Optional Add-Ons Build-Up'!O8, 'Optional Add-Ons Build-Up'!R8) -> 135000
A23: ADD-05 | B23: Additional FQHC | C23: FQHC count exceeds ten | D23: Any scenario | E23: Marginal unit | F23: Onboarding, legal, validation, training, and support | G23: =SUM('Optional Add-Ons Build-Up'!M9, 'Optional Add-Ons Build-Up'!P9) -> 14000 | H23: =SUM('Optional Add-Ons Build-Up'!N9, 'Optional Add-Ons Build-Up'!Q9) -> 31000 | I23: =SUM('Optional Add-Ons Build-Up'!O9, 'Optional Add-Ons Build-Up'!R9) -> 65000
A24: ADD-06 | B24: Additional source-system configuration | C24: More than five distinct configurations or a materially different tenant pattern | D24: Any scenario | E24: Marginal unit | F24: Mapping, interface configuration, testing, and remediation | G24: =SUM('Optional Add-Ons Build-Up'!M10, 'Optional Add-Ons Build-Up'!P10) -> 60000 | H24: =SUM('Optional Add-Ons Build-Up'!N10, 'Optional Add-Ons Build-Up'!Q10) -> 125000 | I24: =SUM('Optional Add-Ons Build-Up'!O10, 'Optional Add-Ons Build-Up'!R10) -> 260000
A25: ADD-07 | B25: Additional production interface | C25: Interface topology exceeds scenario base | D25: Any scenario | E25: Marginal unit | F25: Mapping, interface configuration, testing, and remediation | G25: =SUM('Optional Add-Ons Build-Up'!M11, 'Optional Add-Ons Build-Up'!P11) -> 50000 | H25: =SUM('Optional Add-Ons Build-Up'!N11, 'Optional Add-Ons Build-Up'!Q11) -> 105000 | I25: =SUM('Optional Add-Ons Build-Up'!O11, 'Optional Add-Ons Build-Up'!R11) -> 220000
A26: ADD-08 | B26: Additional remediation cycle | C26: Two base remediation cycles are insufficient | D26: Any scenario | E26: Marginal unit | F26: Vendor, provider, intermediary, and project-management effort | G26: =SUM('Optional Add-Ons Build-Up'!M12, 'Optional Add-Ons Build-Up'!P12) -> 40000 | H26: =SUM('Optional Add-Ons Build-Up'!N12, 'Optional Add-Ons Build-Up'!Q12) -> 95000 | I26: =SUM('Optional Add-Ons Build-Up'!O12, 'Optional Add-Ons Build-Up'!R12) -> 230000
A27: ADD-09 | B27: Six-month operations sensitivity | C27: Schedule permits only six live months or sponsor chooses shorter evidence period | D27: Any scenario | E27: Schedule sensitivity | F27: Reduces recurring support and evaluation evidence period | G27: =SUM('Optional Add-Ons Build-Up'!M13, 'Optional Add-Ons Build-Up'!P13) -> -240000 | H27: =SUM('Optional Add-Ons Build-Up'!N13, 'Optional Add-Ons Build-Up'!Q13) -> -440000 | I27: =SUM('Optional Add-Ons Build-Up'!O13, 'Optional Add-Ons Build-Up'!R13) -> -740000
A28: ADD-10 | B28: Formal security authorization or penetration testing | C28: PHA/intermediary requires ATO-equivalent approval, independent assessment, or new control documentation | D28: Any scenario | E28: Marginal unit | G28: =SUM('Optional Add-Ons Build-Up'!M14, 'Optional Add-Ons Build-Up'!P14) -> 130000 | H28: =SUM('Optional Add-Ons Build-Up'!N14, 'Optional Add-Ons Build-Up'!Q14) -> 330000 | I28: =SUM('Optional Add-Ons Build-Up'!O14, 'Optional Add-Ons Build-Up'!R14) -> 800000
A29: ADD-11 | B29: New environment or software license | C29: Existing environment capacity or licenses are insufficient | D29: Any scenario | E29: Marginal unit | G29: =SUM('Optional Add-Ons Build-Up'!M15, 'Optional Add-Ons Build-Up'!P15) -> 110000 | H29: =SUM('Optional Add-Ons Build-Up'!N15, 'Optional Add-Ons Build-Up'!Q15) -> 260000 | I29: =SUM('Optional Add-Ons Build-Up'!O15, 'Optional Add-Ons Build-Up'!R15) -> 650000
A30: ADD-12 | B30: High-intensity technical assistance | C30: Readiness validation identifies material participant capability gaps | D30: Any scenario | E30: Marginal unit | G30: =SUM('Optional Add-Ons Build-Up'!M16, 'Optional Add-Ons Build-Up'!P16) -> 45000 | H30: =SUM('Optional Add-Ons Build-Up'!N16, 'Optional Add-Ons Build-Up'!Q16) -> 105000 | I30: =SUM('Optional Add-Ons Build-Up'!O16, 'Optional Add-Ons Build-Up'!R16) -> 240000

Sheet Assumptions & Inputs
A1: Model Assumptions and Inputs
A3: Core modeling assumptions
A4: Assumption | B4: Status | C4: Cost Effect | D4: Treatment
A5: Pre-award charter is complete and not funded | B5: Fixed | C5: Reduces funded planning scope | D5: Exclusion
A6: Implementation plan is funded and derived from the charter | B6: Fixed | C6: Adds Month 1 implementation-management effort | D6: Included
A7: Existing FHIR and HL7 v2 endpoints are functioning | B7: Moderate confidence | C7: Avoids greenfield source-interface builds | D7: Base assumption + contingency risk
A8: Architecture and interface documents need minor updates only | B8: High confidence | C8: Limits architecture/design labor | D8: Fixed assumption
A9: Normalization, matching, deduplication, cohort, de-identification, aggregation, trust, monitoring, and analytics capabilities already exist | B9: Moderate confidence | C9: Primary cost-reduction assumption | D9: Base assumption + contingency risk
A10: Existing PHA analytics tool is configured; no new dashboard platform | B10: High confidence | C10: Avoids platform procurement and development | D10: Fixed assumption
A11: PHA receives aggregate and de-identified line-level data | B11: Fixed | C11: Requires two configured output forms | D11: Included
A12: Intermediary executes CMS122; PHA validates results | B12: Provisional | C12: Avoids duplicate measure-engine implementation | D12: Editable assumption
A13: MedicationRequest is required; MedicationDispense only if already available | B13: Fixed | C13: Avoids new pharmacy/payer connection in base | D13: Base scope / add-on if needed
A14: Two remediation cycles are sufficient | B14: Moderate confidence | C14: Caps vendor and participant rework | D14: Base input + per-cycle sensitivity
A15: Participant direct costs and indirect costs are fully reimbursed | B15: Fixed | C15: Increases total to full participant economic cost | D15: Included
A16: NP/prime administration and post-pilot operations are excluded | B16: Fixed | C16: Keeps estimate site-focused and time-limited | D16: Exclusion
A18: Highest-impact unresolved or variable items
A19: Item | B19: Provisional Assumption | C19: Risk if Different | D19: Model Handling
A20: Formal security authorization | B20: No new ATO or penetration test | C20: Material documentation, testing, and schedule increase | D20: Contingency / optional sensitivity
A21: Trust acceptance thresholds | B21: Feasibility-oriented; critical errors resolved, known completeness gaps documented | C21: Stricter thresholds add remediation cycles | D21: Editable assumption
A22: Existing environment availability | B22: Existing test/UAT/production capacity is sufficient | C22: New environments add cloud, deployment, and security costs | D22: Contingency risk
A23: HCCN ability to serve non-FQHC providers | B23: Legally and technically feasible in Scenario 3 | C23: Scenario 3 may need another intermediary or reduced scope | D23: Scenario risk
A24: Broad care-cascade data completeness | B24: Enough existing data to test feasibility | C24: May require added sources or produce limited findings | D24: Contingency risk / limitation
A25: Participant indirect rates | B25: Organization-specific actual rates | C25: Large effect on topline cost | D25: Editable participant inputs in cost build-up
A28: Cost Model Inputs
A29: Blue font / yellow fill = editable provisional input
A30: Input ID | B30: Input | C30: Low | D30: Base | E30: High | F30: Unit | G30: Cost Model Use
A31: IN-01 | B31: Funded pilot sites | C31: 1 | D31: 1 | E31: 1 | F31: sites | G31: Direct formula input
A32: IN-02 | B32: FQHCs | C32: 5 | D32: 10 | E32: 20 | F32: organizations | G32: Direct formula input
A33: IN-03 | B33: Other healthcare organizations | C33: 1 | D33: 2 | E33: 5 | F33: organizations | G33: Direct formula input
A34: IN-04 | B34: All provider organizations | C34: 6 | D34: 12 | E34: 25 | F34: organizations | G34: Derived total; direct formula input
A35: IN-05 | B35: Source configurations | C35: 3 | D35: 5 | E35: 8 | F35: configurations | G35: Direct formula input
A36: IN-06 | B36: Shared FQHC configurations | C36: 1 | D36: 2 | E36: 4 | F36: configurations | G36: Direct formula input
A37: IN-07 | B37: Production interfaces used by selected scenario | C37: =IF(LEFT('Scenario Definitions'!$C$5,1)="1",$C$66,IF(LEFT('Scenario Definitions'!$C$5,1)="2",$C$65,0)) -> 3 | D37: =IF(LEFT('Scenario Definitions'!$C$5,1)="1",$D$66,IF(LEFT('Scenario Definitions'!$C$5,1)="2",$D$65,0)) -> 3 | E37: =IF(LEFT('Scenario Definitions'!$C$5,1)="1",$E$66,IF(LEFT('Scenario Definitions'!$C$5,1)="2",$E$65,0)) -> 5 | F37: interfaces | G37: Scenario lookup used by HIE/HDU interface-related WBS rows
A38: IN-08 | B38: HCCN consolidated export | C38: 1 | D38: 1 | E38: 1 | F38: interface | G38: Direct formula input
A39: IN-09 | B39: PHA receiving interface | C39: 1 | D39: 1 | E39: 1 | F39: interface | G39: Direct formula input
A40: IN-10 | B40: Primary DUAs/DSAs | C40: 3 | D40: 3 | E40: 5 | F40: agreements | G40: Direct formula input
A41: IN-11 | B41: HCCN agreement plus member amendments | C41: 6 | D41: 11 | E41: 21 | F41: legal instruments | G41: Direct formula input
A42: IN-12 | B42: Line-level and aggregate outputs | C42: 2 | D42: 2 | E42: 3 | F42: output types | G42: Direct formula input
A43: IN-13 | B43: PHA surveillance outputs | C43: 1 | D43: 1 | E43: 2 | F43: outputs | G43: Direct formula input
A44: IN-14 | B44: CMS122 measures | C44: 1 | D44: 1 | E44: 2 | F44: measures | G44: Direct formula input
A45: IN-15 | B45: Selected clinical scope | C45: 1 | D45: 1 | E45: 1 | F45: scope | G45: Direct formula input
A46: IN-16 | B46: Broad-scope increment trigger | C46: 1 | D46: 1 | E46: 1 | F46: binary trigger | G46: Scenario applicability trigger
A47: IN-17 | B47: Funded pilot duration | C47: 12 | D47: 12 | E47: 14 | F47: months | G47: Direct formula input
A48: IN-18 | B48: Live exchange period | C48: 6 | D48: 9 | E48: 9 | F48: months | G48: Direct formula input
A49: IN-19 | B49: Operational/status reporting cycles | C49: 9 | D49: 12 | E49: 18 | F49: cycles | G49: Direct formula input
... A69: IN-39 | B69: Shared tools/templates provided | C69: 0.5 | D69: 0.75 | E69: 0.9 | F69: percent | G69: Contextual assumption already reflected in provisional unit hours
A71: Provisional Fully Loaded Labor Rates — Replace with Actual Rates or Validated Benchmarks
A72: Rate ID | B72: Organization Group | C72: Rate Tier | D72: Rate Basis | E72: Direct Rate | F72: Fringe | G72: Overhead/G&A | H72: Fee | I72: Fully Loaded Rate | J72: Dollar Year | K72: Confidence
A73: RT-01 | B73: State PHA | C73: Executive | D73: Provisional fully loaded participant cost | E73: 97.4 | F73: 0.3 | G73: 0.18 | H73: 0 | I73: 150 | J73: 2026 | K73: Low
A74: RT-02 | B74: State PHA | C74: PM | D74: Provisional fully loaded participant cost | E74: 77.92 | F74: 0.3 | G74: 0.18 | H74: 0 | I74: 120 | J74: 2026 | K74: Low
A75: RT-03 | B75: State PHA | C75: SME | D75: Provisional fully loaded participant cost | E75: 81.17 | F75: 0.3 | G75: 0.18 | H75: 0 | I75: 125 | J75: 2026 | K75: Low
A76: RT-04 | B76: State PHA | C76: Technical | D76: Provisional fully loaded participant cost | E76: 87.66 | F76: 0.3 | G76: 0.18 | H76: 0 | I76: 135 | J76: 2026 | K76: Low
A77: RT-05 | B77: State PHA | C77: Analyst | D77: Provisional fully loaded participant cost | E77: 61.69 | F77: 0.3 | G77: 0.18 | H77: 0 | I77: 95 | J77: 2026 | K77: Low
A78: RT-06 | B78: State PHA | C78: Legal/Security | D78: Provisional fully loaded participant cost | E78: 116.88 | F78: 0.3 | G78: 0.18 | H78: 0 | I78: 180 | J78: 2026 | K78: Low
A79: RT-07 | B79: State PHA | C79: Operations | D79: Provisional fully loaded participant cost | E79: 55.19 | F79: 0.3 | G79: 0.18 | H79: 0 | I79: 85 | J79: 2026 | K79: Low
A80: RT-08 | B80: HIE/HDU Intermediary | C80: Executive | D80: Provisional fully loaded participant cost | E80: 113.64 | F80: 0.3 | G80: 0.18 | H80: 0.04 | I80: 175 | J80: 2026 | K80: Low
A81: RT-09 | B81: HIE/HDU Intermediary | C81: PM | D81: Provisional fully loaded participant cost | E81: 94.16 | F81: 0.3 | G81: 0.18 | H81: 0.04 | I81: 145 | J81: 2026 | K81: Low
A82: RT-10 | B82: HIE/HDU Intermediary | C82: SME | D82: Provisional fully loaded participant cost | E82: 103.9 | F82: 0.3 | G82: 0.18 | H82: 0.04 | I82: 160 | J82: 2026 | K82: Low
A83: RT-11 | B83: HIE/HDU Intermediary | C83: Technical | D83: Provisional fully loaded participant cost | E83: 107.14 | F83: 0.3 | G83: 0.18 | H83: 0.04 | I83: 165 | J83: 2026 | K83: Low
A84: RT-12 | B84: HIE/HDU Intermediary | C84: Analyst | D84: Provisional fully loaded participant cost | E84: 77.92 | F84: 0.3 | G84: 0.18 | H84: 0.04 | I84: 120 | J84: 2026 | K84: Low
... A100: RT-28 | B100: Healthcare Organizations & FQHCs | C100: Operations | D100: Provisional fully loaded participant cost | E100: 55.19 | F100: 0.3 | G100: 0.18 | H100: 0 | I100: 85 | J100: 2026 | K100: Low
A103: Organization Group | B103: Indirect Rate | C103: Basis | D103: Confidence | E103: Notes
A104: State PHA | B104: 0.25 | C104: Applied to direct labor only | D104: Low | E104: Provisional; replace with approved rate
A105: HIE/HDU Intermediary | B105: 0.35 | C105: Applied to direct labor only | D105: Low | E105: Provisional; replace with approved rate
A106: HCCN | B106: 0.3 | C106: Applied to direct labor only | D106: Low | E106: Provisional; replace with approved rate
A107: Healthcare Organizations & FQHCs | B107: 0.25 | C107: Applied to direct labor only | D107: Low | E107: Provisional; replace with approved rate

Sheet Cost Build-Up
A1: Stage 3 Costable Activity Register
A2: This sheet decomposes the controlling Work Breakdown into activities with distinct cost ownership, scaling logic, scenario applicability, labor mix, non-labor inputs, estimating method, assumptions, and risks.
A4: WBS ID | B4: Parent WBS ID | C4: Organization Group | D4: Lifecycle Workstream | E4: Work Package | F4: Costable Activity | G4: Description | H4: Output or Completion Condition | I4: Accountable Organization | J4: Performing Party | K4: Supporting Parties | L4: Cost-Bearing Party | M4: Funded or In Kind | N4: Scenario Applicability | O4: Cost Model Treatment | P4: Scaling Classification | Q4: Scaling Unit | R4: Quantity Input ID | S4: Formula Type | T4: Lead Labor Category | U4: Supporting Labor Categories | V4: Participant Labor | W4: Vendor Labor | X4: Reviewer or Approver | Y4: Non-Labor Inputs | Z4: Estimating Method | AA4: Benchmark ID | AB4: Complexity Level | AC4: Assumption IDs | AD4: Risk IDs | AE4: Include in Selected Scenario | AF4: Low Quantity | AG4: Base Quantity | AH4: High Quantity | AI4: Low Fixed Hours | AJ4: Base Fixed Hours | AK4: High Fixed Hours | AL4: Low Hours per Unit | AM4: Base Hours per Unit | AN4: High Hours per Unit | AO4: Low Total Hours | AP4: Base Total Hours | AQ4: High Total Hours | AR4: Rate ID | AS4: Loaded Rate | AT4: Low Labor Cost | AU4: Base Labor Cost | AV4: High Labor Cost | AW4: Low Non-Labor Cost | AX4: Base Non-Labor Cost | AY4: High Non-Labor Cost | AZ4: Indirect Rate | BA4: Low Indirect Cost | BB4: Base Indirect Cost | BC4: High Indirect Cost | BD4: Contingency Eligible | BE4: Low Contingency | BF4: Base Contingency | BG4: High Contingency | BH4: Low Total Cost | BI4: Base Total Cost | BJ4: High Total Cost | BK4: BOE Status | BL4: Validation Status | BM4: Source ID | BN4: Adjustment / Notes | BO4: Include 1A | BP4: Include 1B | BQ4: Include 2A | BR4: Include 2B | BS4: Include 3A | BT4: Include 3B | BU4: 1A Low Total | BV4: 1A Base Total | BW4: 1A High Total | BX4: 1B Low Total | BY4: 1B Base Total | BZ4: 1B High Total | CA4: 2A Low Total | CB4: 2A Base Total | CC4: 2A High Total | CD4: 2B Low Total | CE4: 2B Base Total | CF4: 2B High Total | CG4: 3A Low Total | CH4: 3A Base Total | CI4: 3A High Total | CJ4: 3B Low Total | CK4: 3B Base Total | CL4: 3B High Total
A5: WBS-01.01.01 | B5: WBS-01.01 | C5: State PHA | D5: Implementation management | E5: Implementation planning | F5: Develop funded implementation plan | G5: Translate the approved pre-award charter into workstreams, activities, owners, milestones, dependencies, and acceptance gates. | H5: Approved implementation plan with traceability to charter decisions | I5: PHA | J5: PHA project team | K5: Intermediary; HCCN; providers | L5: PHA | M5: Funded | N5: 1A, 1B, 2A, 2B, 3A, 3B | O5: Base common | P5: Fixed per site | Q5: pilot site | R5: IN-01 | S5: Fixed hours | T5: Project manager | U5: Program director; business analyst; project coordinator | V5: PHA staff | W5: None | X5: Pilot governance body | Y5: Travel only if workshop is in person | Z5: Bottom-up labor estimate | AA5: BM-01 | AB5: Moderate | AC5: A01; A12; A13 | AD5: RD-13 | AE5: =IF(ISNUMBER(SEARCH('Scenario Definitions'!$C$5,N5)),1,0) -> 1 | AF5: =IFERROR(VLOOKUP(R5,'Assumptions & Inputs'!$A$31:$F$69,3,FALSE),0) -> 1 | AG5: =IFERROR(VLOOKUP(R5,'Assumptions & Inputs'!$A$31:$F$69,4,FALSE),0) -> 1 | AH5: =IFERROR(VLOOKUP(R5,'Assumptions & Inputs'!$A$31:$F$69,5,FALSE),0) -> 1 | AI5: 90 | AJ5: 120 | AK5: 180 | AL5: 0 | AM5: 0 | AN5: 0 | AO5: =AI5+(AF5*AL5) -> 90 | AP5: =AJ5+(AG5*AM5) -> 120 | AQ5: =AK5+(AH5*AN5) -> 180 | AR5: RT-02 | AS5: =IFERROR(VLOOKUP(AR5,'Assumptions & Inputs'!$A$73:$I$100,9,FALSE),0) -> 120 | AT5: =AO5*AS5 -> 10800 | AU5: =AP5*AS5 -> 14400 | AV5: =AQ5*AS5 -> 21600 | AW5: 3000 | AX5: 8000 | AY5: 18000 | AZ5: =IFERROR(VLOOKUP(C5,'Assumptions & Inputs'!$A$104:$B$107,2,FALSE),0) -> 0.25 | BA5: =AT5*AZ5 -> 2700 | BB5: =AU5*AZ5 -> 3600 | BC5: =AV5*AZ5 -> 5400 | BD5: Yes | BE5: =IF(BD5="Yes",(AT5+AW5)*VLOOKUP("IN-34",'Assumptions & Inputs'!$A$31:$F$69,3,FALSE),0) -> 690 | BF5: =IF(BD5="Yes",(AU5+AX5)*VLOOKUP("IN-34",'Assumptions & Inputs'!$A$31:$F$69,4,FALSE),0) -> 1680 | BG5: =IF(BD5="Yes",(AV5+AY5)*VLOOKUP("IN-34",'Assumptions & Inputs'!$A$31:$F$69,5,FALSE),0) -> 5940 | BH5: =AT5+AW5+BA5+BE5 -> 17190 | BI5: =AU5+AX5+BB5+BF5 -> 27680 | BJ5: =AV5+AY5+BC5+BG5 -> 50940 | BK5: Provisional — expert judgment | BL5: Pending participant validation | BM5: BM-01 | BN5: Provisional Stage 4 assumption; replace with actual rate, quote, or validated benchmark where available. | BO5: =IF(ISNUMBER(SEARCH("1A",N5)),1,0) -> 1 | BP5: =IF(ISNUMBER(SEARCH("1B",N5)),1,0) -> 1 | BQ5: =IF(ISNUMBER(SEARCH("2A",N5)),1,0) -> 1 | BR5: =IF(ISNUMBER(SEARCH("2B",N5)),1,0) -> 1 | BS5: =IF(ISNUMBER(SEARCH("3A",N5)),1,0) -> 1 | BT5: =IF(ISNUMBER(SEARCH("3B",N5)),1,0) -> 1 | BU5: =IF(BO5=1,((AI5+(IF(R5="IN-07",'Assumptions & Inputs'!$C$66,AF5))*AL5)*AS5)+AW5+(((AI5+(IF(R5="IN-07",'Assumptions & Inputs'!$C$66,AF5))*AL5)*AS5)*AZ5)+IF(BD5="Yes",(((AI5+(IF(R5="IN-07",'Assumptions & Inputs'!$C$66,AF5))*AL5)*AS5)+AW5)*VLOOKUP("IN-34",'Assumptions & Inputs'!$A$31:$F$69,3,FALSE),0),0) -> 17190 | BV5: =IF(BO5=1,((AJ5+(IF(R5="IN-07",'Assumptions & Inputs'!$D$66,AG5))*AM5)*AS5)+AX5+(((AJ5+(IF(R5="IN-07",'Assumptions & Inputs'!$D$66,AG5))*AM5)*AS5)*AZ5)+IF(BD5="Yes",(((AJ5+(IF(R5="IN-07",'Assumptions & Inputs'!$D$66,AG5))*AM5)*AS5)+AX5)*VLOOKUP("IN-34",'Assumptions & Inputs'!$A$31:$F$69,4,FALSE),0),0) -> 27680 | BW5: =IF(BO5=1,((AK5+(IF(R5="IN-07",'Assumptions & Inputs'!$E$66,AH5))*AN5)*AS5)+AY5+(((AK5+(IF(R5="IN-07",'Assumptions & Inputs'!$E$66,AH5))*AN5)*AS5)*AZ5)+IF(BD5="Yes",(((AK5+(IF(R5="IN-07",'Assumptions & Inputs'!$E$66,AH5))*AN5)*AS5)+AY5)*VLOOKUP("IN-34",'Assumptions & Inputs'!$A$31:$F$69,5,FALSE),0),0) -> 50940 | BX5: =IF(BP5=1,((AI5+(IF(R5="IN-07",'Assumptions & Inputs'!$C$66,AF5))*AL5)*AS5)+AW5+(((AI5+(IF(R5="IN-07",'Assumptions & Inputs'!$C$66,AF5))*AL5)*AS5)*AZ5)+IF(BD5="Yes",(((AI5+(IF(R5="IN-07",'Assumptions & Inputs'!$C$66,AF5))*AL5)*AS5)+AW5)*VLOOKUP("IN-34",'Assumptions & Inputs'!$A$31:$F$69,3,FALSE),0),0) -> 17190 | BY5: =IF(BP5=1,((AJ5+(IF(R5="IN-07",'Assumptions & Inputs'!$D$66,AG5))*AM5)*AS5)+AX5+(((AJ5+(IF(R5="IN-07",'Assumptions & Inputs'!$D$66,AG5))*AM5)*AS5)*AZ5)+IF(BD5="Yes",(((AJ5+(IF(R5="IN-07",'Assumptions & Inputs'!$D$66,AG5))*AM5)*AS5)+AX5)*VLOOKUP("IN-34",'Assumptions & Inputs'!$A$31:$F$69,4,FALSE),0),0) -> 27680 | BZ5: =IF(BP5=1,((AK5+(IF(R5="IN-07",'Assumptions & Inputs'!$E$66,AH5))*AN5)*AS5)+AY5+(((AK5+(IF(R5="IN-07",'Assumptions & Inputs'!$E$66,AH5))*AN5)*AS5)*AZ5)+IF(BD5="Yes",(((AK5+(IF(R5="IN-07",'Assumptions & Inputs'!$E$66,AH5))*AN5)*AS5)+AY5)*VLOOKUP("IN-34",'Assumptions & Inputs'!$A$31:$F$69,5,FALSE),0),0) -> 50940 | CA5: =IF(BQ5=1,((AI5+(IF(R5="IN-07",'Assumptions & Inputs'!$C$65,AF5))*AL5)*AS5)+AW5+(((AI5+(IF(R5="IN-07",'Assumptions & Inputs'!$C$65,AF5))*AL5)*AS5)*AZ5)+IF(BD5="Yes",(((AI5+(IF(R5="IN-07",'Assumptions & Inputs'!$C$65,AF5))*AL5)*AS5)+AW5)*VLOOKUP("IN-34",'Assumptions & Inputs'!$A$31:$F$69,3,FALSE),0),0) -> 17190 | CB5: =IF(BQ5=1,((AJ5+(IF(R5="IN-07",'Assumptions & Inputs'!$D$65,AG5))*AM5)*AS5)+AX5+(((AJ5+(IF(R5="IN-07",'Assumptions & Inputs'!$D$65,AG5))*AM5)*AS5)*AZ5)+IF(BD5="Yes",(((AJ5+(IF(R5="IN-07",'Assumptions & Inputs'!$D$65,AG5))*AM5)*AS5)+AX5)*VLOOKUP("IN-34",'Assumptions & Inputs'!$A$31:$F$69,4,FALSE),0),0) -> 27680 | CC5: =IF(BQ5=1,((AK5+(IF(R5="IN-07",'Assumptions & Inputs'!$E$65,AH5))*AN5)*AS5)+AY5+(((AK5+(IF(R5="IN-07",'Assumptions & Inputs'!$E$65,AH5))*AN5)*AS5)*AZ5)+IF(BD5="Yes",(((AK5+(IF(R5="IN-07",'Assumptions & Inputs'!$E$65,AH5))*AN5)*AS5)+AY5)*VLOOKUP("IN-34",'Assumptions & Inputs'!$A$31:$F$69,5,FALSE),0),0) -> 50940 | CD5: =IF(BR5=1,((AI5+(IF(R5="IN-07",'Assumptions & Inputs'!$C$65,AF5))*AL5)*AS5)+AW5+(((AI5+(IF(R5="IN-07",'Assumptions & Inputs'!$C$65,AF5))*AL5)*AS5)*AZ5)+IF(BD5="Yes",(((AI5+(IF(R5="IN-07",'Assumptions & Inputs'!$C$65,AF5))*AL5)*AS5)+AW5)*VLOOKUP("IN-34",'Assumptions & Inputs'!$A$31:$F$69,3,FALSE),0),0) -> 17190 | CE5: =IF(BR5=1,((AJ5+(IF(R5="IN-07",'Assumptions & Inputs'!$D$65,AG5))*AM5)*AS5)+AX5+(((AJ5+(IF(R5="IN-07",'Assumptions & Inputs'!$D$65,AG5))*AM5)*AS5)*AZ5)+IF(BD5="Yes",(((AJ5+(IF(R5="IN-07",'Assumptions & Inputs'!$D$65,AG5))*AM5)*AS5)+AX5)*VLOOKUP("IN-34",'Assumptions & Inputs'!$A$31:$F$69,4,FALSE),0),0) -> 27680 | CF5: =IF(BR5=1,((AK5+(IF(R5="IN-07",'Assumptions & Inputs'!$E$65,AH5))*AN5)*AS5)+AY5+(((AK5+(IF(R5="IN-07",'Assumptions & Inputs'!$E$65,AH5))*AN5)*AS5)*AZ5)+IF(BD5="Yes",(((AK5+(IF(R5="IN-07",'Assumptions & Inputs'!$E$65,AH5))*AN5)*AS5)+AY5)*VLOOKUP("IN-34",'Assumptions & Inputs'!$A$31:$F$69,5,FALSE),0),0) -> 50940 | CG5: =IF(BS5=1,((AI5+(IF(R5="IN-07",0,AF5))*AL5)*AS5)+AW5+(((AI5+(IF(R5="IN-07",0,AF5))*AL5)*AS5)*AZ5)+IF(BD5="Yes",(((AI5+(IF(R5="IN-07",0,AF5))*AL5)*AS5)+AW5)*VLOOKUP("IN-34",'Assumptions & Inputs'!$A$31:$F$69,3,FALSE),0),0) -> 17190 | CH5: =IF(BS5=1,((AJ5+(IF(R5="IN-07",0,AG5))*AM5)*AS5)+AX5+(((AJ5+(IF(R5="IN-07",0,AG5))*AM5)*AS5)*AZ5)+IF(BD5="Yes",(((AJ5+(IF(R5="IN-07",0,AG5))*AM5)*AS5)+AX5)*VLOOKUP("IN-34",'Assumptions & Inputs'!$A$31:$F$69,4,FALSE),0),0) -> 27680 | CI5: =IF(BS5=1,((AK5+(IF(R5="IN-07",0,AH5))*AN5)*AS5)+AY5+(((AK5+(IF(R5="IN-07",0,AH5))*AN5)*AS5)*AZ5)+IF(BD5="Yes",(((AK5+(IF(R5="IN-07",0,AH5))*AN5)*AS5)+AY5)*VLOOKUP("IN-34",'Assumptions & Inputs'!$A$31:$F$69,5,FALSE),0),0) -> 50940 | CJ5: =IF(BT5=1,((AI5+(IF(R5="IN-07",0,AF5))*AL5)*AS5)+AW5+(((AI5+(IF(R5="IN-07",0,AF5))*AL5)*AS5)*AZ5)+IF(BD5="Yes",(((AI5+(IF(R5="IN-07",0,AF5))*AL5)*AS5)+AW5)*VLOOKUP("IN-34",'Assumptions & Inputs'!$A$31:$F$69,3,FALSE),0),0) -> 17190 | CK5: =IF(BT5=1,((AJ5+(IF(R5="IN-07",0,AG5))*AM5)*AS5)+AX5+(((AJ5+(IF(R5="IN-07",0,AG5))*AM5)*AS5)*AZ5)+IF(BD5="Yes",(((AJ5+(IF(R5="IN-07",0,AG5))*AM5)*AS5)+AX5)*VLOOKUP("IN-34",'Assumptions & Inputs'!$A$31:$F$69,4,FALSE),0),0) -> 27680 | CL5: =IF(BT5=1,((AK5+(IF(R5="IN-07",0,AH5))*AN5)*AS5)+AY5+(((AK5+(IF(R5="IN-07",0,AH5))*AN5)*AS5)*AZ5)+IF(BD5="Yes",(((AK5+(IF(R5="IN-07",0,AH5))*AN5)*AS5)+AY5)*VLOOKUP("IN-34",'Assumptions & Inputs'!$A$31:$F$69,5,FALSE),0),0) -> 50940
A6: WBS-01.01.02 | B6: WBS-01.01 | C6: State PHA | D6: Implementation management | E6: Implementation planning | F6: Maintain schedule, risks, decisions, and status reporting | G6: Operate the project-control cadence throughout implementation and pilot operations. | H6: Current schedule, RAID log, decision log, and monthly status reports | I6: PHA | J6: PHA project team | K6: Intermediary; HCCN | L6: PHA | M6: Funded | N6: 1A, 1B, 2A, 2B, 3A, 3B | O6: Base common | P6: Recurring | Q6: project month | R6: IN-17 | S6: Monthly hours × operating months | T6: Project manager | U6: Project coordinator; program director | V6: PHA staff | W6: None | X6: Pilot governance body | Y6: Meeting and travel ODCs | Z6: Bottom-up labor estimate | AA6: BM-01 | AB6: Moderate | AC6: A64; A69 | AD6: RD-13 | AE6: =IF(ISNUMBER(SEARCH('Scenario Definitions'!$C$5,N6)),1,0) -> 1 | AF6: =IFERROR(VLOOKUP(R6,'Assumptions & Inputs'!$A$31:$F$69,3,FALSE),0) -> 12 | AG6: =IFERROR(VLOOKUP(R6,'Assumptions & Inputs'!$A$31:$F$69,4,FALSE),0) -> 12 | AH6: =IFERROR(VLOOKUP(R6,'Assumptions & Inputs'!$A$31:$F$69,5,FALSE),0) -> 14 | AI6: 0 | AJ6: 0 | AK6: 0 | AL6: 24 | AM6: 32 | AN6: 48 | AO6: =AI6+(AF6*AL6) -> 288 | AP6: =AJ6+(AG6*AM6) -> 384 | AQ6: =AK6+(AH6*AN6) -> 672 | AR6: RT-02 | AS6: =IFERROR(VLOOKUP(AR6,'Assumptions & Inputs'!$A$73:$I$100,9,FALSE),0) -> 120 | AT6: =AO6*AS6 -> 34560 | AU6: =AP6*AS6 -> 46080 | AV6: =AQ6*AS6 -> 80640 | AW6: 2000 | AX6: 5000 | AY6: 12000 | AZ6: =IFERROR(VLOOKUP(C6,'Assumptions & Inputs'!$A$104:$B$107,2,FALSE),0) -> 0.25 | BA6: =AT6*AZ6 -> 8640 | BB6: =AU6*AZ6 -> 11520 | BC6: =AV6*AZ6 -> 20160 | BD6: Yes | BE6: =IF(BD6="Yes",(AT6+AW6)*VLOOKUP("IN-34",'Assumptions & Inputs'!$A$31:$F$69,3,FALSE),0) -> 1828 | BF6: =IF(BD6="Yes",(AU6+AX6)*VLOOKUP("IN-34",'Assumptions & Inputs'!$A$31:$F$69,4,FALSE),0) -> 3831 | BG6: =IF(BD6="Yes",(AV6+AY6)*VLOOKUP("IN-34",'Assumptions & Inputs'!$A$31:$F$69,5,FALSE),0) -> 13896 | BH6: =AT6+AW6+BA6+BE6 -> 47028 | BI6: =AU6+AX6+BB6+BF6 -> 66431 | BJ6: =AV6+AY6+BC6+BG6 -> 126696 | BK6: Provisional — expert judgment | BL6: Pending participant validation | BM6: BM-01 | BN6: Provisional Stage 4 assumption; replace with actual rate, quote, or validated benchmark where available. | BO6: =IF(ISNUMBER(SEARCH("1A",N6)),1,0) -> 1 | BP6: =IF(ISNUMBER(SEARCH("1B",N6)),1,0) -> 1 | BQ6: =IF(ISNUMBER(SEARCH("2A",N6)),1,0) -> 1 | BR6: =IF(ISNUMBER(SEARCH("2B",N6)),1,0) -> 1 | BS6: =IF(ISNUMBER(SEARCH("3A",N6)),1,0) -> 1 | BT6: =IF(ISNUMBER(SEARCH("3B",N6)),1,0) -> 1 | BU6: =IF(BO6=1,((AI6+(IF(R6="IN-07",'Assumptions & Inputs'!$C$66,AF6))*AL6)*AS6)+AW6+(((AI6+(IF(R6="IN-07",'Assumptions & Inputs'!$C$66,AF6))*AL6)*AS6)*AZ6)+IF(BD6="Yes",(((AI6+(IF(R6="IN-07",'Assumptions & Inputs'!$C$66,AF6))*AL6)*AS6)+AW6)*VLOOKUP("IN-34",'Assumptions & Inputs'!$A$31:$F$69,3,FALSE),0),0) -> 47028 | BV6: =IF(BO6=1,((AJ6+(IF(R6="IN-07",'Assumptions & Inputs'!$D$66,AG6))*AM6)*AS6)+AX6+(((AJ6+(IF(R6="IN-07",'Assumptions & Inputs'!$D$66,AG6))*AM6)*AS6)*AZ6)+IF(BD6="Yes",(((AJ6+(IF(R6="IN-07",'Assumptions & Inputs'!$D$66,AG6))*AM6)*AS6)+AX6)*VLOOKUP("IN-34",'Assumptions & Inputs'!$A$31:$F$69,4,FALSE),0),0) -> 66431 | BW6: =IF(BO6=1,((AK6+(IF(R6="IN-07",'Assumptions & Inputs'!$E$66,AH6))*AN6)*AS6)+AY6+(((AK6+(IF(R6="IN-07",'Assumptions & Inputs'!$E$66,AH6))*AN6)*AS6)*AZ6)+IF(BD6="Yes",(((AK6+(IF(R6="IN-07",'Assumptions & Inputs'!$E$66,AH6))*AN6)*AS6)+AY6)*VLOOKUP("IN-34",'Assumptions & Inputs'!$A$31:$F$69,5,FALSE),0),0) -> 126696 | BX6: =IF(BP6=1,((AI6+(IF(R6="IN-07",'Assumptions & Inputs'!$C$66,AF6))*AL6)*AS6)+AW6+(((AI6+(IF(R6="IN-07",'Assumptions & Inputs'!$C$66,AF6))*AL6)*AS6)*AZ6)+IF(BD6="Yes",(((AI6+(IF(R6="IN-07",'Assumptions & Inputs'!$C$66,AF6))*AL6)*AS6)+AW6)*VLOOKUP("IN-34",'Assumptions & Inputs'!$A$31:$F$69,3,FALSE),0),0) -> 47028 | BY6: =IF(BP6=1,((AJ6+(IF(R6="IN-07",'Assumptions & Inputs'!$D$66,AG6))*AM6)*AS6)+AX6+(((AJ6+(IF(R6="IN-07",'Assumptions & Inputs'!$D$66,AG6))*AM6)*AS6)*AZ6)+IF(BD6="Yes",(((AJ6+(IF(R6="IN-07",'Assumptions & Inputs'!$D$66,AG6))*AM6)*AS6)+AX6)*VLOOKUP("IN-34",'Assumptions & Inputs'!$A$31:$F$69,4,FALSE),0),0) -> 66431 | BZ6: =IF(BP6=1,((AK6+(IF(R6="IN-07",'Assumptions & Inputs'!$E$66,AH6))*AN6)*AS6)+AY6+(((AK6+(IF(R6="IN-07",'Assumptions & Inputs'!$E$66,AH6))*AN6)*AS6)*AZ6)+IF(BD6="Yes",(((AK6+(IF(R6="IN-07",'Assumptions & Inputs'!$E$66,AH6))*AN6)*AS6)+AY6)*VLOOKUP("IN-34",'Assumptions & Inputs'!$A$31:$F$69,5,FALSE),0),0) -> 126696 | CA6: =IF(BQ6=1,((AI6+(IF(R6="IN-07",'Assumptions & Inputs'!$C$65,AF6))*AL6)*AS6)+AW6+(((AI6+(IF(R6="IN-07",'Assumptions & Inputs'!$C$65,AF6))*AL6)*AS6)*AZ6)+IF(BD6="Yes",(((AI6+(IF(R6="IN-07",'Assumptions & Inputs'!$C$65,AF6))*AL6)*AS6)+AW6)*VLOOKUP("IN-34",'Assumptions & Inputs'!$A$31:$F$69,3,FALSE),0),0) -> 47028 | CB6: =IF(BQ6=1,((AJ6+(IF(R6="IN-07",'Assumptions & Inputs'!$D$65,AG6))*AM6)*AS6)+AX6+(((AJ6+(IF(R6="IN-07",'Assumptions & Inputs'!$D$65,AG6))*AM6)*AS6)*AZ6)+IF(BD6="Yes",(((AJ6+(IF(R6="IN-07",'Assumptions & Inputs'!$D$65,AG6))*AM6)*AS6)+AX6)*VLOOKUP("IN-34",'Assumptions & Inputs'!$A$31:$F$69,4,FALSE),0),0) -> 66431 | CC6: =IF(BQ6=1,((AK6+(IF(R6="IN-07",'Assumptions & Inputs'!$E$65,AH6))*AN6)*AS6)+AY6+(((AK6+(IF(R6="IN-07",'Assumptions & Inputs'!$E$65,AH6))*AN6)*AS6)*AZ6)+IF(BD6="Yes",(((AK6+(IF(R6="IN-07",'Assumptions & Inputs'!$E$65,AH6))*AN6)*AS6)+AY6)*VLOOKUP("IN-34",'Assumptions & Inputs'!$A$31:$F$69,5,FALSE),0),0) -> 126696 | CD6: =IF(BR6=1,((AI6+(IF(R6="IN-07",'Assumptions & Inputs'!$C$65,AF6))*AL6)*AS6)+AW6+(((AI6+(IF(R6="IN-07",'Assumptions & Inputs'!$C$65,AF6))*AL6)*AS6)*AZ6)+IF(BD6="Yes",(((AI6+(IF(R6="IN-07",'Assumptions & Inputs'!$C$65,AF6))*AL6)*AS6)+AW6)*VLOOKUP("IN-34",'Assumptions & Inputs'!$A$31:$F$69,3,FALSE),0),0) -> 47028 | CE6: =IF(BR6=1,((AJ6+(IF(R6="IN-07",'Assumptions & Inputs'!$D$65,AG6))*AM6)*AS6)+AX6+(((AJ6+(IF(R6="IN-07",'Assumptions & Inputs'!$D$65,AG6))*AM6)*AS6)*AZ6)+IF(BD6="Yes",(((AJ6+(IF(R6="IN-07",'Assumptions & Inputs'!$D$65,AG6))*AM6)*AS6)+AX6)*VLOOKUP("IN-34",'Assumptions & Inputs'!$A$31:$F$69,4,FALSE),0),0) -> 66431 | CF6: =IF(BR6=1,((AK6+(IF(R6="IN-07",'Assumptions & Inputs'!$E$65,AH6))*AN6)*AS6)+AY6+(((AK6+(IF(R6="IN-07",'Assumptions & Inputs'!$E$65,AH6))*AN6)*AS6)*AZ6)+IF(BD6="Yes",(((AK6+(IF(R6="IN-07",'Assumptions & Inputs'!$E$65,AH6))*AN6)*AS6)+AY6)*VLOOKUP("IN-34",'Assumptions & Inputs'!$A$31:$F$69,5,FALSE),0),0) -> 126696 | CG6: =IF(BS6=1,((AI6+(IF(R6="IN-07",0,AF6))*AL6)*AS6)+AW6+(((AI6+(IF(R6="IN-07",0,AF6))*AL6)*AS6)*AZ6)+IF(BD6="Yes",(((AI6+(IF(R6="IN-07",0,AF6))*AL6)*AS6)+AW6)*VLOOKUP("IN-34",'Assumptions & Inputs'!$A$31:$F$69,3,FALSE),0),0) -> 47028 | CH6: =IF(BS6=1,((AJ6+(IF(R6="IN-07",0,AG6))*AM6)*AS6)+AX6+(((AJ6+(IF(R6="IN-07",0,AG6))*AM6)*AS6)*AZ6)+IF(BD6="Yes",(((AJ6+(IF(R6="IN-07",0,AG6))*AM6)*AS6)+AX6)*VLOOKUP("IN-34",'Assumptions & Inputs'!$A$31:$F$69,4,FALSE),0),0) -> 66431 | CI6: =IF(BS6=1,((AK6+(IF(R6="IN-07",0,AH6))*AN6)*AS6)+AY6+(((AK6+(IF(R6="IN-07",0,AH6))*AN6)*AS6)*AZ6)+IF(BD6="Yes",(((AK6+(IF(R6="IN-07",0,AH6))*AN6)*AS6)+AY6)*VLOOKUP("IN-34",'Assumptions & Inputs'!$A$31:$F$69,5,FALSE),0),0) -> 126696 | CJ6: =IF(BT6=1,((AI6+(IF(R6="IN-07",0,AF6))*AL6)*AS6)+AW6+(((AI6+(IF(R6="IN-07",0,AF6))*AL6)*AS6)*AZ6)+IF(BD6="Yes",(((AI6+(IF(R6="IN-07",0,AF6))*AL6)*AS6)+AW6)*VLOOKUP("IN-34",'Assumptions & Inputs'!$A$31:$F$69,3,FALSE),0),0) -> 47028 | CK6: =IF(BT6=1,((AJ6+(IF(R6="IN-07",0,AG6))*AM6)*AS6)+AX6+(((AJ6+(IF(R6="IN-07",0,AG6))*AM6)*AS6)*AZ6)+IF(BD6="Yes",(((AJ6+(IF(R6="IN-07",0,AG6))*AM6)*AS6)+AX6)*VLOOKUP("IN-34",'Assumptions & Inputs'!$A$31:$F$69,4,FALSE),0),0) -> 66431 | CL6: =IF(BT6=1,((AK6+(IF(R6="IN-07",0,AH6))*AN6)*AS6)+AY6+(((AK6+(IF(R6="IN-07",0,AH6))*AN6)*AS6)*AZ6)+IF(BD6="Yes",(((AK6+(IF(R6="IN-07",0,AH6))*AN6)*AS6)+AY6)*VLOOKUP("IN-34",'Assumptions & Inputs'!$A$31:$F$69,5,FALSE),0),0) -> 126696
A7: WBS-01.02.01 | B7: WBS-01.02 | C7: State PHA | D7: Implementation management | E7: Stakeholder coordination | F7: Facilitate governance and cross-participant decision meetings | G7: Prepare, conduct, and document site-level governance and implementation sessions. | H7: Meeting materials, decisions, action items, and escalations | I7: PHA | J7: PHA project team | K7: All funded participants | L7: PHA | M7: Funded | N7: 1A, 1B, 2A, 2B, 3A, 3B | O7: Base common | P7: Recurring | Q7: meeting cycle | R7: IN-20 | S7: Reporting cycles × hours per report | T7: Project manager | U7: Program director; project coordinator | V7: PHA and participant staff | W7: None | X7: Executive sponsor | Y7: Meeting and travel expenses | Z7: Bottom-up labor estimate | AA7: BM-01 | AB7: Moderate | AC7: A61; A67 | AD7: RD-21 | AE7: =IF(ISNUMBER(SEARCH('Scenario Definitions'!$C$5,N7)),1,0) -> 1 | AF7: =IFERROR(VLOOKUP(R7,'Assumptions & Inputs'!$A$31:$F$69,3,FALSE),0) -> 9 | AG7: =IFERROR(VLOOKUP(R7,'Assumptions & Inputs'!$A$31:$F$69,4,FALSE),0) -> 12 | AH7: =IFERROR(VLOOKUP(R7,'Assumptions & Inputs'!$A$31:$F$69,5,FALSE),0) -> 18 | AI7: 0 | AJ7: 0 | AK7: 0 | AL7: 7.5 | AM7: 10 | AN7: 15 | AO7: =AI7+(AF7*AL7) -> 67.5 | AP7: =AJ7+(AG7*AM7) -> 120 | AQ7: =AK7+(AH7*AN7) -> 270 | AR7: RT-02 | AS7: =IFERROR(VLOOKUP(AR7,'Assumptions & Inputs'!$A$73:$I$100,9,FALSE),0) -> 120 | AT7: =AO7*AS7 -> 8100 | AU7: =AP7*AS7 -> 14400 | AV7: =AQ7*AS7 -> 32400 | AW7: 0 | AX7: 0 | AY7: 0 | AZ7: =IFERROR(VLOOKUP(C7,'Assumptions & Inputs'!$A$104:$B$107,2,FALSE),0) -> 0.25 | BA7: =AT7*AZ7 -> 2025 | BB7: =AU7*AZ7 -> 3600 | BC7: =AV7*AZ7 -> 8100 | BD7: Yes | BE7: =IF(BD7="Yes",(AT7+AW7)*VLOOKUP("IN-34",'Assumptions & Inputs'!$A$31:$F$69,3,FALSE),0) -> 405 | BF7: =IF(BD7="Yes",(AU7+AX7)*VLOOKUP("IN-34",'Assumptions & Inputs'!$A$31:$F$69,4,FALSE),0) -> 1080 | BG7: =IF(BD7="Yes",(AV7+AY7)*VLOOKUP("IN-34",'Assumptions & Inputs'!$A$31:$F$69,5,FALSE),0) -> 4860 | BH7: =AT7+AW7+BA7+BE7 -> 10530 | BI7: =AU7+AX7+BB7+BF7 -> 19080 | BJ7: =AV7+AY7+BC7+BG7 -> 45360 | BK7: Provisional — expert judgment | BL7: Pending participant validation | BM7: BM-01 | BN7: Provisional Stage 4 assumption; replace with actual rate, quote, or validated benchmark where available. | BO7: =IF(ISNUMBER(SEARCH("1A",N7)),1,0) -> 1 | BP7: =IF(ISNUMBER(SEARCH("1B",N7)),1,0) -> 1 | BQ7: =IF(ISNUMBER(SEARCH("2A",N7)),1,0) -> 1 | BR7: =IF(ISNUMBER(SEARCH("2B",N7)),1,0) -> 1 | BS7: =IF(ISNUMBER(SEARCH("3A",N7)),1,0) -> 1 | BT7: =IF(ISNUMBER(SEARCH("3B",N7)),1,0) -> 1 | BU7: =IF(BO7=1,((AI7+(IF(R7="IN-07",'Assumptions & Inputs'!$C$66,AF7))*AL7)*AS7)+AW7+(((AI7+(IF(R7="IN-07",'Assumptions & Inputs'!$C$66,AF7))*AL7)*AS7)*AZ7)+IF(BD7="Yes",(((AI7+(IF(R7="IN-07",'Assumptions & Inputs'!$C$66,AF7))*AL7)*AS7)+AW7)*VLOOKUP("IN-34",'Assumptions & Inputs'!$A$31:$F$69,3,FALSE),0),0) -> 10530 | BV7: =IF(BO7=1,((AJ7+(IF(R7="IN-07",'Assumptions & Inputs'!$D$66,AG7))*AM7)*AS7)+AX7+(((AJ7+(IF(R7="IN-07",'Assumptions & Inputs'!$D$66,AG7))*AM7)*AS7)*AZ7)+IF(BD7="Yes",(((AJ7+(IF(R7="IN-07",'Assumptions & Inputs'!$D$66,AG7))*AM7)*AS7)+AX7)*VLOOKUP("IN-34",'Assumptions & Inputs'!$A$31:$F$69,4,FALSE),0),0) -> 19080 | BW7: =IF(BO7=1,((AK7+(IF(R7="IN-07",'Assumptions & Inputs'!$E$66,AH7))*AN7)*AS7)+AY7+(((AK7+(IF(R7="IN-07",'Assumptions & Inputs'!$E$66,AH7))*AN7)*AS7)*AZ7)+IF(BD7="Yes",(((AK7+(IF(R7="IN-07",'Assumptions & Inputs'!$E$66,AH7))*AN7)*AS7)+AY7)*VLOOKUP("IN-34",'Assumptions & Inputs'!$A$31:$F$69,5,FALSE),0),0) -> 45360 | BX7: =IF(BP7=1,((AI7+(IF(R7="IN-07",'Assumptions & Inputs'!$C$66,AF7))*AL7)*AS7)+AW7+(((AI7+(IF(R7="IN-07",'Assumptions & Inputs'!$C$66,AF7))*AL7)*AS7)*AZ7)+IF(BD7="Yes",(((AI7+(IF(R7="IN-07",'Assumptions & Inputs'!$C$66,AF7))*AL7)*AS7)+AW7)*VLOOKUP("IN-34",'Assumptions & Inputs'!$A$31:$F$69,3,FALSE),0),0) -> 10530 | BY7: =IF(BP7=1,((AJ7+(IF(R7="IN-07",'Assumptions & Inputs'!$D$66,AG7))*AM7)*AS7)+AX7+(((AJ7+(IF(R7="IN-07",'Assumptions & Inputs'!$D$66,AG7))*AM7)*AS7)*AZ7)+IF(BD7="Yes",(((AJ7+(IF(R7="IN-07",'Assumptions & Inputs'!$D$66,AG7))*AM7)*AS7)+AX7)*VLOOKUP("IN-34",'Assumptions & Inputs'!$A$31:$F$69,4,FALSE),0),0) -> 19080 | BZ7: =IF(BP7=1,((AK7+(IF(R7="IN-07",'Assumptions & Inputs'!$E$66,AH7))*AN7)*AS7)+AY7+(((AK7+(IF(R7="IN-07",'Assumptions & Inputs'!$E$66,AH7))*AN7)*AS7)*AZ7)+IF(BD7="Yes",(((AK7+(IF(R7="IN-07",'Assumptions & Inputs'!$E$66,AH7))*AN7)*AS7)+AY7)*VLOOKUP("IN-34",'Assumptions & Inputs'!$A$31:$F$69,5,FALSE),0),0) -> 45360 | CA7: =IF(BQ7=1,((AI7+(IF(R7="IN-07",'Assumptions & Inputs'!$C$65,AF7))*AL7)*AS7)+AW7+(((AI7+(IF(R7="IN-07",'Assumptions & Inputs'!$C$65,AF7))*AL7)*AS7)*AZ7)+IF(BD7="Yes",(((AI7+(IF(R7="IN-07",'Assumptions & Inputs'!$C$65,AF7))*AL7)*AS7)+AW7)*VLOOKUP("IN-34",'Assumptions & Inputs'!$A$31:$F$69,3,FALSE),0),0) -> 10530 | CB7: =IF(BQ7=1,((AJ7+(IF(R7="IN-07",'Assumptions & Inputs'!$D$65,AG7))*AM7)*AS7)+AX7+(((AJ7+(IF(R7="IN-07",'Assumptions & Inputs'!$D$65,AG7))*AM7)*AS7)*AZ7)+IF(BD7="Yes",(((AJ7+(IF(R7="IN-07",'Assumptions & Inputs'!$D$65,AG7))*AM7)*AS7)+AX7)*VLOOKUP("IN-34",'Assumptions & Inputs'!$A$31:$F$69,4,FALSE),0),0) -> 19080 | CC7: =IF(BQ7=1,((AK7+(IF(R7="IN-07",'Assumptions & Inputs'!$E$65,AH7))*AN7)*AS7)+AY7+(((AK7+(IF(R7="IN-07",'Assumptions & Inputs'!$E$65,AH7))*AN7)*AS7)*AZ7)+IF(BD7="Yes",(((AK7+(IF(R7="IN-07",'Assumptions & Inputs'!$E$65,AH7))*AN7)*AS7)+AY7)*VLOOKUP("IN-34",'Assumptions & Inputs'!$A$31:$F$69,5,FALSE),0),0) -> 45360 | CD7: =IF(BR7=1,((AI7+(IF(R7="IN-07",'Assumptions & Inputs'!$C$65,AF7))*AL7)*AS7)+AW7+(((AI7+(IF(R7="IN-07",'Assumptions & Inputs'!$C$65,AF7))*AL7)*AS7)*AZ7)+IF(BD7="Yes",(((AI7+(IF(R7="IN-07",'Assumptions & Inputs'!$C$65,AF7))*AL7)*AS7)+AW7)*VLOOKUP("IN-34",'Assumptions & Inputs'!$A$31:$F$69,3,FALSE),0),0) -> 10530 | CE7: =IF(BR7=1,((AJ7+(IF(R7="IN-07",'Assumptions & Inputs'!$D$65,AG7))*AM7)*AS7)+AX7+(((AJ7+(IF(R7="IN-07",'Assumptions & Inputs'!$D$65,AG7))*AM7)*AS7)*AZ7)+IF(BD7="Yes",(((AJ7+(IF(R7="IN-07",'Assumptions & Inputs'!$D$65,AG7))*AM7)*AS7)+AX7)*VLOOKUP("IN-34",'Assumptions & Inputs'!$A$31:$F$69,4,FALSE),0),0) -> 19080 | CF7: =IF(BR7=1,((AK7+(IF(R7="IN-07",'Assumptions & Inputs'!$E$65,AH7))*AN7)*AS7)+AY7+(((AK7+(IF(R7="IN-07",'Assumptions & Inputs'!$E$65,AH7))*AN7)*AS7)*AZ7)+IF(BD7="Yes",(((AK7+(IF(R7="IN-07",'Assumptions & Inputs'!$E$65,AH7))*AN7)*AS7)+AY7)*VLOOKUP("IN-34",'Assumptions & Inputs'!$A$31:$F$69,5,FALSE),0),0) -> 45360 | CG7: =IF(BS7=1,((AI7+(IF(R7="IN-07",0,AF7))*AL7)*AS7)+AW7+(((AI7+(IF(R7="IN-07",0,AF7))*AL7)*AS7)*AZ7)+IF(BD7="Yes",(((AI7+(IF(R7="IN-07",0,AF7))*AL7)*AS7)+AW7)*VLOOKUP("IN-34",'Assumptions & Inputs'!$A$31:$F$69,3,FALSE),0),0) -> 10530 | CH7: =IF(BS7=1,((AJ7+(IF(R7="IN-07",0,AG7))*AM7)*AS7)+AX7+(((AJ7+(IF(R7="IN-07",0,AG7))*AM7)*AS7)*AZ7)+IF(BD7="Yes",(((AJ7+(IF(R7="IN-07",0,AG7))*AM7)*AS7)+AX7)*VLOOKUP("IN-34",'Assumptions & Inputs'!$A$31:$F$69,4,FALSE),0),0) -> 19080 | CI7: =IF(BS7=1,((AK7+(IF(R7="IN-07",0,AH7))*AN7)*AS7)+AY7+(((AK7+(IF(R7="IN-07",0,AH7))*AN7)*AS7)*AZ7)+IF(BD7="Yes",(((AK7+(IF(R7="IN-07",0,AH7))*AN7)*AS7)+AY7)*VLOOKUP("IN-34",'Assumptions & Inputs'!$A$31:$F$69,5,FALSE),0),0) -> 45360 | CJ7: =IF(BT7=1,((AI7+(IF(R7="IN-07",0,AF7))*AL7)*AS7)+AW7+(((AI7+(IF(R7="IN-07",0,AF7))*AL7)*AS7)*AZ7)+IF(BD7="Yes",(((AI7+(IF(R7="IN-07",0,AF7))*AL7)*AS7)+AW7)*VLOOKUP("IN-34",'Assumptions & Inputs'!$A$31:$F$69,3,FALSE),0),0) -> 10530 | CK7: =IF(BT7=1,((AJ7+(IF(R7="IN-07",0,AG7))*AM7)*AS7)+AX7+(((AJ7+(IF(R7="IN-07",0,AG7))*AM7)*AS7)*AZ7)+IF(BD7="Yes",(((AJ7+(IF(R7="IN-07",0,AG7))*AM7)*AS7)+AX7)*VLOOKUP("IN-34",'Assumptions & Inputs'!$A$31:$F$69,4,FALSE),0),0) -> 19080 | CL7: =IF(BT7=1,((AK7+(IF(R7="IN-07",0,AH7))*AN7)*AS7)+AY7+(((AK7+(IF(R7="IN-07",0,AH7))*AN7)*AS7)*AZ7)+IF(BD7="Yes",(((AK7+(IF(R7="IN-07",0,AH7))*AN7)*AS7)+AY7)*VLOOKUP("IN-34",'Assumptions & Inputs'!$A$31:$F$69,5,FALSE),0),0) -> 45360
A8: WBS-01.03.01 | B8: WBS-01.03 | C8: State PHA | D8: Governance, legal, privacy, and security | E8: Governance activation | F8: Operationalize governance and decision rights | G8: Activate decision, escalation, change-control, access-approval, and issue-resolution processes already defined in the charter. | H8: Operating governance calendar and decision-rights matrix | I8: PHA | J8: PHA governance lead | K8: Intermediary; HCCN; providers | L8: PHA | M8: Funded | N8: 1A, 1B, 2A, 2B, 3A, 3B | O8: Base common | P8: Fixed per site | Q8: pilot site | R8: IN-01 | S8: Fixed hours | T8: Governance specialist | U8: Project manager; legal counsel; privacy officer | V8: PHA staff | W8: None | X8: Executive sponsor | Y8: None material | Z8: Bottom-up labor estimate | AA8: BM-02 | AB8: Moderate | AC8: A67 | AD8: RD-24 | AE8: =IF(ISNUMBER(SEARCH('Scenario Definitions'!$C$5,N8)),1,0) -> 1 | AF8: =IFERROR(VLOOKUP(R8,'Assumptions & Inputs'!$A$31:$F$69,3,FALSE),0) -> 1 | AG8: =IFERROR(VLOOKUP(R8,'Assumptions & Inputs'!$A$31:$F$69,4,FALSE),0) -> 1 | AH8: =IFERROR(VLOOKUP(R8,'Assumptions & Inputs'!$A$31:$F$69,5,FALSE),0) -> 1 | AI8: 48 | AJ8: 64 | AK8: 96 | AL8: 0 | AM8: 0 | AN8: 0 | AO8: =AI8+(AF8*AL8) -> 48 | AP8: =AJ8+(AG8*AM8) -> 64 | AQ8: =AK8+(AH8*AN8) -> 96 | AR8: RT-05 | AS8: =IFERROR(VLOOKUP(AR8,'Assumptions & Inputs'!$A$73:$I$100,9,FALSE),0) -> 95 | AT8: =AO8*AS8 -> 4560 | AU8: =AP8*AS8 -> 6080 | AV8: =AQ8*AS8 -> 9120 | AW8: 0 | AX8: 0 | AY8: 0 | AZ8: =IFERROR(VLOOKUP(C8,'Assumptions & Inputs'!$A$104:$B$107,2,FALSE),0) -> 0.25 | BA8: =AT8*AZ8 -> 1140 | BB8: =AU8*AZ8 -> 1520 | BC8: =AV8*AZ8 -> 2280 | BD8: Yes | BE8: =IF(BD8="Yes",(AT8+AW8)*VLOOKUP("IN-34",'Assumptions & Inputs'!$A$31:$F$69,3,FALSE),0) -> 228 | BF8: =IF(BD8="Yes",(AU8+AX8)*VLOOKUP("IN-34",'Assumptions & Inputs'!$A$31:$F$69,4,FALSE),0) -> 456 | BG8: =IF(BD8="Yes",(AV8+AY8)*VLOOKUP("IN-34",'Assumptions & Inputs'!$A$31:$F$69,5,FALSE),0) -> 1368 | BH8: =AT8+AW8+BA8+BE8 -> 5928 | BI8: =AU8+AX8+BB8+BF8 -> 8056 | BJ8: =AV8+AY8+BC8+BG8 -> 12768 | BK8: Provisional — expert judgment | BL8: Pending participant validation | BM8: BM-02 | BN8: Provisional Stage 4 assumption; replace with actual rate, quote, or validated benchmark where available. | BO8: =IF(ISNUMBER(SEARCH("1A",N8)),1,0) -> 1 | BP8: =IF(ISNUMBER(SEARCH("1B",N8)),1,0) -> 1 | BQ8: =IF(ISNUMBER(SEARCH("2A",N8)),1,0) -> 1 | BR8: =IF(ISNUMBER(SEARCH("2B",N8)),1,0) -> 1 | BS8: =IF(ISNUMBER(SEARCH("3A",N8)),1,0) -> 1 | BT8: =IF(ISNUMBER(SEARCH("3B",N8)),1,0) -> 1 | BU8: =IF(BO8=1,((AI8+(IF(R8="IN-07",'Assumptions & Inputs'!$C$66,AF8))*AL8)*AS8)+AW8+(((AI8+(IF(R8="IN-07",'Assumptions & Inputs'!$C$66,AF8))*AL8)*AS8)*AZ8)+IF(BD8="Yes",(((AI8+(IF(R8="IN-07",'Assumptions & Inputs'!$C$66,AF8))*AL8)*AS8)+AW8)*VLOOKUP("IN-34",'Assumptions & Inputs'!$A$31:$F$69,3,FALSE),0),0) -> 5928 | BV8: =IF(BO8=1,((AJ8+(IF(R8="IN-07",'Assumptions & Inputs'!$D$66,AG8))*AM8)*AS8)+AX8+(((AJ8+(IF(R8="IN-07",'Assumptions & Inputs'!$D$66,AG8))*AM8)*AS8)*AZ8)+IF(BD8="Yes",(((AJ8+(IF(R8="IN-07",'Assumptions & Inputs'!$D$66,AG8))*AM8)*AS8)+AX8)*VLOOKUP("IN-34",'Assumptions & Inputs'!$A$31:$F$69,4,FALSE),0),0) -> 8056 | BW8: =IF(BO8=1,((AK8+(IF(R8="IN-07",'Assumptions & Inputs'!$E$66,AH8))*AN8)*AS8)+AY8+(((AK8+(IF(R8="IN-07",'Assumptions & Inputs'!$E$66,AH8))*AN8)*AS8)*AZ8)+IF(BD8="Yes",(((AK8+(IF(R8="IN-07",'Assumptions & Inputs'!$E$66,AH8))*AN8)*AS8)+AY8)*VLOOKUP("IN-34",'Assumptions & Inputs'!$A$31:$F$69,5,FALSE),0),0) -> 12768 | BX8: =IF(BP8=1,((AI8+(IF(R8="IN-07",'Assumptions & Inputs'!$C$66,AF8))*AL8)*AS8)+AW8+(((AI8+(IF(R8="IN-07",'Assumptions & Inputs'!$C$66,AF8))*AL8)*AS8)*AZ8)+IF(BD8="Yes",(((AI8+(IF(R8="IN-07",'Assumptions & Inputs'!$C$66,AF8))*AL8)*AS8)+AW8)*VLOOKUP("IN-34",'Assumptions & Inputs'!$A$31:$F$69,3,FALSE),0),0) -> 5928 | BY8: =IF(BP8=1,((AJ8+(IF(R8="IN-07",'Assumptions & Inputs'!$D$66,AG8))*AM8)*AS8)+AX8+(((AJ8+(IF(R8="IN-07",'Assumptions & Inputs'!$D$66,AG8))*AM8)*AS8)*AZ8)+IF(BD8="Yes",(((AJ8+(IF(R8="IN-07",'Assumptions & Inputs'!$D$66,AG8))*AM8)*AS8)+AX8)*VLOOKUP("IN-34",'Assumptions & Inputs'!$A$31:$F$69,4,FALSE),0),0) -> 8056 | BZ8: =IF(BP8=1,((AK8+(IF(R8="IN-07",'Assumptions & Inputs'!$E$66,AH8))*AN8)*AS8)+AY8+(((AK8+(IF(R8="IN-07",'Assumptions & Inputs'!$E$66,AH8))*AN8)*AS8)*AZ8)+IF(BD8="Yes",(((AK8+(IF(R8="IN-07",'Assumptions & Inputs'!$E$66,AH8))*AN8)*AS8)+AY8)*VLOOKUP("IN-34",'Assumptions & Inputs'!$A$31:$F$69,5,FALSE),0),0) -> 12768 | CA8: =IF(BQ8=1,((AI8+(IF(R8="IN-07",'Assumptions & Inputs'!$C$65,AF8))*AL8)*AS8)+AW8+(((AI8+(IF(R8="IN-07",'Assumptions & Inputs'!$C$65,AF8))*AL8)*AS8)*AZ8)+IF(BD8="Yes",(((AI8+(IF(R8="IN-07",'Assumptions & Inputs'!$C$65,AF8))*AL8)*AS8)+AW8)*VLOOKUP("IN-34",'Assumptions & Inputs'!$A$31:$F$69,3,FALSE),0),0) -> 5928 | CB8: =IF(BQ8=1,((AJ8+(IF(R8="IN-07",'Assumptions & Inputs'!$D$65,AG8))*AM8)*AS8)+AX8+(((AJ8+(IF(R8="IN-07",'Assumptions & Inputs'!$D$65,AG8))*AM8)*AS8)*AZ8)+IF(BD8="Yes",(((AJ8+(IF(R8="IN-07",'Assumptions & Inputs'!$D$65,AG8))*AM8)*AS8)+AX8)*VLOOKUP("IN-34",'Assumptions & Inputs'!$A$31:$F$69,4,FALSE),0),0) -> 8056 | CC8: =IF(BQ8=1,((AK8+(IF(R8="IN-07",'Assumptions & Inputs'!$E$65,AH8))*AN8)*AS8)+AY8+(((AK8+(IF(R8="IN-07",'Assumptions & Inputs'!$E$65,AH8))*AN8)*AS8)*AZ8)+IF(BD8="Yes",(((AK8+(IF(R8="IN-07",'Assumptions & Inputs'!$E$65,AH8))*AN8)*AS8)+AY8)*VLOOKUP("IN-34",'Assumptions & Inputs'!$A$31:$F$69,5,FALSE),0),0) -> 12768 | CD8: =IF(BR8=1,((AI8+(IF(R8="IN-07",'Assumptions & Inputs'!$C$65,AF8))*AL8)*AS8)+AW8+(((AI8+(IF(R8="IN-07",'Assumptions & Inputs'!$C$65,AF8))*AL8)*AS8)*AZ8)+IF(BD8="Yes",(((AI8+(IF(R8="IN-07",'Assumptions & Inputs'!$C$65,AF8))*AL8)*AS8)+AW8)*VLOOKUP("IN-34",'Assumptions & Inputs'!$A$31:$F$69,3,FALSE),0),0) -> 5928 | CE8: =IF(BR8=1,((AJ8+(IF(R8="IN-07",'Assumptions & Inputs'!$D$65,AG8))*AM8)*AS8)+AX8+(((AJ8+(IF(R8="IN-07",'Assumptions & Inputs'!$D$65,AG8))*AM8)*AS8)*AZ8)+IF(BD8="Yes",(((AJ8+(IF(R8="IN-07",'Assumptions & Inputs'!$D$65,AG8))*AM8)*AS8)+AX8)*VLOOKUP("IN-34",'Assumptions & Inputs'!$A$31:$F$69,4,FALSE),0),0) -> 8056 | CF8: =IF(BR8=1,((AK8+(IF(R8="IN-07",'Assumptions & Inputs'!$E$65,AH8))*AN8)*AS8)+AY8+(((AK8+(IF(R8="IN-07",'Assumptions & Inputs'!$E$65,AH8))*AN8)*AS8)*AZ8)+IF(BD8="Yes",(((AK8+(IF(R8="IN-07",'Assumptions & Inputs'!$E$65,AH8))*AN8)*AS8)+AY8)*VLOOKUP("IN-34",'Assumptions & Inputs'!$A$31:$F$69,5,FALSE),0),0) -> 12768 | CG8: =IF(BS8=1,((AI8+(IF(R8="IN-07",0,AF8))*AL8)*AS8)+AW8+(((AI8+(IF(R8="IN-07",0,AF8))*AL8)*AS8)*AZ8)+IF(BD8="Yes",(((AI8+(IF(R8="IN-07",0,AF8))*AL8)*AS8)+AW8)*VLOOKUP("IN-34",'Assumptions & Inputs'!$A$31:$F$69,3,FALSE),0),0) -> 5928 | CH8: =IF(BS8=1,((AJ8+(IF(R8="IN-07",0,AG8))*AM8)*AS8)+AX8+(((AJ8+(IF(R8="IN-07",0,AG8))*AM8)*AS8)*AZ8)+IF(BD8="Yes",(((AJ8+(IF(R8="IN-07",0,AG8))*AM8)*AS8)+AX8)*VLOOKUP("IN-34",'Assumptions & Inputs'!$A$31:$F$69,4,FALSE),0),0) -> 8056 | CI8: =IF(BS8=1,((AK8+(IF(R8="IN-07",0,AH8))*AN8)*AS8)+AY8+(((AK8+(IF(R8="IN-07",0,AH8))*AN8)*AS8)*AZ8)+IF(BD8="Yes",(((AK8+(IF(R8="IN-07",0,AH8))*AN8)*AS8)+AY8)*VLOOKUP("IN-34",'Assumptions & Inputs'!$A$31:$F$69,5,FALSE),0),0) -> 12768 | CJ8: =IF(BT8=1,((AI8+(IF(R8="IN-07",0,AF8))*AL8)*AS8)+AW8+(((AI8+(IF(R8="IN-07",0,AF8))*AL8)*AS8)*AZ8)+IF(BD8="Yes",(((AI8+(IF(R8="IN-07",0,AF8))*AL8)*AS8)+AW8)*VLOOKUP("IN-34",'Assumptions & Inputs'!$A$31:$F$69,3,FALSE),0),0) -> 5928 | CK8: =IF(BT8=1,((AJ8+(IF(R8="IN-07",0,AG8))*AM8)*AS8)+AX8+(((AJ8+(IF(R8="IN-07",0,AG8))*AM8)*AS8)*AZ8)+IF(BD8="Yes",(((AJ8+(IF(R8="IN-07",0,AG8))*AM8)*AS8)+AX8)*VLOOKUP("IN-34",'Assumptions & Inputs'!$A$31:$F$69,4,FALSE),0),0) -> 8056 | CL8: =IF(BT8=1,((AK8+(IF(R8="IN-07",0,AH8))*AN8)*AS8)+AY8+(((AK8+(IF(R8="IN-07",0,AH8))*AN8)*AS8)*AZ8)+IF(BD8="Yes",(((AK8+(IF(R8="IN-07",0,AH8))*AN8)*AS8)+AY8)*VLOOKUP("IN-34",'Assumptions & Inputs'!$A$31:$F$69,5,FALSE),0),0) -> 12768
A9: WBS-01.04.01 | B9: WBS-01.04 | C9: State PHA | D9: Governance, legal, privacy, and security | E9: Agreement execution | F9: Coordinate and review primary DUAs/DSAs | G9: Complete site-side review and execution of the HCCN/FQHC agreement and two non-FQHC provider agreements. | H9: Executed primary data-use or data-sharing agreements | I9: PHA | J9: PHA legal/privacy team | K9: Intermediary; HCCN; provider counsel | L9: PHA | M9: Funded | N9: 1A, 1B, 2A, 2B, 3A, 3B | O9: Base common | P9: Variable | Q9: primary agreement | R9: IN-10 | S9: Agreements × hours per agreement | T9: Legal counsel | U9: Privacy specialist; project manager | V9: PHA staff | W9: External counsel if used | X9: Authorized signatory | Y9: External legal services if required | Z9: Bottom-up labor estimate / vendor quote | AA9: BM-03 | AB9: High | AC9: A51; A52 | AD9: RD-10 | AE9: =IF(ISNUMBER(SEARCH('Scenario Definitions'!$C$5,N9)),1,0) -> 1 | AF9: =IFERROR(VLOOKUP(R9,'Assumptions & Inputs'!$A$31:$F$69,3,FALSE),0) -> 3 | AG9: =IFERROR(VLOOKUP(R9,'Assumptions & Inputs'!$A$31:$F$69,4,FALSE),0) -> 3 | AH9: =IFERROR(VLOOKUP(R9,'Assumptions & Inputs'!$A$31:$F$69,5,FALSE),0) -> 5 | AI9: 0 | AJ9: 0 | AK9: 0 | AL9: 20.2 | AM9: 27 | AN9: 40.5 | AO9: =AI9+(AF9*AL9) -> 60.6 | AP9: =AJ9+(AG9*AM9) -> 81 | AQ9: =AK9+(AH9*AN9) -> 202.5 | AR9: RT-06 | AS9: =IFERROR(VLOOKUP(AR9,'Assumptions & Inputs'!$A$73:$I$100,9,FALSE),0) -> 180 | AT9: =AO9*AS9 -> 10908 | AU9: =AP9*AS9 -> 14580 | AV9: =AQ9*AS9 -> 36450 | AW9: 0 | AX9: 0 | AY9: 25000 | AZ9: =IFERROR(VLOOKUP(C9,'Assumptions & Inputs'!$A$104:$B$107,2,FALSE),0) -> 0.25 | BA9: =AT9*AZ9 -> 2727 | BB9: =AU9*AZ9 -> 3645 | BC9: =AV9*AZ9 -> 9112.5 | BD9: Yes | BE9: =IF(BD9="Yes",(AT9+AW9)*VLOOKUP("IN-34",'Assumptions & Inputs'!$A$31:$F$69,3,FALSE),0) -> 545.4 | BF9: =IF(BD9="Yes",(AU9+AX9)*VLOOKUP("IN-34",'Assumptions & Inputs'!$A$31:$F$69,4,FALSE),0) -> 1093.5 | BG9: =IF(BD9="Yes",(AV9+AY9)*VLOOKUP("IN-34",'Assumptions & Inputs'!$A$31:$F$69,5,FALSE),0) -> 9217.5 | BH9: =AT9+AW9+BA9+BE9 -> 14180.4 | BI9: =AU9+AX9+BB9+BF9 -> 19318.5 | BJ9: =AV9+AY9+BC9+BG9 -> 79780 | BK9: Provisional — expert judgment | BL9: Pending participant validation | BM9: BM-03 | BN9: Provisional Stage 4 assumption; replace with actual rate, quote, or validated benchmark where available. | BO9: =IF(ISNUMBER(SEARCH("1A",N9)),1,0) -> 1 | BP9: =IF(ISNUMBER(SEARCH("1B",N9)),1,0) -> 1 | BQ9: =IF(ISNUMBER(SEARCH("2A",N9)),1,0) -> 1 | BR9: =IF(ISNUMBER(SEARCH("2B",N9)),1,0) -> 1 | BS9: =IF(ISNUMBER(SEARCH("3A",N9)),1,0) -> 1 | BT9: =IF(ISNUMBER(SEARCH("3B",N9)),1,0) -> 1 | BU9: =IF(BO9=1,((AI9+(IF(R9="IN-07",'Assumptions & Inputs'!$C$66,AF9))*AL9)*AS9)+AW9+(((AI9+(IF(R9="IN-07",'Assumptions & Inputs'!$C$66,AF9))*AL9)*AS9)*AZ9)+IF(BD9="Yes",(((AI9+(IF(R9="IN-07",'Assumptions & Inputs'!$C$66,AF9))*AL9)*AS9)+AW9)*VLOOKUP("IN-34",'Assumptions & Inputs'!$A$31:$F$69,3,FALSE),0),0) -> 14180.4 | BV9: =IF(BO9=1,((AJ9+(IF(R9="IN-07",'Assumptions & Inputs'!$D$66,AG9))*AM9)*AS9)+AX9+(((AJ9+(IF(R9="IN-07",'Assumptions & Inputs'!$D$66,AG9))*AM9)*AS9)*AZ9)+IF(BD9="Yes",(((AJ9+(IF(R9="IN-07",'Assumptions & Inputs'!$D$66,AG9))*AM9)*AS9)+AX9)*VLOOKUP("IN-34",'Assumptions & Inputs'!$A$31:$F$69,4,FALSE),0),0) -> 19318.5 | BW9: =IF(BO9=1,((AK9+(IF(R9="IN-07",'Assumptions & Inputs'!$E$66,AH9))*AN9)*AS9)+AY9+(((AK9+(IF(R9="IN-07",'Assumptions & Inputs'!$E$66,AH9))*AN9)*AS9)*AZ9)+IF(BD9="Yes",(((AK9+(IF(R9="IN-07",'Assumptions & Inputs'!$E$66,AH9))*AN9)*AS9)+AY9)*VLOOKUP("IN-34",'Assumptions & Inputs'!$A$31:$F$69,5,FALSE),0),0) -> 79780 | BX9: =IF(BP9=1,((AI9+(IF(R9="IN-07",'Assumptions & Inputs'!$C$66,AF9))*AL9)*AS9)+AW9+(((AI9+(IF(R9="IN-07",'Assumptions & Inputs'!$C$66,AF9))*AL9)*AS9)*AZ9)+IF(BD9="Yes",(((AI9+(IF(R9="IN-07",'Assumptions & Inputs'!$C$66,AF9))*AL9)*AS9)+AW9)*VLOOKUP("IN-34",'Assumptions & Inputs'!$A$31:$F$69,3,FALSE),0),0) -> 14180.4 | BY9: =IF(BP9=1,((AJ9+(IF(R9="IN-07",'Assumptions & Inputs'!$D$66,AG9))*AM9)*AS9)+AX9+(((AJ9+(IF(R9="IN-07",'Assumptions & Inputs'!$D$66,AG9))*AM9)*AS9)*AZ9)+IF(BD9="Yes",(((AJ9+(IF(R9="IN-07",'Assumptions & Inputs'!$D$66,AG9))*AM9)*AS9)+AX9)*VLOOKUP("IN-34",'Assumptions & Inputs'!$A$31:$F$69,4,FALSE),0),0) -> 19318.5 | BZ9: =IF(BP9=1,((AK9+(IF(R9="IN-07",'Assumptions & Inputs'!$E$66,AH9))*AN9)*AS9)+AY9+(((AK9+(IF(R9="IN-07",'Assumptions & Inputs'!$E$66,AH9))*AN9)*AS9)*AZ9)+IF(BD9="Yes",(((AK9+(IF(R9="IN-07",'Assumptions & Inputs'!$E$66,AH9))*AN9)*AS9)+AY9)*VLOOKUP("IN-34",'Assumptions & Inputs'!$A$31:$F$69,5,FALSE),0),0) -> 79780 | CA9: =IF(BQ9=1,((AI9+(IF(R9="IN-07",'Assumptions & Inputs'!$C$65,AF9))*AL9)*AS9)+AW9+(((AI9+(IF(R9="IN-07",'Assumptions & Inputs'!$C$65,AF9))*AL9)*AS9)*AZ9)+IF(BD9="Yes",(((AI9+(IF(R9="IN-07",'Assumptions & Inputs'!$C$65,AF9))*AL9)*AS9)+AW9)*VLOOKUP("IN-34",'Assumptions & Inputs'!$A$31:$F$69,3,FALSE),0),0) -> 14180.4 | CB9: =IF(BQ9=1,((AJ9+(IF(R9="IN-07",'Assumptions & Inputs'!$D$65,AG9))*AM9)*AS9)+AX9+(((AJ9+(IF(R9="IN-07",'Assumptions & Inputs'!$D$65,AG9))*AM9)*AS9)*AZ9)+IF(BD9="Yes",(((AJ9+(IF(R9="IN-07",'Assumptions & Inputs'!$D$65,AG9))*AM9)*AS9)+AX9)*VLOOKUP("IN-34",'Assumptions & Inputs'!$A$31:$F$69,4,FALSE),0),0) -> 19318.5 | CC9: =IF(BQ9=1,((AK9+(IF(R9="IN-07",'Assumptions & Inputs'!$E$65,AH9))*AN9)*AS9)+AY9+(((AK9+(IF(R9="IN-07",'Assumptions & Inputs'!$E$65,AH9))*AN9)*AS9)*AZ9)+IF(BD9="Yes",(((AK9+(IF(R9="IN-07",'Assumptions & Inputs'!$E$65,AH9))*AN9)*AS9)+AY9)*VLOOKUP("IN-34",'Assumptions & Inputs'!$A$31:$F$69,5,FALSE),0),0) -> 79780 | CD9: =IF(BR9=1,((AI9+(IF(R9="IN-07",'Assumptions & Inputs'!$C$65,AF9))*AL9)*AS9)+AW9+(((AI9+(IF(R9="IN-07",'Assumptions & Inputs'!$C$65,AF9))*AL9)*AS9)*AZ9)+IF(BD9="Yes",(((AI9+(IF(R9="IN-07",'Assumptions & Inputs'!$C$65,AF9))*AL9)*AS9)+AW9)*VLOOKUP("IN-34",'Assumptions & Inputs'!$A$31:$F$69,3,FALSE),0),0) -> 14180.4 | CE9: =IF(BR9=1,((AJ9+(IF(R9="IN-07",'Assumptions & Inputs'!$D$65,AG9))*AM9)*AS9)+AX9+(((AJ9+(IF(R9="IN-07",'Assumptions & Inputs'!$D$65,AG9))*AM9)*AS9)*AZ9)+IF(BD9="Yes",(((AJ9+(IF(R9="IN-07",'Assumptions & Inputs'!$D$65,AG9))*AM9)*AS9)+AX9)*VLOOKUP("IN-34",'Assumptions & Inputs'!$A$31:$F$69,4,FALSE),0),0) -> 19318.5 | CF9: =IF(BR9=1,((AK9+(IF(R9="IN-07",'Assumptions & Inputs'!$E$65,AH9))*AN9)*AS9)+AY9+(((AK9+(IF(R9="IN-07",'Assumptions & Inputs'!$E$65,AH9))*AN9)*AS9)*AZ9)+IF(BD9="Yes",(((AK9+(IF(R9="IN-07",'Assumptions & Inputs'!$E$65,AH9))*AN9)*AS9)+AY9)*VLOOKUP("IN-34",'Assumptions & Inputs'!$A$31:$F$69,5,FALSE),0),0) -> 79780 | CG9: =IF(BS9=1,((AI9+(IF(R9="IN-07",0,AF9))*AL9)*AS9)+AW9+(((AI9+(IF(R9="IN-07",0,AF9))*AL9)*AS9)*AZ9)+IF(BD9="Yes",(((AI9+(IF(R9="IN-07",0,AF9))*AL9)*AS9)+AW9)*VLOOKUP("IN-34",'Assumptions & Inputs'!$A$31:$F$69,3,FALSE),0),0) -> 14180.4 | CH9: =IF(BS9=1,((AJ9+(IF(R9="IN-07",0,AG9))*AM9)*AS9)+AX9+(((AJ9+(IF(R9="IN-07",0,AG9))*AM9)*AS9)*AZ9)+IF(BD9="Yes",(((AJ9+(IF(R9="IN-07",0,AG9))*AM9)*AS9)+AX9)*VLOOKUP("IN-34",'Assumptions & Inputs'!$A$31:$F$69,4,FALSE),0),0) -> 19318.5 | CI9: =IF(BS9=1,((AK9+(IF(R9="IN-07",0,AH9))*AN9)*AS9)+AY9+(((AK9+(IF(R9="IN-07",0,AH9))*AN9)*AS9)*AZ9)+IF(BD9="Yes",(((AK9+(IF(R9="IN-07",0,AH9))*AN9)*AS9)+AY9)*VLOOKUP("IN-34",'Assumptions & Inputs'!$A$31:$F$69,5,FALSE),0),0) -> 79780 | CJ9: =IF(BT9=1,((AI9+(IF(R9="IN-07",0,AF9))*AL9)*AS9)+AW9+(((AI9+(IF(R9="IN-07",0,AF9))*AL9)*AS9)*AZ9)+IF(BD9="Yes",(((AI9+(IF(R9="IN-07",0,AF9))*AL9)*AS9)+AW9)*VLOOKUP("IN-34",'Assumptions & Inputs'!$A$31:$F$69,3,FALSE),0),0) -> 14180.4 | CK9: =IF(BT9=1,((AJ9+(IF(R9="IN-07",0,AG9))*AM9)*AS9)+AX9+(((AJ9+(IF(R9="IN-07",0,AG9))*AM9)*AS9)*AZ9)+IF(BD9="Yes",(((AJ9+(IF(R9="IN-07",0,AG9))*AM9)*AS9)+AX9)*VLOOKUP("IN-34",'Assumptions & Inputs'!$A$31:$F$69,4,FALSE),0),0) -> 19318.5 | CL9: =IF(BT9=1,((AK9+(IF(R9="IN-07",0,AH9))*AN9)*AS9)+AY9+(((AK9+(IF(R9="IN-07",0,AH9))*AN9)*AS9)*AZ9)+IF(BD9="Yes",(((AK9+(IF(R9="IN-07",0,AH9))*AN9)*AS9)+AY9)*VLOOKUP("IN-34",'Assumptions & Inputs'!$A$31:$F$69,5,FALSE),0),0) -> 79780
A10: WBS-01.05.01 | B10: WBS-01.05 | C10: State PHA | D10: Governance, legal, privacy, and security | E10: Privacy and de-identification approval | F10: Approve de-identified line-level and aggregate output design | G10: Review fields, transformations, minimum-necessary use, access, retention implementation, and disclosure controls. | H10: Documented privacy determination and approved output specification | I10: PHA | J10: PHA privacy team | K10: Intermediary; legal counsel; analytics team | L10: PHA | M10: Funded | N10: 1A, 1B, 2A, 2B, 3A, 3B | O10: Base common | P10: Fixed per output | Q10: output type | R10: IN-12 | S10: Quantity × hours per unit | T10: Privacy specialist | U10: Legal counsel; public health informatics lead | V10: PHA staff | W10: None | X10: PHA privacy officer | Y10: External legal services if required | Z10: Bottom-up labor estimate | AA10: BM-03 | AB10: High | AC10: A22; A57; A66 | AD10: RD-25 | AE10: =IF(ISNUMBER(SEARCH('Scenario Definitions'!$C$5,N10)),1,0) -> 1 | AF10: =IFERROR(VLOOKUP(R10,'Assumptions & Inputs'!$A$31:$F$69,3,FALSE),0) -> 2 | AG10: =IFERROR(VLOOKUP(R10,'Assumptions & Inputs'!$A$31:$F$69,4,FALSE),0) -> 2 | AH10: =IFERROR(VLOOKUP(R10,'Assumptions & Inputs'!$A$31:$F$69,5,FALSE),0) -> 3 | AI10: 0 | AJ10: 0 | AK10: 0 | AL10: 16.2 | AM10: 21.6 | AN10: 32.4 | AO10: =AI10+(AF10*AL10) -> 32.4 | AP10: =AJ10+(AG10*AM10) -> 43.2 | AQ10: =AK10+(AH10*AN10) -> 97.2 | AR10: RT-06 | AS10: =IFERROR(VLOOKUP(AR10,'Assumptions & Inputs'!$A$73:$I$100,9,FALSE),0) -> 180 | AT10: =AO10*AS10 -> 5832 | AU10: =AP10*AS10 -> 7776 | AV10: =AQ10*AS10 -> 17496 | AW10: 0 | AX10: 0 | AY10: 15000 | AZ10: =IFERROR(VLOOKUP(C10,'Assumptions & Inputs'!$A$104:$B$107,2,FALSE),0) -> 0.25 | BA10: =AT10*AZ10 -> 1458 | BB10: =AU10*AZ10 -> 1944 | BC10: =AV10*AZ10 -> 4374 | BD10: Yes | BE10: =IF(BD10="Yes",(AT10+AW10)*VLOOKUP("IN-34",'Assumptions & Inputs'!$A$31:$F$69,3,FALSE),0) -> 291.6 | BF10: =IF(BD10="Yes",(AU10+AX10)*VLOOKUP("IN-34",'Assumptions & Inputs'!$A$31:$F$69,4,FALSE),0) -> 583.2 | BG10: =IF(BD10="Yes",(AV10+AY10)*VLOOKUP("IN-34",'Assumptions & Inputs'!$A$31:$F$69,5,FALSE),0) -> 4874.4 | BH10: =AT10+AW10+BA10+BE10 -> 7581.6 | BI10: =AU10+AX10+BB10+BF10 -> 10303.2 | BJ10: =AV10+AY10+BC10+BG10 -> 41744.4 | BK10: Provisional — expert judgment | BL10: Pending participant validation | BM10: BM-03 | BN10: Provisional Stage 4 assumption; replace with actual rate, quote, or validated benchmark where available. | BO10: =IF(ISNUMBER(SEARCH("1A",N10)),1,0) -> 1 | BP10: =IF(ISNUMBER(SEARCH("1B",N10)),1,0) -> 1 | BQ10: =IF(ISNUMBER(SEARCH("2A",N10)),1,0) -> 1 | BR10: =IF(ISNUMBER(SEARCH("2B",N10)),1,0) -> 1 | BS10: =IF(ISNUMBER(SEARCH("3A",N10)),1,0) -> 1 | BT10: =IF(ISNUMBER(SEARCH("3B",N10)),1,0) -> 1 | BU10: =IF(BO10=1,((AI10+(IF(R10="IN-07",'Assumptions & Inputs'!$C$66,AF10))*AL10)*AS10)+AW10+(((AI10+(IF(R10="IN-07",'Assumptions & Inputs'!$C$66,AF10))*AL10)*AS10)*AZ10)+IF(BD10="Yes",(((AI10+(IF(R10="IN-07",'Assumptions & Inputs'!$C$66,AF10))*AL10)*AS10)+AW10)*VLOOKUP("IN-34",'Assumptions & Inputs'!$A$31:$F$69,3,FALSE),0),0) -> 7581.6 | BV10: =IF(BO10=1,((AJ10+(IF(R10="IN-07",'Assumptions & Inputs'!$D$66,AG10))*AM10)*AS10)+AX10+(((AJ10+(IF(R10="IN-07",'Assumptions & Inputs'!$D$66,AG10))*AM10)*AS10)*AZ10)+IF(BD10="Yes",(((AJ10+(IF(R10="IN-07",'Assumptions & Inputs'!$D$66,AG10))*AM10)*AS10)+AX10)*VLOOKUP("IN-34",'Assumptions & Inputs'!$A$31:$F$69,4,FALSE),0),0) -> 10303.2 | BW10: =IF(BO10=1,((AK10+(IF(R10="IN-07",'Assumptions & Inputs'!$E$66,AH10))*AN10)*AS10)+AY10+(((AK10+(IF(R10="IN-07",'Assumptions & Inputs'!$E$66,AH10))*AN10)*AS10)*AZ10)+IF(BD10="Yes",(((AK10+(IF(R10="IN-07",'Assumptions & Inputs'!$E$66,AH10))*AN10)*AS10)+AY10)*VLOOKUP("IN-34",'Assumptions & Inputs'!$A$31:$F$69,5,FALSE),0),0) -> 41744.4 | BX10: =IF(BP10=1,((AI10+(IF(R10="IN-07",'Assumptions & Inputs'!$C$66,AF10))*AL10)*AS10)+AW10+(((AI10+(IF(R10="IN-07",'Assumptions & Inputs'!$C$66,AF10))*AL10)*AS10)*AZ10)+IF(BD10="Yes",(((AI10+(IF(R10="IN-07",'Assumptions & Inputs'!$C$66,AF10))*AL10)*AS10)+AW10)*VLOOKUP("IN-34",'Assumptions & Inputs'!$A$31:$F$69,3,FALSE),0),0) -> 7581.6 | BY10: =IF(BP10=1,((AJ10+(IF(R10="IN-07",'Assumptions & Inputs'!$D$66,AG10))*AM10)*AS10)+AX10+(((AJ10+(IF(R10="IN-07",'Assumptions & Inputs'!$D$66,AG10))*AM10)*AS10)*AZ10)+IF(BD10="Yes",(((AJ10+(IF(R10="IN-07",'Assumptions & Inputs'!$D$66,AG10))*AM10)*AS10)+AX10)*VLOOKUP("IN-34",'Assumptions & Inputs'!$A$31:$F$69,4,FALSE),0),0) -> 10303.2 | BZ10: =IF(BP10=1,((AK10+(IF(R10="IN-07",'Assumptions & Inputs'!$E$66,AH10))*AN10)*AS10)+AY10+(((AK10+(IF(R10="IN-07",'Assumptions & Inputs'!$E$66,AH10))*AN10)*AS10)*AZ10)+IF(BD10="Yes",(((AK10+(IF(R10="IN-07",'Assumptions & Inputs'!$E$66,AH10))*AN10)*AS10)+AY10)*VLOOKUP("IN-34",'Assumptions & Inputs'!$A$31:$F$69,5,FALSE),0),0) -> 41744.4 | CA10: =IF(BQ10=1,((AI10+(IF(R10="IN-07",'Assumptions & Inputs'!$C$65,AF10))*AL10)*AS10)+AW10+(((AI10+(IF(R10="IN-07",'Assumptions & Inputs'!$C$65,AF10))*AL10)*AS10)*AZ10)+IF(BD10="Yes",(((AI10+(IF(R10="IN-07",'Assumptions & Inputs'!$C$65,AF10))*AL10)*AS10)+AW10)*VLOOKUP("IN-34",'Assumptions & Inputs'!$A$31:$F$69,3,FALSE),0),0) -> 7581.6 | CB10: =IF(BQ10=1,((AJ10+(IF(R10="IN-07",'Assumptions & Inputs'!$D$65,AG10))*AM10)*AS10)+AX10+(((AJ10+(IF(R10="IN-07",'Assumptions & Inputs'!$D$65,AG10))*AM10)*AS10)*AZ10)+IF(BD10="Yes",(((AJ10+(IF(R10="IN-07",'Assumptions & Inputs'!$D$65,AG10))*AM10)*AS10)+AX10)*VLOOKUP("IN-34",'Assumptions & Inputs'!$A$31:$F$69,4,FALSE),0),0) -> 10303.2 | CC10: =IF(BQ10=1,((AK10+(IF(R10="IN-07",'Assumptions & Inputs'!$E$65,AH10))*AN10)*AS10)+AY10+(((AK10+(IF(R10="IN-07",'Assumptions & Inputs'!$E$65,AH10))*AN10)*AS10)*AZ10)+IF(BD10="Yes",(((AK10+(IF(R10="IN-07",'Assumptions & Inputs'!$E$65,AH10))*AN10)*AS10)+AY10)*VLOOKUP("IN-34",'Assumptions & Inputs'!$A$31:$F$69,5,FALSE),0),0) -> 41744.4 | CD10: =IF(BR10=1,((AI10+(IF(R10="IN-07",'Assumptions & Inputs'!$C$65,AF10))*AL10)*AS10)+AW10+(((AI10+(IF(R10="IN-07",'Assumptions & Inputs'!$C$65,AF10))*AL10)*AS10)*AZ10)+IF(BD10="Yes",(((AI10+(IF(R10="IN-07",'Assumptions & Inputs'!$C$65,AF10))*AL10)*AS10)+AW10)*VLOOKUP("IN-34",'Assumptions & Inputs'!$A$31:$F$69,3,FALSE),0),0) -> 7581.6 | CE10: =IF(BR10=1,((AJ10+(IF(R10="IN-07",'Assumptions & Inputs'!$D$65,AG10))*AM10)*AS10)+AX10+(((AJ10+(IF(R10="IN-07",'Assumptions & Inputs'!$D$65,AG10))*AM10)*AS10)*AZ10)+IF(BD10="Yes",(((AJ10+(IF(R10="IN-07",'Assumptions & Inputs'!$D$65,AG10))*AM10)*AS10)+AX10)*VLOOKUP("IN-34",'Assumptions & Inputs'!$A$31:$F$69,4,FALSE),0),0) -> 10303.2 | CF10: =IF(BR10=1,((AK10+(IF(R10="IN-07",'Assumptions & Inputs'!$E$65,AH10))*AN10)*AS10)+AY10+(((AK10+(IF(R10="IN-07",'Assumptions & Inputs'!$E$65,AH10))*AN10)*AS10)*AZ10)+IF(BD10="Yes",(((AK10+(IF(R10="IN-07",'Assumptions & Inputs'!$E$65,AH10))*AN10)*AS10)+AY10)*VLOOKUP("IN-34",'Assumptions & Inputs'!$A$31:$F$69,5,FALSE),0),0) -> 41744.4 | CG10: =IF(BS10=1,((AI10+(IF(R10="IN-07",0,AF10))*AL10)*AS10)+AW10+(((AI10+(IF(R10="IN-07",0,AF10))*AL10)*AS10)*AZ10)+IF(BD10="Yes",(((AI10+(IF(R10="IN-07",0,AF10))*AL10)*AS10)+AW10)*VLOOKUP("IN-34",'Assumptions & Inputs'!$A$31:$F$69,3,FALSE),0),0) -> 7581.6 | CH10: =IF(BS10=1,((AJ10+(IF(R10="IN-07",0,AG10))*AM10)*AS10)+AX10+(((AJ10+(IF(R10="IN-07",0,AG10))*AM10)*AS10)*AZ10)+IF(BD10="Yes",(((AJ10+(IF(R10="IN-07",0,AG10))*AM10)*AS10)+AX10)*VLOOKUP("IN-34",'Assumptions & Inputs'!$A$31:$F$69,4,FALSE),0),0) -> 10303.2 | CI10: =IF(BS10=1,((AK10+(IF(R10="IN-07",0,AH10))*AN10)*AS10)+AY10+(((AK10+(IF(R10="IN-07",0,AH10))*AN10)*AS10)*AZ10)+IF(BD10="Yes",(((AK10+(IF(R10="IN-07",0,AH10))*AN10)*AS10)+AY10)*VLOOKUP("IN-34",'Assumptions & Inputs'!$A$31:$F$69,5,FALSE),0),0) -> 41744.4 | CJ10: =IF(BT10=1,((AI10+(IF(R10="IN-07",0,AF10))*AL10)*AS10)+AW10+(((AI10+(IF(R10="IN-07",0,AF10))*AL10)*AS10)*AZ10)+IF(BD10="Yes",(((AI10+(IF(R10="IN-07",0,AF10))*AL10)*AS10)+AW10)*VLOOKUP("IN-34",'Assumptions & Inputs'!$A$31:$F$69,3,FALSE),0),0) -> 7581.6 | CK10: =IF(BT10=1,((AJ10+(IF(R10="IN-07",0,AG10))*AM10)*AS10)+AX10+(((AJ10+(IF(R10="IN-07",0,AG10))*AM10)*AS10)*AZ10)+IF(BD10="Yes",(((AJ10+(IF(R10="IN-07",0,AG10))*AM10)*AS10)+AX10)*VLOOKUP("IN-34",'Assumptions & Inputs'!$A$31:$F$69,4,FALSE),0),0) -> 10303.2 | CL10: =IF(BT10=1,((AK10+(IF(R10="IN-07",0,AH10))*AN10)*AS10)+AY10+(((AK10+(IF(R10="IN-07",0,AH10))*AN10)*AS10)*AZ10)+IF(BD10="Yes",(((AK10+(IF(R10="IN-07",0,AH10))*AN10)*AS10)+AY10)*VLOOKUP("IN-34",'Assumptions & Inputs'!$A$31:$F$69,5,FALSE),0),0) -> 41744.4
A11: WBS-01.06.01 | B11: WBS-01.06 | C11: State PHA | D11: Governance, legal, privacy, and security | E11: Security review | F11: Approve PHA receiving connection and access controls | G11: Review secure transport, IAM, logging, incident escalation, and use of existing PHA environments. | H11: Connection/security approval and access-control matrix | I11: PHA | J11: PHA security team | K11: Intermediary; PHA platform team | L11: PHA | M11: Funded | N11: 1A, 1B, 2A, 2B, 3A, 3B | O11: Base common | P11: Step-fixed | Q11: receiving system | R11: IN-32 | S11: Quantity × hours per unit | T11: Security engineer | U11: IAM specialist; privacy specialist; compliance specialist | V11: PHA staff | W11: Security vendor if required | X11: PHA security authority | Y11: Incremental security tooling only if required | Z11: Bottom-up labor estimate | AA11: BM-04 | AB11: High | AC11: A49; A50; A59 | AD11: RD-09 | AE11: =IF(ISNUMBER(SEARCH('Scenario Definitions'!$C$5,N11)),1,0) -> 1 | AF11: =IFERROR(VLOOKUP(R11,'Assumptions & Inputs'!$A$31:$F$69,3,FALSE),0) -> 1 | AG11: =IFERROR(VLOOKUP(R11,'Assumptions & Inputs'!$A$31:$F$69,4,FALSE),0) -> 1 | AH11: =IFERROR(VLOOKUP(R11,'Assumptions & Inputs'!$A$31:$F$69,5,FALSE),0) -> 2 | AI11: 0 | AJ11: 0 | AK11: 0 | AL11: 16.2 | AM11: 21.6 | AN11: 32.4 | AO11: =AI11+(AF11*AL11) -> 16.2 | AP11: =AJ11+(AG11*AM11) -> 21.6 | AQ11: =AK11+(AH11*AN11) -> 64.8 | AR11: RT-06 | AS11: =IFERROR(VLOOKUP(AR11,'Assumptions & Inputs'!$A$73:$I$100,9,FALSE),0) -> 180 | AT11: =AO11*AS11 -> 2916 | AU11: =AP11*AS11 -> 3888 | AV11: =AQ11*AS11 -> 11664 | AW11: 0 | AX11: 5000 | AY11: 40000 | AZ11: =IFERROR(VLOOKUP(C11,'Assumptions & Inputs'!$A$104:$B$107,2,FALSE),0) -> 0.25 | BA11: =AT11*AZ11 -> 729 | BB11: =AU11*AZ11 -> 972 | BC11: =AV11*AZ11 -> 2916 | BD11: Yes | BE11: =IF(BD11="Yes",(AT11+AW11)*VLOOKUP("IN-34",'Assumptions & Inputs'!$A$31:$F$69,3,FALSE),0) -> 145.8 | BF11: =IF(BD11="Yes",(AU11+AX11)*VLOOKUP("IN-34",'Assumptions & Inputs'!$A$31:$F$69,4,FALSE),0) -> 666.6 | BG11: =IF(BD11="Yes",(AV11+AY11)*VLOOKUP("IN-34",'Assumptions & Inputs'!$A$31:$F$69,5,FALSE),0) -> 7749.6 | BH11: =AT11+AW11+BA11+BE11 -> 3790.8 | BI11: =AU11+AX11+BB11+BF11 -> 10526.6 | BJ11: =AV11+AY11+BC11+BG11 -> 62329.6 | BK11: Provisional — expert judgment | BL11: Pending participant validation | BM11: BM-04 | BN11: Provisional Stage 4 assumption; replace with actual rate, quote, or validated benchmark where available. | BO11: =IF(ISNUMBER(SEARCH("1A",N11)),1,0) -> 1 | BP11: =IF(ISNUMBER(SEARCH("1B",N11)),1,0) -> 1 | BQ11: =IF(ISNUMBER(SEARCH("2A",N11)),1,0) -> 1 | BR11: =IF(ISNUMBER(SEARCH("2B",N11)),1,0) -> 1 | BS11: =IF(ISNUMBER(SEARCH("3A",N11)),1,0) -> 1 | BT11: =IF(ISNUMBER(SEARCH("3B",N11)),1,0) -> 1 | BU11: =IF(BO11=1,((AI11+(IF(R11="IN-07",'Assumptions & Inputs'!$C$66,AF11))*AL11)*AS11)+AW11+(((AI11+(IF(R11="IN-07",'Assumptions & Inputs'!$C$66,AF11))*AL11)*AS11)*AZ11)+IF(BD11="Yes",(((AI11+(IF(R11="IN-07",'Assumptions & Inputs'!$C$66,AF11))*AL11)*AS11)+AW11)*VLOOKUP("IN-34",'Assumptions & Inputs'!$A$31:$F$69,3,FALSE),0),0) -> 3790.8 | BV11: =IF(BO11=1,((AJ11+(IF(R11="IN-07",'Assumptions & Inputs'!$D$66,AG11))*AM11)*AS11)+AX11+(((AJ11+(IF(R11="IN-07",'Assumptions & Inputs'!$D$66,AG11))*AM11)*AS11)*AZ11)+IF(BD11="Yes",(((AJ11+(IF(R11="IN-07",'Assumptions & Inputs'!$D$66,AG11))*AM11)*AS11)+AX11)*VLOOKUP("IN-34",'Assumptions & Inputs'!$A$31:$F$69,4,FALSE),0),0) -> 10526.6 | BW11: =IF(BO11=1,((AK11+(IF(R11="IN-07",'Assumptions & Inputs'!$E$66,AH11))*AN11)*AS11)+AY11+(((AK11+(IF(R11="IN-07",'Assumptions & Inputs'!$E$66,AH11))*AN11)*AS11)*AZ11)+IF(BD11="Yes",(((AK11+(IF(R11="IN-07",'Assumptions & Inputs'!$E$66,AH11))*AN11)*AS11)+AY11)*VLOOKUP("IN-34",'Assumptions & Inputs'!$A$31:$F$69,5,FALSE),0),0) -> 62329.6 | BX11: =IF(BP11=1,((AI11+(IF(R11="IN-07",'Assumptions & Inputs'!$C$66,AF11))*AL11)*AS11)+AW11+(((AI11+(IF(R11="IN-07",'Assumptions & Inputs'!$C$66,AF11))*AL11)*AS11)*AZ11)+IF(BD11="Yes",(((AI11+(IF(R11="IN-07",'Assumptions & Inputs'!$C$66,AF11))*AL11)*AS11)+AW11)*VLOOKUP("IN-34",'Assumptions & Inputs'!$A$31:$F$69,3,FALSE),0),0) -> 3790.8 | BY11: =IF(BP11=1,((AJ11+(IF(R11="IN-07",'Assumptions & Inputs'!$D$66,AG11))*AM11)*AS11)+AX11+(((AJ11+(IF(R11="IN-07",'Assumptions & Inputs'!$D$66,AG11))*AM11)*AS11)*AZ11)+IF(BD11="Yes",(((AJ11+(IF(R11="IN-07",'Assumptions & Inputs'!$D$66,AG11))*AM11)*AS11)+AX11)*VLOOKUP("IN-34",'Assumptions & Inputs'!$A$31:$F$69,4,FALSE),0),0) -> 10526.6 | BZ11: =IF(BP11=1,((AK11+(IF(R11="IN-07",'Assumptions & Inputs'!$E$66,AH11))*AN11)*AS11)+AY11+(((AK11+(IF(R11="IN-07",'Assumptions & Inputs'!$E$66,AH11))*AN11)*AS11)*AZ11)+IF(BD11="Yes",(((AK11+(IF(R11="IN-07",'Assumptions & Inputs'!$E$66,AH11))*AN11)*AS11)+AY11)*VLOOKUP("IN-34",'Assumptions & Inputs'!$A$31:$F$69,5,FALSE),0),0) -> 62329.6 | CA11: =IF(BQ11=1,((AI11+(IF(R11="IN-07",'Assumptions & Inputs'!$C$65,AF11))*AL11)*AS11)+AW11+(((AI11+(IF(R11="IN-07",'Assumptions & Inputs'!$C$65,AF11))*AL11)*AS11)*AZ11)+IF(BD11="Yes",(((AI11+(IF(R11="IN-07",'Assumptions & Inputs'!$C$65,AF11))*AL11)*AS11)+AW11)*VLOOKUP("IN-34",'Assumptions & Inputs'!$A$31:$F$69,3,FALSE),0),0) -> 3790.8 | CB11: =IF(BQ11=1,((AJ11+(IF(R11="IN-07",'Assumptions & Inputs'!$D$65,AG11))*AM11)*AS11)+AX11+(((AJ11+(IF(R11="IN-07",'Assumptions & Inputs'!$D$65,AG11))*AM11)*AS11)*AZ11)+IF(BD11="Yes",(((AJ11+(IF(R11="IN-07",'Assumptions & Inputs'!$D$65,AG11))*AM11)*AS11)+AX11)*VLOOKUP("IN-34",'Assumptions & Inputs'!$A$31:$F$69,4,FALSE),0),0) -> 10526.6 | CC11: =IF(BQ11=1,((AK11+(IF(R11="IN-07",'Assumptions & Inputs'!$E$65,AH11))*AN11)*AS11)+AY11+(((AK11+(IF(R11="IN-07",'Assumptions & Inputs'!$E$65,AH11))*AN11)*AS11)*AZ11)+IF(BD11="Yes",(((AK11+(IF(R11="IN-07",'Assumptions & Inputs'!$E$65,AH11))*AN11)*AS11)+AY11)*VLOOKUP("IN-34",'Assumptions & Inputs'!$A$31:$F$69,5,FALSE),0),0) -> 62329.6 | CD11: =IF(BR11=1,((AI11+(IF(R11="IN-07",'Assumptions & Inputs'!$C$65,AF11))*AL11)*AS11)+AW11+(((AI11+(IF(R11="IN-07",'Assumptions & Inputs'!$C$65,AF11))*AL11)*AS11)*AZ11)+IF(BD11="Yes",(((AI11+(IF(R11="IN-07",'Assumptions & Inputs'!$C$65,AF11))*AL11)*AS11)+AW11)*VLOOKUP("IN-34",'Assumptions & Inputs'!$A$31:$F$69,3,FALSE),0),0) -> 3790.8 | CE11: =IF(BR11=1,((AJ11+(IF(R11="IN-07",'Assumptions & Inputs'!$D$65,AG11))*AM11)*AS11)+AX11+(((AJ11+(IF(R11="IN-07",'Assumptions & Inputs'!$D$65,AG11))*AM11)*AS11)*AZ11)+IF(BD11="Yes",(((AJ11+(IF(R11="IN-07",'Assumptions & Inputs'!$D$65,AG11))*AM11)*AS11)+AX11)*VLOOKUP("IN-34",'Assumptions & Inputs'!$A$31:$F$69,4,FALSE),0),0) -> 10526.6 | CF11: =IF(BR11=1,((AK11+(IF(R11="IN-07",'Assumptions & Inputs'!$E$65,AH11))*AN11)*AS11)+AY11+(((AK11+(IF(R11="IN-07",'Assumptions & Inputs'!$E$65,AH11))*AN11)*AS11)*AZ11)+IF(BD11="Yes",(((AK11+(IF(R11="IN-07",'Assumptions & Inputs'!$E$65,AH11))*AN11)*AS11)+AY11)*VLOOKUP("IN-34",'Assumptions & Inputs'!$A$31:$F$69,5,FALSE),0),0) -> 62329.6 | CG11: =IF(BS11=1,((AI11+(IF(R11="IN-07",0,AF11))*AL11)*AS11)+AW11+(((AI11+(IF(R11="IN-07",0,AF11))*AL11)*AS11)*AZ11)+IF(BD11="Yes",(((AI11+(IF(R11="IN-07",0,AF11))*AL11)*AS11)+AW11)*VLOOKUP("IN-34",'Assumptions & Inputs'!$A$31:$F$69,3,FALSE),0),0) -> 3790.8 | CH11: =IF(BS11=1,((AJ11+(IF(R11="IN-07",0,AG11))*AM11)*AS11)+AX11+(((AJ11+(IF(R11="IN-07",0,AG11))*AM11)*AS11)*AZ11)+IF(BD11="Yes",(((AJ11+(IF(R11="IN-07",0,AG11))*AM11)*AS11)+AX11)*VLOOKUP("IN-34",'Assumptions & Inputs'!$A$31:$F$69,4,FALSE),0),0) -> 10526.6 | CI11: =IF(BS11=1,((AK11+(IF(R11="IN-07",0,AH11))*AN11)*AS11)+AY11+(((AK11+(IF(R11="IN-07",0,AH11))*AN11)*AS11)*AZ11)+IF(BD11="Yes",(((AK11+(IF(R11="IN-07",0,AH11))*AN11)*AS11)+AY11)*VLOOKUP("IN-34",'Assumptions & Inputs'!$A$31:$F$69,5,FALSE),0),0) -> 62329.6 | CJ11: =IF(BT11=1,((AI11+(IF(R11="IN-07",0,AF11))*AL11)*AS11)+AW11+(((AI11+(IF(R11="IN-07",0,AF11))*AL11)*AS11)*AZ11)+IF(BD11="Yes",(((AI11+(IF(R11="IN-07",0,AF11))*AL11)*AS11)+AW11)*VLOOKUP("IN-34",'Assumptions & Inputs'!$A$31:$F$69,3,FALSE),0),0) -> 3790.8 | CK11: =IF(BT11=1,((AJ11+(IF(R11="IN-07",0,AG11))*AM11)*AS11)+AX11+(((AJ11+(IF(R11="IN-07",0,AG11))*AM11)*AS11)*AZ11)+IF(BD11="Yes",(((AJ11+(IF(R11="IN-07",0,AG11))*AM11)*AS11)+AX11)*VLOOKUP("IN-34",'Assumptions & Inputs'!$A$31:$F$69,4,FALSE),0),0) -> 10526.6 | CL11: =IF(BT11=1,((AK11+(IF(R11="IN-07",0,AH11))*AN11)*AS11)+AY11+(((AK11+(IF(R11="IN-07",0,AH11))*AN11)*AS11)*AZ11)+IF(BD11="Yes",(((AK11+(IF(R11="IN-07",0,AH11))*AN11)*AS11)+AY11)*VLOOKUP("IN-34",'Assumptions & Inputs'!$A$31:$F$69,5,FALSE),0),0) -> 62329.6
A12: WBS-01.07.01 | B12: WBS-01.07 | C12: State PHA | D12: Data specification and mapping | E12: Surveillance requirements | F12: Confirm surveillance indicators and acceptance requirements | G12: Translate charter-defined questions into field, stratification, timeliness, quality, and usability requirements. | H12: Approved PHA surveillance requirements and acceptance criteria | I12: PHA | J12: PHA public health team | K12: Intermediary; clinical SMEs | L12: PHA | M12: Funded | N12: 1A, 1B, 2A, 2B, 3A, 3B | O12: Base common | P12: Fixed per output | Q12: PHA surveillance output | R12: IN-13 | S12: Quantity × hours per unit | T12: Public health informatics lead | U12: Epidemiologist; diabetes SME; business analyst | V12: PHA staff | W12: None | X12: PHA program lead | Y12: None material | Z12: Bottom-up labor estimate | AA12: BM-05 | AB12: Moderate | AC12: A17; A23 | AD12: RD-26 | AE12: =IF(ISNUMBER(SEARCH('Scenario Definitions'!$C$5,N12)),1,0) -> 1 | AF12: =IFERROR(VLOOKUP(R12,'Assumptions & Inputs'!$A$31:$F$69,3,FALSE),0) -> 1 | AG12: =IFERROR(VLOOKUP(R12,'Assumptions & Inputs'!$A$31:$F$69,4,FALSE),0) -> 1 | AH12: =IFERROR(VLOOKUP(R12,'Assumptions & Inputs'!$A$31:$F$69,5,FALSE),0) -> 2 | AI12: 0 | AJ12: 0 | AK12: 0 | AL12: 12 | AM12: 16 | AN12: 24 | AO12: =AI12+(AF12*AL12) -> 12 | AP12: =AJ12+(AG12*AM12) -> 16 | AQ12: =AK12+(AH12*AN12) -> 48 | AR12: RT-03 | AS12: =IFERROR(VLOOKUP(AR12,'Assumptions & Inputs'!$A$73:$I$100,9,FALSE),0) -> 125 | AT12: =AO12*AS12 -> 1500 | AU12: =AP12*AS12 -> 2000 | AV12: =AQ12*AS12 -> 6000 | AW12: 0 | AX12: 0 | AY12: 0 | AZ12: =IFERROR(VLOOKUP(C12,'Assumptions & Inputs'!$A$104:$B$107,2,FALSE),0) -> 0.25 | BA12: =AT12*AZ12 -> 375 | BB12: =AU12*AZ12 -> 500 | BC12: =AV12*AZ12 -> 1500 | BD12: Yes | BE12: =IF(BD12="Yes",(AT12+AW12)*VLOOKUP("IN-34",'Assumptions & Inputs'!$A$31:$F$69,3,FALSE),0) -> 75 | BF12: =IF(BD12="Yes",(AU12+AX12)*VLOOKUP("IN-34",'Assumptions & Inputs'!$A$31:$F$69,4,FALSE),0) -> 150 | BG12: =IF(BD12="Yes",(AV12+AY12)*VLOOKUP("IN-34",'Assumptions & Inputs'!$A$31:$F$69,5,FALSE),0) -> 900 | BH12: =AT12+AW12+BA12+BE12 -> 1950 | BI12: =AU12+AX12+BB12+BF12 -> 2650 | BJ12: =AV12+AY12+BC12+BG12 -> 8400 | BK12: Provisional — expert judgment | BL12: Pending participant validation | BM12: BM-05 | BN12: Provisional Stage 4 assumption; replace with actual rate, quote, or validated benchmark where available. | BO12: =IF(ISNUMBER(SEARCH("1A",N12)),1,0) -> 1 | BP12: =IF(ISNUMBER(SEARCH("1B",N12)),1,0) -> 1 | BQ12: =IF(ISNUMBER(SEARCH("2A",N12)),1,0) -> 1 | BR12: =IF(ISNUMBER(SEARCH("2B",N12)),1,0) -> 1 | BS12: =IF(ISNUMBER(SEARCH("3A",N12)),1,0) -> 1 | BT12: =IF(ISNUMBER(SEARCH("3B",N12)),1,0) -> 1 | BU12: =IF(BO12=1,((AI12+(IF(R12="IN-07",'Assumptions & Inputs'!$C$66,AF12))*AL12)*AS12)+AW12+(((AI12+(IF(R12="IN-07",'Assumptions & Inputs'!$C$66,AF12))*AL12)*AS12)*AZ12)+IF(BD12="Yes",(((AI12+(IF(R12="IN-07",'Assumptions & Inputs'!$C$66,AF12))*AL12)*AS12)+AW12)*VLOOKUP("IN-34",'Assumptions & Inputs'!$A$31:$F$69,3,FALSE),0),0) -> 1950 | BV12: =IF(BO12=1,((AJ12+(IF(R12="IN-07",'Assumptions & Inputs'!$D$66,AG12))*AM12)*AS12)+AX12+(((AJ12+(IF(R12="IN-07",'Assumptions & Inputs'!$D$66,AG12))*AM12)*AS12)*AZ12)+IF(BD12="Yes",(((AJ12+(IF(R12="IN-07",'Assumptions & Inputs'!$D$66,AG12))*AM12)*AS12)+AX12)*VLOOKUP("IN-34",'Assumptions & Inputs'!$A$31:$F$69,4,FALSE),0),0) -> 2650 | BW12: =IF(BO12=1,((AK12+(IF(R12="IN-07",'Assumptions & Inputs'!$E$66,AH12))*AN12)*AS12)+AY12+(((AK12+(IF(R12="IN-07",'Assumptions & Inputs'!$E$66,AH12))*AN12)*AS12)*AZ12)+IF(BD12="Yes",(((AK12+(IF(R12="IN-07",'Assumptions & Inputs'!$E$66,AH12))*AN12)*AS12)+AY12)*VLOOKUP("IN-34",'Assumptions & Inputs'!$A$31:$F$69,5,FALSE),0),0) -> 8400 | BX12: =IF(BP12=1,((AI12+(IF(R12="IN-07",'Assumptions & Inputs'!$C$66,AF12))*AL12)*AS12)+AW12+(((AI12+(IF(R12="IN-07",'Assumptions & Inputs'!$C$66,AF12))*AL12)*AS12)*AZ12)+IF(BD12="Yes",(((AI12+(IF(R12="IN-07",'Assumptions & Inputs'!$C$66,AF12))*AL12)*AS12)+AW12)*VLOOKUP("IN-34",'Assumptions & Inputs'!$A$31:$F$69,3,FALSE),0),0) -> 1950 | BY12: =IF(BP12=1,((AJ12+(IF(R12="IN-07",'Assumptions & Inputs'!$D$66,AG12))*AM12)*AS12)+AX12+(((AJ12+(IF(R12="IN-07",'Assumptions & Inputs'!$D$66,AG12))*AM12)*AS12)*AZ12)+IF(BD12="Yes",(((AJ12+(IF(R12="IN-07",'Assumptions & Inputs'!$D$66,AG12))*AM12)*AS12)+AX12)*VLOOKUP("IN-34",'Assumptions & Inputs'!$A$31:$F$69,4,FALSE),0),0) -> 2650 | BZ12: =IF(BP12=1,((AK12+(IF(R12="IN-07",'Assumptions & Inputs'!$E$66,AH12))*AN12)*AS12)+AY12+(((AK12+(IF(R12="IN-07",'Assumptions & Inputs'!$E$66,AH12))*AN12)*AS12)*AZ12)+IF(BD12="Yes",(((AK12+(IF(R12="IN-07",'Assumptions & Inputs'!$E$66,AH12))*AN12)*AS12)+AY12)*VLOOKUP("IN-34",'Assumptions & Inputs'!$A$31:$F$69,5,FALSE),0),0) -> 8400 | CA12: =IF(BQ12=1,((AI12+(IF(R12="IN-07",'Assumptions & Inputs'!$C$65,AF12))*AL12)*AS12)+AW12+(((AI12+(IF(R12="IN-07",'Assumptions & Inputs'!$C$65,AF12))*AL12)*AS12)*AZ12)+IF(BD12="Yes",(((AI12+(IF(R12="IN-07",'Assumptions & Inputs'!$C$65,AF12))*AL12)*AS12)+AW12)*VLOOKUP("IN-34",'Assumptions & Inputs'!$A$31:$F$69,3,FALSE),0),0) -> 1950 | CB12: =IF(BQ12=1,((AJ12+(IF(R12="IN-07",'Assumptions & Inputs'!$D$65,AG12))*AM12)*AS12)+AX12+(((AJ12+(IF(R12="IN-07",'Assumptions & Inputs'!$D$65,AG12))*AM12)*AS12)*AZ12)+IF(BD12="Yes",(((AJ12+(IF(R12="IN-07",'Assumptions & Inputs'!$D$65,AG12))*AM12)*AS12)+AX12)*VLOOKUP("IN-34",'Assumptions & Inputs'!$A$31:$F$69,4,FALSE),0),0) -> 2650 | CC12: =IF(BQ12=1,((AK12+(IF(R12="IN-07",'Assumptions & Inputs'!$E$65,AH12))*AN12)*AS12)+AY12+(((AK12+(IF(R12="IN-07",'Assumptions & Inputs'!$E$65,AH12))*AN12)*AS12)*AZ12)+IF(BD12="Yes",(((AK12+(IF(R12="IN-07",'Assumptions & Inputs'!$E$65,AH12))*AN12)*AS12)+AY12)*VLOOKUP("IN-34",'Assumptions & Inputs'!$A$31:$F$69,5,FALSE),0),0) -> 8400 | CD12: =IF(BR12=1,((AI12+(IF(R12="IN-07",'Assumptions & Inputs'!$C$65,AF12))*AL12)*AS12)+AW12+(((AI12+(IF(R12="IN-07",'Assumptions & Inputs'!$C$65,AF12))*AL12)*AS12)*AZ12)+IF(BD12="Yes",(((AI12+(IF(R12="IN-07",'Assumptions & Inputs'!$C$65,AF12))*AL12)*AS12)+AW12)*VLOOKUP("IN-34",'Assumptions & Inputs'!$A$31:$F$69,3,FALSE),0),0) -> 1950 | CE12: =IF(BR12=1,((AJ12+(IF(R12="IN-07",'Assumptions & Inputs'!$D$65,AG12))*AM12)*AS12)+AX12+(((AJ12+(IF(R12="IN-07",'Assumptions & Inputs'!$D$65,AG12))*AM12)*AS12)*AZ12)+IF(BD12="Yes",(((AJ12+(IF(R12="IN-07",'Assumptions & Inputs'!$D$65,AG12))*AM12)*AS12)+AX12)*VLOOKUP("IN-34",'Assumptions & Inputs'!$A$31:$F$69,4,FALSE),0),0) -> 2650 | CF12: =IF(BR12=1,((AK12+(IF(R12="IN-07",'Assumptions & Inputs'!$E$65,AH12))*AN12)*AS12)+AY12+(((AK12+(IF(R12="IN-07",'Assumptions & Inputs'!$E$65,AH12))*AN12)*AS12)*AZ12)+IF(BD12="Yes",(((AK12+(IF(R12="IN-07",'Assumptions & Inputs'!$E$65,AH12))*AN12)*AS12)+AY12)*VLOOKUP("IN-34",'Assumptions & Inputs'!$A$31:$F$69,5,FALSE),0),0) -> 8400 | CG12: =IF(BS12=1,((AI12+(IF(R12="IN-07",0,AF12))*AL12)*AS12)+AW12+(((AI12+(IF(R12="IN-07",0,AF12))*AL12)*AS12)*AZ12)+IF(BD12="Yes",(((AI12+(IF(R12="IN-07",0,AF12))*AL12)*AS12)+AW12)*VLOOKUP("IN-34",'Assumptions & Inputs'!$A$31:$F$69,3,FALSE),0),0) -> 1950 | CH12: =IF(BS12=1,((AJ12+(IF(R12="IN-07",0,AG12))*AM12)*AS12)+AX12+(((AJ12+(IF(R12="IN-07",0,AG12))*AM12)*AS12)*AZ12)+IF(BD12="Yes",(((AJ12+(IF(R12="IN-07",0,AG12))*AM12)*AS12)+AX12)*VLOOKUP("IN-34",'Assumptions & Inputs'!$A$31:$F$69,4,FALSE),0),0) -> 2650 | CI12: =IF(BS12=1,((AK12+(IF(R12="IN-07",0,AH12))*AN12)*AS12)+AY12+(((AK12+(IF(R12="IN-07",0,AH12))*AN12)*AS12)*AZ12)+IF(BD12="Yes",(((AK12+(IF(R12="IN-07",0,AH12))*AN12)*AS12)+AY12)*VLOOKUP("IN-34",'Assumptions & Inputs'!$A$31:$F$69,5,FALSE),0),0) -> 8400 | CJ12: =IF(BT12=1,((AI12+(IF(R12="IN-07",0,AF12))*AL12)*AS12)+AW12+(((AI12+(IF(R12="IN-07",0,AF12))*AL12)*AS12)*AZ12)+IF(BD12="Yes",(((AI12+(IF(R12="IN-07",0,AF12))*AL12)*AS12)+AW12)*VLOOKUP("IN-34",'Assumptions & Inputs'!$A$31:$F$69,3,FALSE),0),0) -> 1950 | CK12: =IF(BT12=1,((AJ12+(IF(R12="IN-07",0,AG12))*AM12)*AS12)+AX12+(((AJ12+(IF(R12="IN-07",0,AG12))*AM12)*AS12)*AZ12)+IF(BD12="Yes",(((AJ12+(IF(R12="IN-07",0,AG12))*AM12)*AS12)+AX12)*VLOOKUP("IN-34",'Assumptions & Inputs'!$A$31:$F$69,4,FALSE),0),0) -> 2650 | CL12: =IF(BT12=1,((AK12+(IF(R12="IN-07",0,AH12))*AN12)*AS12)+AY12+(((AK12+(IF(R12="IN-07",0,AH12))*AN12)*AS12)*AZ12)+IF(BD12="Yes",(((AK12+(IF(R12="IN-07",0,AH12))*AN12)*AS12)+AY12)*VLOOKUP("IN-34",'Assumptions & Inputs'!$A$31:$F$69,5,FALSE),0),0) -> 8400
A13: WBS-01.08.01 | B13: WBS-01.08 | C13: State PHA | D13: Data specification and mapping | E13: Clinical and analytic review | F13: Review minimum dataset, mappings, and value-set deltas | G13: Validate that the proposed diabetes elements and mappings support public health interpretation and approved stratifications. | H13: PHA review comments and approval of pilot-specific data specification | I13: PHA | J13: PHA public health team | K13: Intermediary; providers; measure SME | L13: PHA | M13: Funded | N13: 1A, 1B, 2A, 2B, 3A, 3B | O13: Base common | P13: Fixed per use case | Q13: clinical scope | R13: IN-15 | S13: Quantity × hours per unit | T13: Epidemiologist | U13: Diabetes SME; public health informatics lead | V13: PHA staff | W13: None | X13: PHA program lead | Y13: None material | Z13: Bottom-up labor estimate | AA13: BM-05 | AB13: Moderate | AC13: A14; A15; A17 | AD13: RD-27 | AE13: =IF(ISNUMBER(SEARCH('Scenario Definitions'!$C$5,N13)),1,0) -> 1 | AF13: =IFERROR(VLOOKUP(R13,'Assumptions & Inputs'!$A$31:$F$69,3,FALSE),0) -> 1 | AG13: =IFERROR(VLOOKUP(R13,'Assumptions & Inputs'!$A$31:$F$69,4,FALSE),0) -> 1 | AH13: =IFERROR(VLOOKUP(R13,'Assumptions & Inputs'!$A$31:$F$69,5,FALSE),0) -> 1 | AI13: 0 | AJ13: 0 | AK13: 0 | AL13: 12 | AM13: 16 | AN13: 24 | AO13: =AI13+(AF13*AL13) -> 12 | AP13: =AJ13+(AG13*AM13) -> 16 | AQ13: =AK13+(AH13*AN13) -> 24 | AR13: RT-03 | AS13: =IFERROR(VLOOKUP(AR13,'Assumptions & Inputs'!$A$73:$I$100,9,FALSE),0) -> 125 | AT13: =AO13*AS13 -> 1500 | AU13: =AP13*AS13 -> 2000 | AV13: =AQ13*AS13 -> 3000 | AW13: 0 | AX13: 0 | AY13: 0 | AZ13: =IFERROR(VLOOKUP(C13,'Assumptions & Inputs'!$A$104:$B$107,2,FALSE),0) -> 0.25 | BA13: =AT13*AZ13 -> 375 | BB13: =AU13*AZ13 -> 500 | BC13: =AV13*AZ13 -> 750 | BD13: Yes | BE13: =IF(BD13="Yes",(AT13+AW13)*VLOOKUP("IN-34",'Assumptions & Inputs'!$A$31:$F$69,3,FALSE),0) -> 75 | BF13: =IF(BD13="Yes",(AU13+AX13)*VLOOKUP("IN-34",'Assumptions & Inputs'!$A$31:$F$69,4,FALSE),0) -> 150 | BG13: =IF(BD13="Yes",(AV13+AY13)*VLOOKUP("IN-34",'Assumptions & Inputs'!$A$31:$F$69,5,FALSE),0) -> 450 | BH13: =AT13+AW13+BA13+BE13 -> 1950 | BI13: =AU13+AX13+BB13+BF13 -> 2650 | BJ13: =AV13+AY13+BC13+BG13 -> 4200 | BK13: Provisional — expert judgment | BL13: Pending participant validation | BM13: BM-05 | BN13: Provisional Stage 4 assumption; replace with actual rate, quote, or validated benchmark where available. | BO13: =IF(ISNUMBER(SEARCH("1A",N13)),1,0) -> 1 | BP13: =IF(ISNUMBER(SEARCH("1B",N13)),1,0) -> 1 | BQ13: =IF(ISNUMBER(SEARCH("2A",N13)),1,0) -> 1 | BR13: =IF(ISNUMBER(SEARCH("2B",N13)),1,0) -> 1 | BS13: =IF(ISNUMBER(SEARCH("3A",N13)),1,0) -> 1 | BT13: =IF(ISNUMBER(SEARCH("3B",N13)),1,0) -> 1 | BU13: =IF(BO13=1,((AI13+(IF(R13="IN-07",'Assumptions & Inputs'!$C$66,AF13))*AL13)*AS13)+AW13+(((AI13+(IF(R13="IN-07",'Assumptions & Inputs'!$C$66,AF13))*AL13)*AS13)*AZ13)+IF(BD13="Yes",(((AI13+(IF(R13="IN-07",'Assumptions & Inputs'!$C$66,AF13))*AL13)*AS13)+AW13)*VLOOKUP("IN-34",'Assumptions & Inputs'!$A$31:$F$69,3,FALSE),0),0) -> 1950 | BV13: =IF(BO13=1,((AJ13+(IF(R13="IN-07",'Assumptions & Inputs'!$D$66,AG13))*AM13)*AS13)+AX13+(((AJ13+(IF(R13="IN-07",'Assumptions & Inputs'!$D$66,AG13))*AM13)*AS13)*AZ13)+IF(BD13="Yes",(((AJ13+(IF(R13="IN-07",'Assumptions & Inputs'!$D$66,AG13))*AM13)*AS13)+AX13)*VLOOKUP("IN-34",'Assumptions & Inputs'!$A$31:$F$69,4,FALSE),0),0) -> 2650 | BW13: =IF(BO13=1,((AK13+(IF(R13="IN-07",'Assumptions & Inputs'!$E$66,AH13))*AN13)*AS13)+AY13+(((AK13+(IF(R13="IN-07",'Assumptions & Inputs'!$E$66,AH13))*AN13)*AS13)*AZ13)+IF(BD13="Yes",(((AK13+(IF(R13="IN-07",'Assumptions & Inputs'!$E$66,AH13))*AN13)*AS13)+AY13)*VLOOKUP("IN-34",'Assumptions & Inputs'!$A$31:$F$69,5,FALSE),0),0) -> 4200 | BX13: =IF(BP13=1,((AI13+(IF(R13="IN-07",'Assumptions & Inputs'!$C$66,AF13))*AL13)*AS13)+AW13+(((AI13+(IF(R13="IN-07",'Assumptions & Inputs'!$C$66,AF13))*AL13)*AS13)*AZ13)+IF(BD13="Yes",(((AI13+(IF(R13="IN-07",'Assumptions & Inputs'!$C$66,AF13))*AL13)*AS13)+AW13)*VLOOKUP("IN-34",'Assumptions & Inputs'!$A$31:$F$69,3,FALSE),0),0) -> 1950 | BY13: =IF(BP13=1,((AJ13+(IF(R13="IN-07",'Assumptions & Inputs'!$D$66,AG13))*AM13)*AS13)+AX13+(((AJ13+(IF(R13="IN-07",'Assumptions & Inputs'!$D$66,AG13))*AM13)*AS13)*AZ13)+IF(BD13="Yes",(((AJ13+(IF(R13="IN-07",'Assumptions & Inputs'!$D$66,AG13))*AM13)*AS13)+AX13)*VLOOKUP("IN-34",'Assumptions & Inputs'!$A$31:$F$69,4,FALSE),0),0) -> 2650 | BZ13: =IF(BP13=1,((AK13+(IF(R13="IN-07",'Assumptions & Inputs'!$E$66,AH13))*AN13)*AS13)+AY13+(((AK13+(IF(R13="IN-07",'Assumptions & Inputs'!$E$66,AH13))*AN13)*AS13)*AZ13)+IF(BD13="Yes",(((AK13+(IF(R13="IN-07",'Assumptions & Inputs'!$E$66,AH13))*AN13)*AS13)+AY13)*VLOOKUP("IN-34",'Assumptions & Inputs'!$A$31:$F$69,5,FALSE),0),0) -> 4200 | CA13: =IF(BQ13=1,((AI13+(IF(R13="IN-07",'Assumptions & Inputs'!$C$65,AF13))*AL13)*AS13)+AW13+(((AI13+(IF(R13="IN-07",'Assumptions & Inputs'!$C$65,AF13))*AL13)*AS13)*AZ13)+IF(BD13="Yes",(((AI13+(IF(R13="IN-07",'Assumptions & Inputs'!$C$65,AF13))*AL13)*AS13)+AW13)*VLOOKUP("IN-34",'Assumptions & Inputs'!$A$31:$F$69,3,FALSE),0),0) -> 1950 | CB13: =IF(BQ13=1,((AJ13+(IF(R13="IN-07",'Assumptions & Inputs'!$D$65,AG13))*AM13)*AS13)+AX13+(((AJ13+(IF(R13="IN-07",'Assumptions & Inputs'!$D$65,AG13))*AM13)*AS13)*AZ13)+IF(BD13="Yes",(((AJ13+(IF(R13="IN-07",'Assumptions & Inputs'!$D$65,AG13))*AM13)*AS13)+AX13)*VLOOKUP("IN-34",'Assumptions & Inputs'!$A$31:$F$69,4,FALSE),0),0) -> 2650 | CC13: =IF(BQ13=1,((AK13+(IF(R13="IN-07",'Assumptions & Inputs'!$E$65,AH13))*AN13)*AS13)+AY13+(((AK13+(IF(R13="IN-07",'Assumptions & Inputs'!$E$65,AH13))*AN13)*AS13)*AZ13)+IF(BD13="Yes",(((AK13+(IF(R13="IN-07",'Assumptions & Inputs'!$E$65,AH13))*AN13)*AS13)+AY13)*VLOOKUP("IN-34",'Assumptions & Inputs'!$A$31:$F$69,5,FALSE),0),0) -> 4200 | CD13: =IF(BR13=1,((AI13+(IF(R13="IN-07",'Assumptions & Inputs'!$C$65,AF13))*AL13)*AS13)+AW13+(((AI13+(IF(R13="IN-07",'Assumptions & Inputs'!$C$65,AF13))*AL13)*AS13)*AZ13)+IF(BD13="Yes",(((AI13+(IF(R13="IN-07",'Assumptions & Inputs'!$C$65,AF13))*AL13)*AS13)+AW13)*VLOOKUP("IN-34",'Assumptions & Inputs'!$A$31:$F$69,3,FALSE),0),0) -> 1950 | CE13: =IF(BR13=1,((AJ13+(IF(R13="IN-07",'Assumptions & Inputs'!$D$65,AG13))*AM13)*AS13)+AX13+(((AJ13+(IF(R13="IN-07",'Assumptions & Inputs'!$D$65,AG13))*AM13)*AS13)*AZ13)+IF(BD13="Yes",(((AJ13+(IF(R13="IN-07",'Assumptions & Inputs'!$D$65,AG13))*AM13)*AS13)+AX13)*VLOOKUP("IN-34",'Assumptions & Inputs'!$A$31:$F$69,4,FALSE),0),0) -> 2650 | CF13: =IF(BR13=1,((AK13+(IF(R13="IN-07",'Assumptions & Inputs'!$E$65,AH13))*AN13)*AS13)+AY13+(((AK13+(IF(R13="IN-07",'Assumptions & Inputs'!$E$65,AH13))*AN13)*AS13)*AZ13)+IF(BD13="Yes",(((AK13+(IF(R13="IN-07",'Assumptions & Inputs'!$E$65,AH13))*AN13)*AS13)+AY13)*VLOOKUP("IN-34",'Assumptions & Inputs'!$A$31:$F$69,5,FALSE),0),0) -> 4200 | CG13: =IF(BS13=1,((AI13+(IF(R13="IN-07",0,AF13))*AL13)*AS13)+AW13+(((AI13+(IF(R13="IN-07",0,AF13))*AL13)*AS13)*AZ13)+IF(BD13="Yes",(((AI13+(IF(R13="IN-07",0,AF13))*AL13)*AS13)+AW13)*VLOOKUP("IN-34",'Assumptions & Inputs'!$A$31:$F$69,3,FALSE),0),0) -> 1950 | CH13: =IF(BS13=1,((AJ13+(IF(R13="IN-07",0,AG13))*AM13)*AS13)+AX13+(((AJ13+(IF(R13="IN-07",0,AG13))*AM13)*AS13)*AZ13)+IF(BD13="Yes",(((AJ13+(IF(R13="IN-07",0,AG13))*AM13)*AS13)+AX13)*VLOOKUP("IN-34",'Assumptions & Inputs'!$A$31:$F$69,4,FALSE),0),0) -> 2650 | CI13: =IF(BS13=1,((AK13+(IF(R13="IN-07",0,AH13))*AN13)*AS13)+AY13+(((AK13+(IF(R13="IN-07",0,AH13))*AN13)*AS13)*AZ13)+IF(BD13="Yes",(((AK13+(IF(R13="IN-07",0,AH13))*AN13)*AS13)+AY13)*VLOOKUP("IN-34",'Assumptions & Inputs'!$A$31:$F$69,5,FALSE),0),0) -> 4200 | CJ13: =IF(BT13=1,((AI13+(IF(R13="IN-07",0,AF13))*AL13)*AS13)+AW13+(((AI13+(IF(R13="IN-07",0,AF13))*AL13)*AS13)*AZ13)+IF(BD13="Yes",(((AI13+(IF(R13="IN-07",0,AF13))*AL13)*AS13)+AW13)*VLOOKUP("IN-34",'Assumptions & Inputs'!$A$31:$F$69,3,FALSE),0),0) -> 1950 | CK13: =IF(BT13=1,((AJ13+(IF(R13="IN-07",0,AG13))*AM13)*AS13)+AX13+(((AJ13+(IF(R13="IN-07",0,AG13))*AM13)*AS13)*AZ13)+IF(BD13="Yes",(((AJ13+(IF(R13="IN-07",0,AG13))*AM13)*AS13)+AX13)*VLOOKUP("IN-34",'Assumptions & Inputs'!$A$31:$F$69,4,FALSE),0),0) -> 2650 | CL13: =IF(BT13=1,((AK13+(IF(R13="IN-07",0,AH13))*AN13)*AS13)+AY13+(((AK13+(IF(R13="IN-07",0,AH13))*AN13)*AS13)*AZ13)+IF(BD13="Yes",(((AK13+(IF(R13="IN-07",0,AH13))*AN13)*AS13)+AY13)*VLOOKUP("IN-34",'Assumptions & Inputs'!$A$31:$F$69,5,FALSE),0),0) -> 4200
A14: WBS-01.08.02 | B14: WBS-01.08 | C14: State PHA | D14: Data specification and mapping | E14: Broad cascade incremental review | F14: Validate medication, follow-up, and utilization elements | G14: Perform incremental review required only for the broad longitudinal diabetes cascade. | H14: Approved broad-cascade requirements and limitations | I14: PHA | J14: PHA public health and clinical team | K14: Intermediary; providers | L14: PHA | M14: Funded | N14: 1B, 2B, 3B | O14: Broad-scope increment | P14: Fixed per use case | Q14: broad scope | R14: IN-16 | S14: Fixed hours | T14: Diabetes SME | U14: Epidemiologist; public health informatics lead | V14: PHA staff | W14: None | X14: PHA program lead | Y14: None material | Z14: Bottom-up labor estimate | AA14: BM-05 | AB14: High | AC14: A15; A20; A21; A30 | AD14: RD-02 | AE14: =IF(ISNUMBER(SEARCH('Scenario Definitions'!$C$5,N14)),1,0) -> 0 | AF14: =IFERROR(VLOOKUP(R14,'Assumptions & Inputs'!$A$31:$F$69,3,FALSE),0) -> 1 | AG14: =IFERROR(VLOOKUP(R14,'Assumptions & Inputs'!$A$31:$F$69,4,FALSE),0) -> 1 | AH14: =IFERROR(VLOOKUP(R14,'Assumptions & Inputs'!$A$31:$F$69,5,FALSE),0) -> 1 | AI14: 64.8 | AJ14: 86.4 | AK14: 129.6 | AL14: 0 | AM14: 0 | AN14: 0 | AO14: =AI14+(AF14*AL14) -> 64.8 | AP14: =AJ14+(AG14*AM14) -> 86.4 | AQ14: =AK14+(AH14*AN14) -> 129.6 | AR14: RT-03 | AS14: =IFERROR(VLOOKUP(AR14,'Assumptions & Inputs'!$A$73:$I$100,9,FALSE),0) -> 125 | AT14: =AO14*AS14 -> 8100 | AU14: =AP14*AS14 -> 10800 | AV14: =AQ14*AS14 -> 16200 | AW14: 0 | AX14: 0 | AY14: 0 | AZ14: =IFERROR(VLOOKUP(C14,'Assumptions & Inputs'!$A$104:$B$107,2,FALSE),0) -> 0.25 | BA14: =AT14*AZ14 -> 2025 | BB14: =AU14*AZ14 -> 2700 | BC14: =AV14*AZ14 -> 4050 | BD14: Yes | BE14: =IF(BD14="Yes",(AT14+AW14)*VLOOKUP("IN-34",'Assumptions & Inputs'!$A$31:$F$69,3,FALSE),0) -> 405 | BF14: =IF(BD14="Yes",(AU14+AX14)*VLOOKUP("IN-34",'Assumptions & Inputs'!$A$31:$F$69,4,FALSE),0) -> 810 | BG14: =IF(BD14="Yes",(AV14+AY14)*VLOOKUP("IN-34",'Assumptions & Inputs'!$A$31:$F$69,5,FALSE),0) -> 2430 | BH14: =AT14+AW14+BA14+BE14 -> 10530 | BI14: =AU14+AX14+BB14+BF14 -> 14310 | BJ14: =AV14+AY14+BC14+BG14 -> 22680 | BK14: Provisional — expert judgment | BL14: Pending participant validation | BM14: BM-05 | BN14: Provisional Stage 4 assumption; replace with actual rate, quote, or validated benchmark where available. | BO14: =IF(ISNUMBER(SEARCH("1A",N14)),1,0) -> 0 | BP14: =IF(ISNUMBER(SEARCH("1B",N14)),1,0) -> 1 | BQ14: =IF(ISNUMBER(SEARCH("2A",N14)),1,0) -> 0 | BR14: =IF(ISNUMBER(SEARCH("2B",N14)),1,0) -> 1 | BS14: =IF(ISNUMBER(SEARCH("3A",N14)),1,0) -> 0 | BT14: =IF(ISNUMBER(SEARCH("3B",N14)),1,0) -> 1 | BU14: =IF(BO14=1,((AI14+(IF(R14="IN-07",'Assumptions & Inputs'!$C$66,AF14))*AL14)*AS14)+AW14+(((AI14+(IF(R14="IN-07",'Assumptions & Inputs'!$C$66,AF14))*AL14)*AS14)*AZ14)+IF(BD14="Yes",(((AI14+(IF(R14="IN-07",'Assumptions & Inputs'!$C$66,AF14))*AL14)*AS14)+AW14)*VLOOKUP("IN-34",'Assumptions & Inputs'!$A$31:$F$69,3,FALSE),0),0) -> 0 | BV14: =IF(BO14=1,((AJ14+(IF(R14="IN-07",'Assumptions & Inputs'!$D$66,AG14))*AM14)*AS14)+AX14+(((AJ14+(IF(R14="IN-07",'Assumptions & Inputs'!$D$66,AG14))*AM14)*AS14)*AZ14)+IF(BD14="Yes",(((AJ14+(IF(R14="IN-07",'Assumptions & Inputs'!$D$66,AG14))*AM14)*AS14)+AX14)*VLOOKUP("IN-34",'Assumptions & Inputs'!$A$31:$F$69,4,FALSE),0),0) -> 0 | BW14: =IF(BO14=1,((AK14+(IF(R14="IN-07",'Assumptions & Inputs'!$E$66,AH14))*AN14)*AS14)+AY14+(((AK14+(IF(R14="IN-07",'Assumptions & Inputs'!$E$66,AH14))*AN14)*AS14)*AZ14)+IF(BD14="Yes",(((AK14+(IF(R14="IN-07",'Assumptions & Inputs'!$E$66,AH14))*AN14)*AS14)+AY14)*VLOOKUP("IN-34",'Assumptions & Inputs'!$A$31:$F$69,5,FALSE),0),0) -> 0 | BX14: =IF(BP14=1,((AI14+(IF(R14="IN-07",'Assumptions & Inputs'!$C$66,AF14))*AL14)*AS14)+AW14+(((AI14+(IF(R14="IN-07",'Assumptions & Inputs'!$C$66,AF14))*AL14)*AS14)*AZ14)+IF(BD14="Yes",(((AI14+(IF(R14="IN-07",'Assumptions & Inputs'!$C$66,AF14))*AL14)*AS14)+AW14)*VLOOKUP("IN-34",'Assumptions & Inputs'!$A$31:$F$69,3,FALSE),0),0) -> 10530 | BY14: =IF(BP14=1,((AJ14+(IF(R14="IN-07",'Assumptions & Inputs'!$D$66,AG14))*AM14)*AS14)+AX14+(((AJ14+(IF(R14="IN-07",'Assumptions & Inputs'!$D$66,AG14))*AM14)*AS14)*AZ14)+IF(BD14="Yes",(((AJ14+(IF(R14="IN-07",'Assumptions & Inputs'!$D$66,AG14))*AM14)*AS14)+AX14)*VLOOKUP("IN-34",'Assumptions & Inputs'!$A$31:$F$69,4,FALSE),0),0) -> 14310 | BZ14: =IF(BP14=1,((AK14+(IF(R14="IN-07",'Assumptions & Inputs'!$E$66,AH14))*AN14)*AS14)+AY14+(((AK14+(IF(R14="IN-07",'Assumptions & Inputs'!$E$66,AH14))*AN14)*AS14)*AZ14)+IF(BD14="Yes",(((AK14+(IF(R14="IN-07",'Assumptions & Inputs'!$E$66,AH14))*AN14)*AS14)+AY14)*VLOOKUP("IN-34",'Assumptions & Inputs'!$A$31:$F$69,5,FALSE),0),0) -> 22680 | CA14: =IF(BQ14=1,((AI14+(IF(R14="IN-07",'Assumptions & Inputs'!$C$65,AF14))*AL14)*AS14)+AW14+(((AI14+(IF(R14="IN-07",'Assumptions & Inputs'!$C$65,AF14))*AL14)*AS14)*AZ14)+IF(BD14="Yes",(((AI14+(IF(R14="IN-07",'Assumptions & Inputs'!$C$65,AF14))*AL14)*AS14)+AW14)*VLOOKUP("IN-34",'Assumptions & Inputs'!$A$31:$F$69,3,FALSE),0),0) -> 0 | CB14: =IF(BQ14=1,((AJ14+(IF(R14="IN-07",'Assumptions & Inputs'!$D$65,AG14))*AM14)*AS14)+AX14+(((AJ14+(IF(R14="IN-07",'Assumptions & Inputs'!$D$65,AG14))*AM14)*AS14)*AZ14)+IF(BD14="Yes",(((AJ14+(IF(R14="IN-07",'Assumptions & Inputs'!$D$65,AG14))*AM14)*AS14)+AX14)*VLOOKUP("IN-34",'Assumptions & Inputs'!$A$31:$F$69,4,FALSE),0),0) -> 0 | CC14: =IF(BQ14=1,((AK14+(IF(R14="IN-07",'Assumptions & Inputs'!$E$65,AH14))*AN14)*AS14)+AY14+(((AK14+(IF(R14="IN-07",'Assumptions & Inputs'!$E$65,AH14))*AN14)*AS14)*AZ14)+IF(BD14="Yes",(((AK14+(IF(R14="IN-07",'Assumptions & Inputs'!$E$65,AH14))*AN14)*AS14)+AY14)*VLOOKUP("IN-34",'Assumptions & Inputs'!$A$31:$F$69,5,FALSE),0),0) -> 0 | CD14: =IF(BR14=1,((AI14+(IF(R14="IN-07",'Assumptions & Inputs'!$C$65,AF14))*AL14)*AS14)+AW14+(((AI14+(IF(R14="IN-07",'Assumptions & Inputs'!$C$65,AF14))*AL14)*AS14)*AZ14)+IF(BD14="Yes",(((AI14+(IF(R14="IN-07",'Assumptions & Inputs'!$C$65,AF14))*AL14)*AS14)+AW14)*VLOOKUP("IN-34",'Assumptions & Inputs'!$A$31:$F$69,3,FALSE),0),0) -> 10530 | CE14: =IF(BR14=1,((AJ14+(IF(R14="IN-07",'Assumptions & Inputs'!$D$65,AG14))*AM14)*AS14)+AX14+(((AJ14+(IF(R14="IN-07",'Assumptions & Inputs'!$D$65,AG14))*AM14)*AS14)*AZ14)+IF(BD14="Yes",(((AJ14+(IF(R14="IN-07",'Assumptions & Inputs'!$D$65,AG14))*AM14)*AS14)+AX14)*VLOOKUP("IN-34",'Assumptions & Inputs'!$A$31:$F$69,4,FALSE),0),0) -> 14310 | CF14: =IF(BR14=1,((AK14+(IF(R14="IN-07",'Assumptions & Inputs'!$E$65,AH14))*AN14)*AS14)+AY14+(((AK14+(IF(R14="IN-07",'Assumptions & Inputs'!$E$65,AH14))*AN14)*AS14)*AZ14)+IF(BD14="Yes",(((AK14+(IF(R14="IN-07",'Assumptions & Inputs'!$E$65,AH14))*AN14)*AS14)+AY14)*VLOOKUP("IN-34",'Assumptions & Inputs'!$A$31:$F$69,5,FALSE),0),0) -> 22680 | CG14: =IF(BS14=1,((AI14+(IF(R14="IN-07",0,AF14))*AL14)*AS14)+AW14+(((AI14+(IF(R14="IN-07",0,AF14))*AL14)*AS14)*AZ14)+IF(BD14="Yes",(((AI14+(IF(R14="IN-07",0,AF14))*AL14)*AS14)+AW14)*VLOOKUP("IN-34",'Assumptions & Inputs'!$A$31:$F$69,3,FALSE),0),0) -> 0 | CH14: =IF(BS14=1,((AJ14+(IF(R14="IN-07",0,AG14))*AM14)*AS14)+AX14+(((AJ14+(IF(R14="IN-07",0,AG14))*AM14)*AS14)*AZ14)+IF(BD14="Yes",(((AJ14+(IF(R14="IN-07",0,AG14))*AM14)*AS14)+AX14)*VLOOKUP("IN-34",'Assumptions & Inputs'!$A$31:$F$69,4,FALSE),0),0) -> 0 | CI14: =IF(BS14=1,((AK14+(IF(R14="IN-07",0,AH14))*AN14)*AS14)+AY14+(((AK14+(IF(R14="IN-07",0,AH14))*AN14)*AS14)*AZ14)+IF(BD14="Yes",(((AK14+(IF(R14="IN-07",0,AH14))*AN14)*AS14)+AY14)*VLOOKUP("IN-34",'Assumptions & Inputs'!$A$31:$F$69,5,FALSE),0),0) -> 0 | CJ14: =IF(BT14=1,((AI14+(IF(R14="IN-07",0,AF14))*AL14)*AS14)+AW14+(((AI14+(IF(R14="IN-07",0,AF14))*AL14)*AS14)*AZ14)+IF(BD14="Yes",(((AI14+(IF(R14="IN-07",0,AF14))*AL14)*AS14)+AW14)*VLOOKUP("IN-34",'Assumptions & Inputs'!$A$31:$F$69,3,FALSE),0),0) -> 10530 | CK14: =IF(BT14=1,((AJ14+(IF(R14="IN-07",0,AG14))*AM14)*AS14)+AX14+(((AJ14+(IF(R14="IN-07",0,AG14))*AM14)*AS14)*AZ14)+IF(BD14="Yes",(((AJ14+(IF(R14="IN-07",0,AG14))*AM14)*AS14)+AX14)*VLOOKUP("IN-34",'Assumptions & Inputs'!$A$31:$F$69,4,FALSE),0),0) -> 14310 | CL14: =IF(BT14=1,((AK14+(IF(R14="IN-07",0,AH14))*AN14)*AS14)+AY14+(((AK14+(IF(R14="IN-07",0,AH14))*AN14)*AS14)*AZ14)+IF(BD14="Yes",(((AK14+(IF(R14="IN-07",0,AH14))*AN14)*AS14)+AY14)*VLOOKUP("IN-34",'Assumptions & Inputs'!$A$31:$F$69,5,FALSE),0),0) -> 22680
A15: WBS-01.09.01 | B15: WBS-01.09 | C15: State PHA | D15: Configuration and integration | E15: Receiving interface configuration | F15: Configure existing PHA intake process | G15: Configure secure scheduled receipt, schema validation, acknowledgments, retries, monitoring, and data loading. | H15: Operational PHA receiving interface | I15: PHA | J15: PHA platform team | K15: Intermediary; PHA security team | L15: PHA | M15: Funded | N15: 1A, 1B, 2A, 2B, 3A, 3B | O15: Base common | P15: Step-fixed | Q15: recipient interface | R15: IN-09 | S15: Interfaces × hours per interface | T15: Data engineer | U15: Cloud/DevOps engineer; security engineer; BI developer | V15: PHA staff | W15: Platform vendor if used | X15: PHA technical lead | Y15: Incremental cloud, software, or interface fees | Z15: Bottom-up labor estimate / vendor quote | AA15: BM-07 | AB15: High | AC15: A39; A41 | AD15: RD-04 | AE15: =IF(ISNUMBER(SEARCH('Scenario Definitions'!$C$5,N15)),1,0) -> 1 | AF15: =IFERROR(VLOOKUP(R15,'Assumptions & Inputs'!$A$31:$F$69,3,FALSE),0) -> 1 | AG15: =IFERROR(VLOOKUP(R15,'Assumptions & Inputs'!$A$31:$F$69,4,FALSE),0) -> 1 | AH15: =IFERROR(VLOOKUP(R15,'Assumptions & Inputs'!$A$31:$F$69,5,FALSE),0) -> 1 | AI15: 0 | AJ15: 0 | AK15: 0 | AL15: 40.5 | AM15: 54 | AN15: 81 | AO15: =AI15+(AF15*AL15) -> 40.5 | AP15: =AJ15+(AG15*AM15) -> 54 | AQ15: =AK15+(AH15*AN15) -> 81 | AR15: RT-04 | AS15: =IFERROR(VLOOKUP(AR15,'Assumptions & Inputs'!$A$73:$I$100,9,FALSE),0) -> 135 | AT15: =AO15*AS15 -> 5467.5 | AU15: =AP15*AS15 -> 7290 | AV15: =AQ15*AS15 -> 10935 | AW15: 10000 | AX15: 25000 | AY15: 60000 | AZ15: =IFERROR(VLOOKUP(C15,'Assumptions & Inputs'!$A$104:$B$107,2,FALSE),0) -> 0.25 | BA15: =AT15*AZ15 -> 1366.875 | BB15: =AU15*AZ15 -> 1822.5 | BC15: =AV15*AZ15 -> 2733.75 | BD15: Yes | BE15: =IF(BD15="Yes",(AT15+AW15)*VLOOKUP("IN-34",'Assumptions & Inputs'!$A$31:$F$69,3,FALSE),0) -> 773.375 | BF15: =IF(BD15="Yes",(AU15+AX15)*VLOOKUP("IN-34",'Assumptions & Inputs'!$A$31:$F$69,4,FALSE),0) -> 2421.75 | BG15: =IF(BD15="Yes",(AV15+AY15)*VLOOKUP("IN-34",'Assumptions & Inputs'!$A$31:$F$69,5,FALSE),0) -> 10640.25 | BH15: =AT15+AW15+BA15+BE15 -> 17607.75 | BI15: =AU15+AX15+BB15+BF15 -> 36534.25 | BJ15: =AV15+AY15+BC15+BG15 -> 84309 | BK15: Provisional — expert judgment | BL15: Pending participant validation | BM15: BM-07 | BN15: Provisional Stage 4 assumption; replace with actual rate, quote, or validated benchmark where available. | BO15: =IF(ISNUMBER(SEARCH("1A",N15)),1,0) -> 1 | BP15: =IF(ISNUMBER(SEARCH("1B",N15)),1,0) -> 1 | BQ15: =IF(ISNUMBER(SEARCH("2A",N15)),1,0) -> 1 | BR15: =IF(ISNUMBER(SEARCH("2B",N15)),1,0) -> 1 | BS15: =IF(ISNUMBER(SEARCH("3A",N15)),1,0) -> 1 | BT15: =IF(ISNUMBER(SEARCH("3B",N15)),1,0) -> 1 | BU15: =IF(BO15=1,((AI15+(IF(R15="IN-07",'Assumptions & Inputs'!$C$66,AF15))*AL15)*AS15)+AW15+(((AI15+(IF(R15="IN-07",'Assumptions & Inputs'!$C$66,AF15))*AL15)*AS15)*AZ15)+IF(BD15="Yes",(((AI15+(IF(R15="IN-07",'Assumptions & Inputs'!$C$66,AF15))*AL15)*AS15)+AW15)*VLOOKUP("IN-34",'Assumptions & Inputs'!$A$31:$F$69,3,FALSE),0),0) -> 17607.75 | BV15: =IF(BO15=1,((AJ15+(IF(R15="IN-07",'Assumptions & Inputs'!$D$66,AG15))*AM15)*AS15)+AX15+(((AJ15+(IF(R15="IN-07",'Assumptions & Inputs'!$D$66,AG15))*AM15)*AS15)*AZ15)+IF(BD15="Yes",(((AJ15+(IF(R15="IN-07",'Assumptions & Inputs'!$D$66,AG15))*AM15)*AS15)+AX15)*VLOOKUP("IN-34",'Assumptions & Inputs'!$A$31:$F$69,4,FALSE),0),0) -> 36534.25 | BW15: =IF(BO15=1,((AK15+(IF(R15="IN-07",'Assumptions & Inputs'!$E$66,AH15))*AN15)*AS15)+AY15+(((AK15+(IF(R15="IN-07",'Assumptions & Inputs'!$E$66,AH15))*AN15)*AS15)*AZ15)+IF(BD15="Yes",(((AK15+(IF(R15="IN-07",'Assumptions & Inputs'!$E$66,AH15))*AN15)*AS15)+AY15)*VLOOKUP("IN-34",'Assumptions & Inputs'!$A$31:$F$69,5,FALSE),0),0) -> 84309 | BX15: =IF(BP15=1,((AI15+(IF(R15="IN-07",'Assumptions & Inputs'!$C$66,AF15))*AL15)*AS15)+AW15+(((AI15+(IF(R15="IN-07",'Assumptions & Inputs'!$C$66,AF15))*AL15)*AS15)*AZ15)+IF(BD15="Yes",(((AI15+(IF(R15="IN-07",'Assumptions & Inputs'!$C$66,AF15))*AL15)*AS15)+AW15)*VLOOKUP("IN-34",'Assumptions & Inputs'!$A$31:$F$69,3,FALSE),0),0) -> 17607.75 | BY15: =IF(BP15=1,((AJ15+(IF(R15="IN-07",'Assumptions & Inputs'!$D$66,AG15))*AM15)*AS15)+AX15+(((AJ15+(IF(R15="IN-07",'Assumptions & Inputs'!$D$66,AG15))*AM15)*AS15)*AZ15)+IF(BD15="Yes",(((AJ15+(IF(R15="IN-07",'Assumptions & Inputs'!$D$66,AG15))*AM15)*AS15)+AX15)*VLOOKUP("IN-34",'Assumptions & Inputs'!$A$31:$F$69,4,FALSE),0),0) -> 36534.25 | BZ15: =IF(BP15=1,((AK15+(IF(R15="IN-07",'Assumptions & Inputs'!$E$66,AH15))*AN15)*AS15)+AY15+(((AK15+(IF(R15="IN-07",'Assumptions & Inputs'!$E$66,AH15))*AN15)*AS15)*AZ15)+IF(BD15="Yes",(((AK15+(IF(R15="IN-07",'Assumptions & Inputs'!$E$66,AH15))*AN15)*AS15)+AY15)*VLOOKUP("IN-34",'Assumptions & Inputs'!$A$31:$F$69,5,FALSE),0),0) -> 84309 | CA15: =IF(BQ15=1,((AI15+(IF(R15="IN-07",'Assumptions & Inputs'!$C$65,AF15))*AL15)*AS15)+AW15+(((AI15+(IF(R15="IN-07",'Assumptions & Inputs'!$C$65,AF15))*AL15)*AS15)*AZ15)+IF(BD15="Yes",(((AI15+(IF(R15="IN-07",'Assumptions & Inputs'!$C$65,AF15))*AL15)*AS15)+AW15)*VLOOKUP("IN-34",'Assumptions & Inputs'!$A$31:$F$69,3,FALSE),0),0) -> 17607.75 | CB15: =IF(BQ15=1,((AJ15+(IF(R15="IN-07",'Assumptions & Inputs'!$D$65,AG15))*AM15)*AS15)+AX15+(((AJ15+(IF(R15="IN-07",'Assumptions & Inputs'!$D$65,AG15))*AM15)*AS15)*AZ15)+IF(BD15="Yes",(((AJ15+(IF(R15="IN-07",'Assumptions & Inputs'!$D$65,AG15))*AM15)*AS15)+AX15)*VLOOKUP("IN-34",'Assumptions & Inputs'!$A$31:$F$69,4,FALSE),0),0) -> 36534.25 | CC15: =IF(BQ15=1,((AK15+(IF(R15="IN-07",'Assumptions & Inputs'!$E$65,AH15))*AN15)*AS15)+AY15+(((AK15+(IF(R15="IN-07",'Assumptions & Inputs'!$E$65,AH15))*AN15)*AS15)*AZ15)+IF(BD15="Yes",(((AK15+(IF(R15="IN-07",'Assumptions & Inputs'!$E$65,AH15))*AN15)*AS15)+AY15)*VLOOKUP("IN-34",'Assumptions & Inputs'!$A$31:$F$69,5,FALSE),0),0) -> 84309 | CD15: =IF(BR15=1,((AI15+(IF(R15="IN-07",'Assumptions & Inputs'!$C$65,AF15))*AL15)*AS15)+AW15+(((AI15+(IF(R15="IN-07",'Assumptions & Inputs'!$C$65,AF15))*AL15)*AS15)*AZ15)+IF(BD15="Yes",(((AI15+(IF(R15="IN-07",'Assumptions & Inputs'!$C$65,AF15))*AL15)*AS15)+AW15)*VLOOKUP("IN-34",'Assumptions & Inputs'!$A$31:$F$69,3,FALSE),0),0) -> 17607.75 | CE15: =IF(BR15=1,((AJ15+(IF(R15="IN-07",'Assumptions & Inputs'!$D$65,AG15))*AM15)*AS15)+AX15+(((AJ15+(IF(R15="IN-07",'Assumptions & Inputs'!$D$65,AG15))*AM15)*AS15)*AZ15)+IF(BD15="Yes",(((AJ15+(IF(R15="IN-07",'Assumptions & Inputs'!$D$65,AG15))*AM15)*AS15)+AX15)*VLOOKUP("IN-34",'Assumptions & Inputs'!$A$31:$F$69,4,FALSE),0),0) -> 36534.25 | CF15: =IF(BR15=1,((AK15+(IF(R15="IN-07",'Assumptions & Inputs'!$E$65,AH15))*AN15)*AS15)+AY15+(((AK15+(IF(R15="IN-07",'Assumptions & Inputs'!$E$65,AH15))*AN15)*AS15)*AZ15)+IF(BD15="Yes",(((AK15+(IF(R15="IN-07",'Assumptions & Inputs'!$E$65,AH15))*AN15)*AS15)+AY15)*VLOOKUP("IN-34",'Assumptions & Inputs'!$A$31:$F$69,5,FALSE),0),0) -> 84309 | CG15: =IF(BS15=1,((AI15+(IF(R15="IN-07",0,AF15))*AL15)*AS15)+AW15+(((AI15+(IF(R15="IN-07",0,AF15))*AL15)*AS15)*AZ15)+IF(BD15="Yes",(((AI15+(IF(R15="IN-07",0,AF15))*AL15)*AS15)+AW15)*VLOOKUP("IN-34",'Assumptions & Inputs'!$A$31:$F$69,3,FALSE),0),0) -> 17607.75 | CH15: =IF(BS15=1,((AJ15+(IF(R15="IN-07",0,AG15))*AM15)*AS15)+AX15+(((AJ15+(IF(R15="IN-07",0,AG15))*AM15)*AS15)*AZ15)+IF(BD15="Yes",(((AJ15+(IF(R15="IN-07",0,AG15))*AM15)*AS15)+AX15)*VLOOKUP("IN-34",'Assumptions & Inputs'!$A$31:$F$69,4,FALSE),0),0) -> 36534.25 | CI15: =IF(BS15=1,((AK15+(IF(R15="IN-07",0,AH15))*AN15)*AS15)+AY15+(((AK15+(IF(R15="IN-07",0,AH15))*AN15)*AS15)*AZ15)+IF(BD15="Yes",(((AK15+(IF(R15="IN-07",0,AH15))*AN15)*AS15)+AY15)*VLOOKUP("IN-34",'Assumptions & Inputs'!$A$31:$F$69,5,FALSE),0),0) -> 84309 | CJ15: =IF(BT15=1,((AI15+(IF(R15="IN-07",0,AF15))*AL15)*AS15)+AW15+(((AI15+(IF(R15="IN-07",0,AF15))*AL15)*AS15)*AZ15)+IF(BD15="Yes",(((AI15+(IF(R15="IN-07",0,AF15))*AL15)*AS15)+AW15)*VLOOKUP("IN-34",'Assumptions & Inputs'!$A$31:$F$69,3,FALSE),0),0) -> 17607.75 | CK15: =IF(BT15=1,((AJ15+(IF(R15="IN-07",0,AG15))*AM15)*AS15)+AX15+(((AJ15+(IF(R15="IN-07",0,AG15))*AM15)*AS15)*AZ15)+IF(BD15="Yes",(((AJ15+(IF(R15="IN-07",0,AG15))*AM15)*AS15)+AX15)*VLOOKUP("IN-34",'Assumptions & Inputs'!$A$31:$F$69,4,FALSE),0),0) -> 36534.25 | CL15: =IF(BT15=1,((AK15+(IF(R15="IN-07",0,AH15))*AN15)*AS15)+AY15+(((AK15+(IF(R15="IN-07",0,AH15))*AN15)*AS15)*AZ15)+IF(BD15="Yes",(((AK15+(IF(R15="IN-07",0,AH15))*AN15)*AS15)+AY15)*VLOOKUP("IN-34",'Assumptions & Inputs'!$A$31:$F$69,5,FALSE),0),0) -> 84309
A16: WBS-01.10.01 | B16: WBS-01.10 | C16: State PHA | D16: Configuration and integration | E16: Analytics configuration | F16: Configure PHA surveillance views and data products | G16: Configure the existing analytics environment for prevalence, A1c testing, poor control, and approved stratifications. | H16: Configured and documented PHA analytics output | I16: PHA | J16: PHA analytics team | K16: Intermediary | L16: PHA | M16: Funded | N16: 1A, 1B, 2A, 2B, 3A, 3B | O16: Base common | P16: Fixed per output | Q16: analytic output | R16: IN-13 | S16: Quantity × hours per unit | T16: BI developer | U16: PHA data analyst; epidemiologist; data engineer | V16: PHA staff | W16: Analytics vendor if used | X16: PHA program lead | Y16: Incremental BI or platform license only if needed | Z16: Bottom-up labor estimate | AA16: BM-06 | AB16: Moderate | AC16: A17; A39; A40 | AD16: RD-16 | AE16: =IF(ISNUMBER(SEARCH('Scenario Definitions'!$C$5,N16)),1,0) -> 1 | AF16: =IFERROR(VLOOKUP(R16,'Assumptions & Inputs'!$A$31:$F$69,3,FALSE),0) -> 1 | AG16: =IFERROR(VLOOKUP(R16,'Assumptions & Inputs'!$A$31:$F$69,4,FALSE),0) -> 1 | AH16: =IFERROR(VLOOKUP(R16,'Assumptions & Inputs'!$A$31:$F$69,5,FALSE),0) -> 2 | AI16: 0 | AJ16: 0 | AK16: 0 | AL16: 12 | AM16: 16 | AN16: 24 | AO16: =AI16+(AF16*AL16) -> 12 | AP16: =AJ16+(AG16*AM16) -> 16 | AQ16: =AK16+(AH16*AN16) -> 48 | AR16: RT-04 | AS16: =IFERROR(VLOOKUP(AR16,'Assumptions & Inputs'!$A$73:$I$100,9,FALSE),0) -> 135 | AT16: =AO16*AS16 -> 1620 | AU16: =AP16*AS16 -> 2160 | AV16: =AQ16*AS16 -> 6480 | AW16: 0 | AX16: 10000 | AY16: 40000 | AZ16: =IFERROR(VLOOKUP(C16,'Assumptions & Inputs'!$A$104:$B$107,2,FALSE),0) -> 0.25 | BA16: =AT16*AZ16 -> 405 | BB16: =AU16*AZ16 -> 540 | BC16: =AV16*AZ16 -> 1620 | BD16: Yes | BE16: =IF(BD16="Yes",(AT16+AW16)*VLOOKUP("IN-34",'Assumptions & Inputs'!$A$31:$F$69,3,FALSE),0) -> 81 | BF16: =IF(BD16="Yes",(AU16+AX16)*VLOOKUP("IN-34",'Assumptions & Inputs'!$A$31:$F$69,4,FALSE),0) -> 912 | BG16: =IF(BD16="Yes",(AV16+AY16)*VLOOKUP("IN-34",'Assumptions & Inputs'!$A$31:$F$69,5,FALSE),0) -> 6972 | BH16: =AT16+AW16+BA16+BE16 -> 2106 | BI16: =AU16+AX16+BB16+BF16 -> 13612 | BJ16: =AV16+AY16+BC16+BG16 -> 55072 | BK16: Provisional — expert judgment | BL16: Pending participant validation | BM16: BM-06 | BN16: Provisional Stage 4 assumption; replace with actual rate, quote, or validated benchmark where available. | BO16: =IF(ISNUMBER(SEARCH("1A",N16)),1,0) -> 1 | BP16: =IF(ISNUMBER(SEARCH("1B",N16)),1,0) -> 1 | BQ16: =IF(ISNUMBER(SEARCH("2A",N16)),1,0) -> 1 | BR16: =IF(ISNUMBER(SEARCH("2B",N16)),1,0) -> 1 | BS16: =IF(ISNUMBER(SEARCH("3A",N16)),1,0) -> 1 | BT16: =IF(ISNUMBER(SEARCH("3B",N16)),1,0) -> 1 | BU16: =IF(BO16=1,((AI16+(IF(R16="IN-07",'Assumptions & Inputs'!$C$66,AF16))*AL16)*AS16)+AW16+(((AI16+(IF(R16="IN-07",'Assumptions & Inputs'!$C$66,AF16))*AL16)*AS16)*AZ16)+IF(BD16="Yes",(((AI16+(IF(R16="IN-07",'Assumptions & Inputs'!$C$66,AF16))*AL16)*AS16)+AW16)*VLOOKUP("IN-34",'Assumptions & Inputs'!$A$31:$F$69,3,FALSE),0),0) -> 2106 | BV16: =IF(BO16=1,((AJ16+(IF(R16="IN-07",'Assumptions & Inputs'!$D$66,AG16))*AM16)*AS16)+AX16+(((AJ16+(IF(R16="IN-07",'Assumptions & Inputs'!$D$66,AG16))*AM16)*AS16)*AZ16)+IF(BD16="Yes",(((AJ16+(IF(R16="IN-07",'Assumptions & Inputs'!$D$66,AG16))*AM16)*AS16)+AX16)*VLOOKUP("IN-34",'Assumptions & Inputs'!$A$31:$F$69,4,FALSE),0),0) -> 13612 | BW16: =IF(BO16=1,((AK16+(IF(R16="IN-07",'Assumptions & Inputs'!$E$66,AH16))*AN16)*AS16)+AY16+(((AK16+(IF(R16="IN-07",'Assumptions & Inputs'!$E$66,AH16))*AN16)*AS16)*AZ16)+IF(BD16="Yes",(((AK16+(IF(R16="IN-07",'Assumptions & Inputs'!$E$66,AH16))*AN16)*AS16)+AY16)*VLOOKUP("IN-34",'Assumptions & Inputs'!$A$31:$F$69,5,FALSE),0),0) -> 55072 | BX16: =IF(BP16=1,((AI16+(IF(R16="IN-07",'Assumptions & Inputs'!$C$66,AF16))*AL16)*AS16)+AW16+(((AI16+(IF(R16="IN-07",'Assumptions & Inputs'!$C$66,AF16))*AL16)*AS16)*AZ16)+IF(BD16="Yes",(((AI16+(IF(R16="IN-07",'Assumptions & Inputs'!$C$66,AF16))*AL16)*AS16)+AW16)*VLOOKUP("IN-34",'Assumptions & Inputs'!$A$31:$F$69,3,FALSE),0),0) -> 2106 | BY16: =IF(BP16=1,((AJ16+(IF(R16="IN-07",'Assumptions & Inputs'!$D$66,AG16))*AM16)*AS16)+AX16+(((AJ16+(IF(R16="IN-07",'Assumptions & Inputs'!$D$66,AG16))*AM16)*AS16)*AZ16)+IF(BD16="Yes",(((AJ16+(IF(R16="IN-07",'Assumptions & Inputs'!$D$66,AG16))*AM16)*AS16)+AX16)*VLOOKUP("IN-34",'Assumptions & Inputs'!$A$31:$F$69,4,FALSE),0),0) -> 13612 | BZ16: =IF(BP16=1,((AK16+(IF(R16="IN-07",'Assumptions & Inputs'!$E$66,AH16))*AN16)*AS16)+AY16+(((AK16+(IF(R16="IN-07",'Assumptions & Inputs'!$E$66,AH16))*AN16)*AS16)*AZ16)+IF(BD16="Yes",(((AK16+(IF(R16="IN-07",'Assumptions & Inputs'!$E$66,AH16))*AN16)*AS16)+AY16)*VLOOKUP("IN-34",'Assumptions & Inputs'!$A$31:$F$69,5,FALSE),0),0) -> 55072 | CA16: =IF(BQ16=1,((AI16+(IF(R16="IN-07",'Assumptions & Inputs'!$C$65,AF16))*AL16)*AS16)+AW16+(((AI16+(IF(R16="IN-07",'Assumptions & Inputs'!$C$65,AF16))*AL16)*AS16)*AZ16)+IF(BD16="Yes",(((AI16+(IF(R16="IN-07",'Assumptions & Inputs'!$C$65,AF16))*AL16)*AS16)+AW16)*VLOOKUP("IN-34",'Assumptions & Inputs'!$A$31:$F$69,3,FALSE),0),0) -> 2106 | CB16: =IF(BQ16=1,((AJ16+(IF(R16="IN-07",'Assumptions & Inputs'!$D$65,AG16))*AM16)*AS16)+AX16+(((AJ16+(IF(R16="IN-07",'Assumptions & Inputs'!$D$65,AG16))*AM16)*AS16)*AZ16)+IF(BD16="Yes",(((AJ16+(IF(R16="IN-07",'Assumptions & Inputs'!$D$65,AG16))*AM16)*AS16)+AX16)*VLOOKUP("IN-34",'Assumptions & Inputs'!$A$31:$F$69,4,FALSE),0),0) -> 13612 | CC16: =IF(BQ16=1,((AK16+(IF(R16="IN-07",'Assumptions & Inputs'!$E$65,AH16))*AN16)*AS16)+AY16+(((AK16+(IF(R16="IN-07",'Assumptions & Inputs'!$E$65,AH16))*AN16)*AS16)*AZ16)+IF(BD16="Yes",(((AK16+(IF(R16="IN-07",'Assumptions & Inputs'!$E$65,AH16))*AN16)*AS16)+AY16)*VLOOKUP("IN-34",'Assumptions & Inputs'!$A$31:$F$69,5,FALSE),0),0) -> 55072 | CD16: =IF(BR16=1,((AI16+(IF(R16="IN-07",'Assumptions & Inputs'!$C$65,AF16))*AL16)*AS16)+AW16+(((AI16+(IF(R16="IN-07",'Assumptions & Inputs'!$C$65,AF16))*AL16)*AS16)*AZ16)+IF(BD16="Yes",(((AI16+(IF(R16="IN-07",'Assumptions & Inputs'!$C$65,AF16))*AL16)*AS16)+AW16)*VLOOKUP("IN-34",'Assumptions & Inputs'!$A$31:$F$69,3,FALSE),0),0) -> 2106 | CE16: =IF(BR16=1,((AJ16+(IF(R16="IN-07",'Assumptions & Inputs'!$D$65,AG16))*AM16)*AS16)+AX16+(((AJ16+(IF(R16="IN-07",'Assumptions & Inputs'!$D$65,AG16))*AM16)*AS16)*AZ16)+IF(BD16="Yes",(((AJ16+(IF(R16="IN-07",'Assumptions & Inputs'!$D$65,AG16))*AM16)*AS16)+AX16)*VLOOKUP("IN-34",'Assumptions & Inputs'!$A$31:$F$69,4,FALSE),0),0) -> 13612 | CF16: =IF(BR16=1,((AK16+(IF(R16="IN-07",'Assumptions & Inputs'!$E$65,AH16))*AN16)*AS16)+AY16+(((AK16+(IF(R16="IN-07",'Assumptions & Inputs'!$E$65,AH16))*AN16)*AS16)*AZ16)+IF(BD16="Yes",(((AK16+(IF(R16="IN-07",'Assumptions & Inputs'!$E$65,AH16))*AN16)*AS16)+AY16)*VLOOKUP("IN-34",'Assumptions & Inputs'!$A$31:$F$69,5,FALSE),0),0) -> 55072 | CG16: =IF(BS16=1,((AI16+(IF(R16="IN-07",0,AF16))*AL16)*AS16)+AW16+(((AI16+(IF(R16="IN-07",0,AF16))*AL16)*AS16)*AZ16)+IF(BD16="Yes",(((AI16+(IF(R16="IN-07",0,AF16))*AL16)*AS16)+AW16)*VLOOKUP("IN-34",'Assumptions & Inputs'!$A$31:$F$69,3,FALSE),0),0) -> 2106 | CH16: =IF(BS16=1,((AJ16+(IF(R16="IN-07",0,AG16))*AM16)*AS16)+AX16+(((AJ16+(IF(R16="IN-07",0,AG16))*AM16)*AS16)*AZ16)+IF(BD16="Yes",(((AJ16+(IF(R16="IN-07",0,AG16))*AM16)*AS16)+AX16)*VLOOKUP("IN-34",'Assumptions & Inputs'!$A$31:$F$69,4,FALSE),0),0) -> 13612 | CI16: =IF(BS16=1,((AK16+(IF(R16="IN-07",0,AH16))*AN16)*AS16)+AY16+(((AK16+(IF(R16="IN-07",0,AH16))*AN16)*AS16)*AZ16)+IF(BD16="Yes",(((AK16+(IF(R16="IN-07",0,AH16))*AN16)*AS16)+AY16)*VLOOKUP("IN-34",'Assumptions & Inputs'!$A$31:$F$69,5,FALSE),0),0) -> 55072 | CJ16: =IF(BT16=1,((AI16+(IF(R16="IN-07",0,AF16))*AL16)*AS16)+AW16+(((AI16+(IF(R16="IN-07",0,AF16))*AL16)*AS16)*AZ16)+IF(BD16="Yes",(((AI16+(IF(R16="IN-07",0,AF16))*AL16)*AS16)+AW16)*VLOOKUP("IN-34",'Assumptions & Inputs'!$A$31:$F$69,3,FALSE),0),0) -> 2106 | CK16: =IF(BT16=1,((AJ16+(IF(R16="IN-07",0,AG16))*AM16)*AS16)+AX16+(((AJ16+(IF(R16="IN-07",0,AG16))*AM16)*AS16)*AZ16)+IF(BD16="Yes",(((AJ16+(IF(R16="IN-07",0,AG16))*AM16)*AS16)+AX16)*VLOOKUP("IN-34",'Assumptions & Inputs'!$A$31:$F$69,4,FALSE),0),0) -> 13612 | CL16: =IF(BT16=1,((AK16+(IF(R16="IN-07",0,AH16))*AN16)*AS16)+AY16+(((AK16+(IF(R16="IN-07",0,AH16))*AN16)*AS16)*AZ16)+IF(BD16="Yes",(((AK16+(IF(R16="IN-07",0,AH16))*AN16)*AS16)+AY16)*VLOOKUP("IN-34",'Assumptions & Inputs'!$A$31:$F$69,5,FALSE),0),0) -> 55072
... A77: WBS-04.14.01 | B77: WBS-04.14 | C77: Healthcare Organizations & FQHCs | D77: Evaluation, playbook, and closeout | E77: Provider closeout | F77: Complete access, data, contract, and operational closeout | G77: Confirm final data handling, access termination or transition, outstanding issue ownership, and final invoicing. | H77: Provider closeout confirmation | I77: Provider organization | J77: Provider project/legal/IT teams | K77: HCCN/HDU; PHA | L77: Provider organization | M77: Funded | N77: 1A, 1B, 2A, 2B, 3A, 3B | O77: Base common | P77: Variable | Q77: provider organization | R77: IN-04 | S77: Organizations × hours per organization | T77: Provider project lead | U77: Legal counsel; privacy specialist; provider IT lead | V77: Provider staff | W77: None | X77: PHA project manager | Y77: None material | Z77: Bottom-up labor estimate | AA77: BM-14 | AB77: Moderate | AC77: A66; A78 | AD77: RD-23 | AE77: =IF(ISNUMBER(SEARCH('Scenario Definitions'!$C$5,N77)),1,0) -> 1 | AF77: =IFERROR(VLOOKUP(R77,'Assumptions & Inputs'!$A$31:$F$69,3,FALSE),0) -> 6 | AG77: =IFERROR(VLOOKUP(R77,'Assumptions & Inputs'!$A$31:$F$69,4,FALSE),0) -> 12 | AH77: =IFERROR(VLOOKUP(R77,'Assumptions & Inputs'!$A$31:$F$69,5,FALSE),0) -> 25 | AI77: 0 | AJ77: 0 | AK77: 0 | AL77: 9 | AM77: 12 | AN77: 18 | AO77: =AI77+(AF77*AL77) -> 54 | AP77: =AJ77+(AG77*AM77) -> 144 | AQ77: =AK77+(AH77*AN77) -> 450 | AR77: RT-26 | AS77: =IFERROR(VLOOKUP(AR77,'Assumptions & Inputs'!$A$73:$I$100,9,FALSE),0) -> 95 | AT77: =AO77*AS77 -> 5130 | AU77: =AP77*AS77 -> 13680 | AV77: =AQ77*AS77 -> 42750 | AW77: 0 | AX77: 0 | AY77: 0 | AZ77: =IFERROR(VLOOKUP(C77,'Assumptions & Inputs'!$A$104:$B$107,2,FALSE),0) -> 0.25 | BA77: =AT77*AZ77 -> 1282.5 | BB77: =AU77*AZ77 -> 3420 | BC77: =AV77*AZ77 -> 10687.5 | BD77: Yes | BE77: =IF(BD77="Yes",(AT77+AW77)*VLOOKUP("IN-34",'Assumptions & Inputs'!$A$31:$F$69,3,FALSE),0) -> 256.5 | BF77: =IF(BD77="Yes",(AU77+AX77)*VLOOKUP("IN-34",'Assumptions & Inputs'!$A$31:$F$69,4,FALSE),0) -> 1026 | BG77: =IF(BD77="Yes",(AV77+AY77)*VLOOKUP("IN-34",'Assumptions & Inputs'!$A$31:$F$69,5,FALSE),0) -> 6412.5 | BH77: =AT77+AW77+BA77+BE77 -> 6669 | BI77: =AU77+AX77+BB77+BF77 -> 18126 | BJ77: =AV77+AY77+BC77+BG77 -> 59850 | BK77: Provisional — expert judgment | BL77: Pending participant validation | BM77: BM-14 | BN77: Provisional Stage 4 assumption; replace with actual rate, quote, or validated benchmark where available. | BO77: =IF(ISNUMBER(SEARCH("1A",N77)),1,0) -> 1 | BP77: =IF(ISNUMBER(SEARCH("1B",N77)),1,0) -> 1 | BQ77: =IF(ISNUMBER(SEARCH("2A",N77)),1,0) -> 1 | BR77: =IF(ISNUMBER(SEARCH("2B",N77)),1,0) -> 1 | BS77: =IF(ISNUMBER(SEARCH("3A",N77)),1,0) -> 1 | BT77: =IF(ISNUMBER(SEARCH("3B",N77)),1,0) -> 1 | BU77: =IF(BO77=1,((AI77+(IF(R77="IN-07",'Assumptions & Inputs'!$C$66,AF77))*AL77)*AS77)+AW77+(((AI77+(IF(R77="IN-07",'Assumptions & Inputs'!$C$66,AF77))*AL77)*AS77)*AZ77)+IF(BD77="Yes",(((AI77+(IF(R77="IN-07",'Assumptions & Inputs'!$C$66,AF77))*AL77)*AS77)+AW77)*VLOOKUP("IN-34",'Assumptions & Inputs'!$A$31:$F$69,3,FALSE),0),0) -> 6669 | BV77: =IF(BO77=1,((AJ77+(IF(R77="IN-07",'Assumptions & Inputs'!$D$66,AG77))*AM77)*AS77)+AX77+(((AJ77+(IF(R77="IN-07",'Assumptions & Inputs'!$D$66,AG77))*AM77)*AS77)*AZ77)+IF(BD77="Yes",(((AJ77+(IF(R77="IN-07",'Assumptions & Inputs'!$D$66,AG77))*AM77)*AS77)+AX77)*VLOOKUP("IN-34",'Assumptions & Inputs'!$A$31:$F$69,4,FALSE),0),0) -> 18126 | BW77: =IF(BO77=1,((AK77+(IF(R77="IN-07",'Assumptions & Inputs'!$E$66,AH77))*AN77)*AS77)+AY77+(((AK77+(IF(R77="IN-07",'Assumptions & Inputs'!$E$66,AH77))*AN77)*AS77)*AZ77)+IF(BD77="Yes",(((AK77+(IF(R77="IN-07",'Assumptions & Inputs'!$E$66,AH77))*AN77)*AS77)+AY77)*VLOOKUP("IN-34",'Assumptions & Inputs'!$A$31:$F$69,5,FALSE),0),0) -> 59850 | BX77: =IF(BP77=1,((AI77+(IF(R77="IN-07",'Assumptions & Inputs'!$C$66,AF77))*AL77)*AS77)+AW77+(((AI77+(IF(R77="IN-07",'Assumptions & Inputs'!$C$66,AF77))*AL77)*AS77)*AZ77)+IF(BD77="Yes",(((AI77+(IF(R77="IN-07",'Assumptions & Inputs'!$C$66,AF77))*AL77)*AS77)+AW77)*VLOOKUP("IN-34",'Assumptions & Inputs'!$A$31:$F$69,3,FALSE),0),0) -> 6669 | BY77: =IF(BP77=1,((AJ77+(IF(R77="IN-07",'Assumptions & Inputs'!$D$66,AG77))*AM77)*AS77)+AX77+(((AJ77+(IF(R77="IN-07",'Assumptions & Inputs'!$D$66,AG77))*AM77)*AS77)*AZ77)+IF(BD77="Yes",(((AJ77+(IF(R77="IN-07",'Assumptions & Inputs'!$D$66,AG77))*AM77)*AS77)+AX77)*VLOOKUP("IN-34",'Assumptions & Inputs'!$A$31:$F$69,4,FALSE),0),0) -> 18126 | BZ77: =IF(BP77=1,((AK77+(IF(R77="IN-07",'Assumptions & Inputs'!$E$66,AH77))*AN77)*AS77)+AY77+(((AK77+(IF(R77="IN-07",'Assumptions & Inputs'!$E$66,AH77))*AN77)*AS77)*AZ77)+IF(BD77="Yes",(((AK77+(IF(R77="IN-07",'Assumptions & Inputs'!$E$66,AH77))*AN77)*AS77)+AY77)*VLOOKUP("IN-34",'Assumptions & Inputs'!$A$31:$F$69,5,FALSE),0),0) -> 59850 | CA77: =IF(BQ77=1,((AI77+(IF(R77="IN-07",'Assumptions & Inputs'!$C$65,AF77))*AL77)*AS77)+AW77+(((AI77+(IF(R77="IN-07",'Assumptions & Inputs'!$C$65,AF77))*AL77)*AS77)*AZ77)+IF(BD77="Yes",(((AI77+(IF(R77="IN-07",'Assumptions & Inputs'!$C$65,AF77))*AL77)*AS77)+AW77)*VLOOKUP("IN-34",'Assumptions & Inputs'!$A$31:$F$69,3,FALSE),0),0) -> 6669 | CB77: =IF(BQ77=1,((AJ77+(IF(R77="IN-07",'Assumptions & Inputs'!$D$65,AG77))*AM77)*AS77)+AX77+(((AJ77+(IF(R77="IN-07",'Assumptions & Inputs'!$D$65,AG77))*AM77)*AS77)*AZ77)+IF(BD77="Yes",(((AJ77+(IF(R77="IN-07",'Assumptions & Inputs'!$D$65,AG77))*AM77)*AS77)+AX77)*VLOOKUP("IN-34",'Assumptions & Inputs'!$A$31:$F$69,4,FALSE),0),0) -> 18126 | CC77: =IF(BQ77=1,((AK77+(IF(R77="IN-07",'Assumptions & Inputs'!$E$65,AH77))*AN77)*AS77)+AY77+(((AK77+(IF(R77="IN-07",'Assumptions & Inputs'!$E$65,AH77))*AN77)*AS77)*AZ77)+IF(BD77="Yes",(((AK77+(IF(R77="IN-07",'Assumptions & Inputs'!$E$65,AH77))*AN77)*AS77)+AY77)*VLOOKUP("IN-34",'Assumptions & Inputs'!$A$31:$F$69,5,FALSE),0),0) -> 59850 | CD77: =IF(BR77=1,((AI77+(IF(R77="IN-07",'Assumptions & Inputs'!$C$65,AF77))*AL77)*AS77)+AW77+(((AI77+(IF(R77="IN-07",'Assumptions & Inputs'!$C$65,AF77))*AL77)*AS77)*AZ77)+IF(BD77="Yes",(((AI77+(IF(R77="IN-07",'Assumptions & Inputs'!$C$65,AF77))*AL77)*AS77)+AW77)*VLOOKUP("IN-34",'Assumptions & Inputs'!$A$31:$F$69,3,FALSE),0),0) -> 6669 | CE77: =IF(BR77=1,((AJ77+(IF(R77="IN-07",'Assumptions & Inputs'!$D$65,AG77))*AM77)*AS77)+AX77+(((AJ77+(IF(R77="IN-07",'Assumptions & Inputs'!$D$65,AG77))*AM77)*AS77)*AZ77)+IF(BD77="Yes",(((AJ77+(IF(R77="IN-07",'Assumptions & Inputs'!$D$65,AG77))*AM77)*AS77)+AX77)*VLOOKUP("IN-34",'Assumptions & Inputs'!$A$31:$F$69,4,FALSE),0),0) -> 18126 | CF77: =IF(BR77=1,((AK77+(IF(R77="IN-07",'Assumptions & Inputs'!$E$65,AH77))*AN77)*AS77)+AY77+(((AK77+(IF(R77="IN-07",'Assumptions & Inputs'!$E$65,AH77))*AN77)*AS77)*AZ77)+IF(BD77="Yes",(((AK77+(IF(R77="IN-07",'Assumptions & Inputs'!$E$65,AH77))*AN77)*AS77)+AY77)*VLOOKUP("IN-34",'Assumptions & Inputs'!$A$31:$F$69,5,FALSE),0),0) -> 59850 | CG77: =IF(BS77=1,((AI77+(IF(R77="IN-07",0,AF77))*AL77)*AS77)+AW77+(((AI77+(IF(R77="IN-07",0,AF77))*AL77)*AS77)*AZ77)+IF(BD77="Yes",(((AI77+(IF(R77="IN-07",0,AF77))*AL77)*AS77)+AW77)*VLOOKUP("IN-34",'Assumptions & Inputs'!$A$31:$F$69,3,FALSE),0),0) -> 6669 | CH77: =IF(BS77=1,((AJ77+(IF(R77="IN-07",0,AG77))*AM77)*AS77)+AX77+(((AJ77+(IF(R77="IN-07",0,AG77))*AM77)*AS77)*AZ77)+IF(BD77="Yes",(((AJ77+(IF(R77="IN-07",0,AG77))*AM77)*AS77)+AX77)*VLOOKUP("IN-34",'Assumptions & Inputs'!$A$31:$F$69,4,FALSE),0),0) -> 18126 | CI77: =IF(BS77=1,((AK77+(IF(R77="IN-07",0,AH77))*AN77)*AS77)+AY77+(((AK77+(IF(R77="IN-07",0,AH77))*AN77)*AS77)*AZ77)+IF(BD77="Yes",(((AK77+(IF(R77="IN-07",0,AH77))*AN77)*AS77)+AY77)*VLOOKUP("IN-34",'Assumptions & Inputs'!$A$31:$F$69,5,FALSE),0),0) -> 59850 | CJ77: =IF(BT77=1,((AI77+(IF(R77="IN-07",0,AF77))*AL77)*AS77)+AW77+(((AI77+(IF(R77="IN-07",0,AF77))*AL77)*AS77)*AZ77)+IF(BD77="Yes",(((AI77+(IF(R77="IN-07",0,AF77))*AL77)*AS77)+AW77)*VLOOKUP("IN-34",'Assumptions & Inputs'!$A$31:$F$69,3,FALSE),0),0) -> 6669 | CK77: =IF(BT77=1,((AJ77+(IF(R77="IN-07",0,AG77))*AM77)*AS77)+AX77+(((AJ77+(IF(R77="IN-07",0,AG77))*AM77)*AS77)*AZ77)+IF(BD77="Yes",(((AJ77+(IF(R77="IN-07",0,AG77))*AM77)*AS77)+AX77)*VLOOKUP("IN-34",'Assumptions & Inputs'!$A$31:$F$69,4,FALSE),0),0) -> 18126 | CL77: =IF(BT77=1,((AK77+(IF(R77="IN-07",0,AH77))*AN77)*AS77)+AY77+(((AK77+(IF(R77="IN-07",0,AH77))*AN77)*AS77)*AZ77)+IF(BD77="Yes",(((AK77+(IF(R77="IN-07",0,AH77))*AN77)*AS77)+AY77)*VLOOKUP("IN-34",'Assumptions & Inputs'!$A$31:$F$69,5,FALSE),0),0) -> 59850

Sheet Optional Add-Ons Build-Up
A1: Optional Add-Ons and Sensitivity Packages
A2: These packages are excluded from the base scenario unless their trigger occurs.
A4: Add-On ID | B4: Add-On | C4: Trigger | D4: Incremental WBS Activities | E4: Organizations Affected | F4: Formula Structure | G4: Scaling Variables | H4: Benchmark / Estimating Method | I4: Dependencies | J4: Exclusions / Risks | K4: Active? | L4: Applicable Scenario(s) | M4: Low Labor | N4: Base Labor | O4: High Labor | P4: Low Non-Labor | Q4: Base Non-Labor | R4: High Non-Labor | S4: Indirect Rate | T4: Low Contingency | U4: Base Contingency | V4: High Contingency | W4: Low Incremental Total | X4: Base Incremental Total | Y4: High Incremental Total | Z4: BOE Status | AA4: Validation Status | AB4: Source ID
A5: ADD-01 | B5: UDS+ interface and support | C5: Charter includes UDS+ and no adequate existing pathway is available | D5: Requirements/mapping; HRSA authentication; interface configuration; test submission; error remediation; operating support | E5: HCCN; FQHCs; HIE/HDU where applicable | F5: Fixed hours + interface × hours per interface + monthly support × months + vendor fees | G5: 1 interface; FQHC count; test cycles; operating months | H5: Vendor quote; bounded UDS+ implementation analogue | I5: Current UDS+ IG; HRSA test environment; FQHC attribution; agreements | J5: Excludes HRSA federal effort and long-term operations | K5: No | L5: All | M5: 120000 | N5: 220000 | O5: 400000 | P5: 50000 | Q5: 150000 | R5: 350000 | S5: 0.3 | T5: =IF(K5="Yes",(M5+P5)*VLOOKUP("IN-34",'Assumptions & Inputs'!$A$31:$F$69,3,FALSE),0) -> 0 | U5: =IF(K5="Yes",(N5+Q5)*VLOOKUP("IN-34",'Assumptions & Inputs'!$A$31:$F$69,4,FALSE),0) -> 0 | V5: =IF(K5="Yes",(O5+R5)*VLOOKUP("IN-34",'Assumptions & Inputs'!$A$31:$F$69,5,FALSE),0) -> 0 | W5: =IF(K5="Yes",M5+P5+(M5*S5)+T5,0) -> 0 | X5: =IF(K5="Yes",N5+Q5+(N5*S5)+U5,0) -> 0 | Y5: =IF(K5="Yes",O5+R5+(O5*S5)+V5,0) -> 0 | Z5: Provisional — bounded component | AA5: Quote required | AB5: BM-07
A6: ADD-02 | B6: Closed-loop chronic-care referral analysis | C6: Charter includes referral add-on and an existing referral platform/governance model is operational | D6: Workflow confirmation; data-element mapping; marginal platform configuration; test referral/status exchange; analytic and evaluation updates | E6: PHA; intermediary; providers; referral platform/CBO | F6: Fixed workflow effort + participants × onboarding hours + interface/configuration fee | G6: Referral organizations; workflows; test cycles | H6: Bottom-up labor; vendor quote; component analogue | I6: Existing platform, agreements, consent-aware workflow, participating referral recipient | J6: Excludes new referral infrastructure or broad consent-management implementation | K6: No | L6: All | M6: 50000 | N6: 100000 | O6: 220000 | P6: 10000 | Q6: 35000 | R6: 100000 | S6: 0.25 | T6: =IF(K6="Yes",(M6+P6)*VLOOKUP("IN-34",'Assumptions & Inputs'!$A$31:$F$69,3,FALSE),0) -> 0 | U6: =IF(K6="Yes",(N6+Q6)*VLOOKUP("IN-34",'Assumptions & Inputs'!$A$31:$F$69,4,FALSE),0) -> 0 | V6: =IF(K6="Yes",(O6+R6)*VLOOKUP("IN-34",'Assumptions & Inputs'!$A$31:$F$69,5,FALSE),0) -> 0 | W6: =IF(K6="Yes",M6+P6+(M6*S6)+T6,0) -> 0 | X6: =IF(K6="Yes",N6+Q6+(N6*S6)+U6,0) -> 0 | Y6: =IF(K6="Yes",O6+R6+(O6*S6)+V6,0) -> 0 | Z6: Provisional — expert judgment | AA6: Decision required
A7: ADD-03 | B7: New MedicationDispense connection | C7: Broad scope requires dispensing data not already available | D7: Data-source agreement; pharmacy/payer interface; mapping; matching; testing; trust rules; operations | E7: Intermediary; PHA; providers; pharmacy/payer source | F7: Fixed source onboarding + interface × hours + monthly fee × months | G7: 1 new data source/interface; operating months; transaction fees | H7: Vendor quote; public interface fee; bottom-up labor | I7: Data owner participation, legal authority, matching method | J7: Excluded from base; may materially alter schedule | K7: No | L7: 1B, 2B, 3B | M7: 100000 | N7: 220000 | O7: 450000 | P7: 75000 | Q7: 200000 | R7: 500000 | S7: 0.35 | T7: =IF(K7="Yes",(M7+P7)*VLOOKUP("IN-34",'Assumptions & Inputs'!$A$31:$F$69,3,FALSE),0) -> 0 | U7: =IF(K7="Yes",(N7+Q7)*VLOOKUP("IN-34",'Assumptions & Inputs'!$A$31:$F$69,4,FALSE),0) -> 0 | V7: =IF(K7="Yes",(O7+R7)*VLOOKUP("IN-34",'Assumptions & Inputs'!$A$31:$F$69,5,FALSE),0) -> 0 | W7: =IF(K7="Yes",M7+P7+(M7*S7)+T7,0) -> 0 | X7: =IF(K7="Yes",N7+Q7+(N7*S7)+U7,0) -> 0 | Y7: =IF(K7="Yes",O7+R7+(O7*S7)+V7,0) -> 0 | Z7: Provisional — vendor quote needed | AA7: Quote required | AB7: BM-07
A8: ADD-04 | B8: Additional non-FQHC healthcare organization | C8: Participant count exceeds two | D8: Agreement; onboarding; source review; configuration; testing; remediation; training; operations; evaluation | E8: PHA; intermediary/HCCN; added provider; vendor | F8: Organization × hours per organization + source/interface increment where unique | G8: Provider count; source configurations; interfaces; operating months | H8: Parametric estimate using PROV WBS and interface units | I8: Existing connectivity and vendor availability | J8: Does not include new source configuration unless separately triggered | K8: No | L8: All | M8: 25000 | N8: 50000 | O8: 95000 | P8: 5000 | Q8: 15000 | R8: 40000 | S8: 0.25 | T8: =IF(K8="Yes",(M8+P8)*VLOOKUP("IN-34",'Assumptions & Inputs'!$A$31:$F$69,3,FALSE),0) -> 0 | U8: =IF(K8="Yes",(N8+Q8)*VLOOKUP("IN-34",'Assumptions & Inputs'!$A$31:$F$69,4,FALSE),0) -> 0 | V8: =IF(K8="Yes",(O8+R8)*VLOOKUP("IN-34",'Assumptions & Inputs'!$A$31:$F$69,5,FALSE),0) -> 0 | W8: =IF(K8="Yes",M8+P8+(M8*S8)+T8,0) -> 0 | X8: =IF(K8="Yes",N8+Q8+(N8*S8)+U8,0) -> 0 | Y8: =IF(K8="Yes",O8+R8+(O8*S8)+V8,0) -> 0 | Z8: Provisional — parametric | AA8: Pending participant validation | AB8: BM-16
A9: ADD-05 | B9: Additional FQHC | C9: FQHC count exceeds ten | D9: Participation amendment; member onboarding; panel validation; training; operations; evaluation | E9: HCCN; added FQHC; vendor; PHA/HDU | F9: FQHCs × hours per FQHC + marginal support × months | G9: FQHC count; training cohorts; operations months | H9: Parametric estimate using HCCN and PROV WBS | I9: Same HCCN and existing shared vendor pattern | J9: If a new vendor pattern is introduced, also apply ADD-06 | K9: No | L9: 2A, 2B, 3A, 3B | M9: 12000 | N9: 25000 | O9: 50000 | P9: 2000 | Q9: 6000 | R9: 15000 | S9: 0.3 | T9: =IF(K9="Yes",(M9+P9)*VLOOKUP("IN-34",'Assumptions & Inputs'!$A$31:$F$69,3,FALSE),0) -> 0 | U9: =IF(K9="Yes",(N9+Q9)*VLOOKUP("IN-34",'Assumptions & Inputs'!$A$31:$F$69,4,FALSE),0) -> 0 | V9: =IF(K9="Yes",(O9+R9)*VLOOKUP("IN-34",'Assumptions & Inputs'!$A$31:$F$69,5,FALSE),0) -> 0 | W9: =IF(K9="Yes",M9+P9+(M9*S9)+T9,0) -> 0 | X9: =IF(K9="Yes",N9+Q9+(N9*S9)+U9,0) -> 0 | Y9: =IF(K9="Yes",O9+R9+(O9*S9)+V9,0) -> 0 | Z9: Provisional — parametric | AA9: Pending HCCN validation | AB9: BM-15
A10: ADD-06 | B10: Additional source-system configuration | C10: More than five distinct configurations or a materially different tenant pattern | D10: Mapping assessment; interface/configuration; trust rules; testing; baseline; remediation; support | E10: Intermediary/HCCN; affected providers; vendor | F10: Source configurations × hours per configuration + cycles × hours per configuration | G10: Source configuration count; remediation cycles | H10: Parametric estimate; vendor quote | I10: Endpoint and vendor documentation | J10: May also add a production interface | K10: No | L10: All | M10: 45000 | N10: 90000 | O10: 170000 | P10: 15000 | Q10: 35000 | R10: 90000 | S10: 0.35 | T10: =IF(K10="Yes",(M10+P10)*VLOOKUP("IN-34",'Assumptions & Inputs'!$A$31:$F$69,3,FALSE),0) -> 0 | U10: =IF(K10="Yes",(N10+Q10)*VLOOKUP("IN-34",'Assumptions & Inputs'!$A$31:$F$69,4,FALSE),0) -> 0 | V10: =IF(K10="Yes",(O10+R10)*VLOOKUP("IN-34",'Assumptions & Inputs'!$A$31:$F$69,5,FALSE),0) -> 0 | W10: =IF(K10="Yes",M10+P10+(M10*S10)+T10,0) -> 0 | X10: =IF(K10="Yes",N10+Q10+(N10*S10)+U10,0) -> 0 | Y10: =IF(K10="Yes",O10+R10+(O10*S10)+V10,0) -> 0 | Z10: Provisional — parametric | AA10: Quote required | AB10: BM-07
A11: ADD-07 | B11: Additional production interface | C11: Interface topology exceeds scenario base | D11: Architecture delta; connection/security setup; configuration; testing; monitoring; recurring support | E11: Intermediary/HCCN; provider/vendor; PHA if recipient interface | F11: Interfaces × setup hours + monthly fee × months | G11: Interface count; environments; operations months | H11: Vendor quote; bounded interface analogue | I11: Existing endpoint and data-use authority | J11: Separate from source mapping where the same configuration is reused | K11: No | L11: All | M11: 35000 | N11: 70000 | O11: 140000 | P11: 15000 | Q11: 35000 | R11: 80000 | S11: 0.35 | T11: =IF(K11="Yes",(M11+P11)*VLOOKUP("IN-34",'Assumptions & Inputs'!$A$31:$F$69,3,FALSE),0) -> 0 | U11: =IF(K11="Yes",(N11+Q11)*VLOOKUP("IN-34",'Assumptions & Inputs'!$A$31:$F$69,4,FALSE),0) -> 0 | V11: =IF(K11="Yes",(O11+R11)*VLOOKUP("IN-34",'Assumptions & Inputs'!$A$31:$F$69,5,FALSE),0) -> 0 | W11: =IF(K11="Yes",M11+P11+(M11*S11)+T11,0) -> 0 | X11: =IF(K11="Yes",N11+Q11+(N11*S11)+U11,0) -> 0 | Y11: =IF(K11="Yes",O11+R11+(O11*S11)+V11,0) -> 0 | Z11: Provisional — parametric | AA11: Quote required | AB11: BM-07
A12: ADD-08 | B12: Additional remediation cycle | C12: Two base remediation cycles are insufficient | D12: Defect triage; participant/vendor coordination; corrections; reprocessing; retesting; reporting | E12: Intermediary/HCCN; providers; vendors; PHA | F12: Source configurations × additional cycles × hours per cycle + vendor fees | G12: Source configurations; added cycles | H12: Parametric estimate based on base remediation WBS | I12: Baseline severity and vendor availability | J12: Do not duplicate defects covered by fixed-fee vendor implementation | K12: No | L12: All | M12: 30000 | N12: 65000 | O12: 140000 | P12: 10000 | Q12: 30000 | R12: 90000 | S12: 0.3 | T12: =IF(K12="Yes",(M12+P12)*VLOOKUP("IN-34",'Assumptions & Inputs'!$A$31:$F$69,3,FALSE),0) -> 0 | U12: =IF(K12="Yes",(N12+Q12)*VLOOKUP("IN-34",'Assumptions & Inputs'!$A$31:$F$69,4,FALSE),0) -> 0 | V12: =IF(K12="Yes",(O12+R12)*VLOOKUP("IN-34",'Assumptions & Inputs'!$A$31:$F$69,5,FALSE),0) -> 0 | W12: =IF(K12="Yes",M12+P12+(M12*S12)+T12,0) -> 0 | X12: =IF(K12="Yes",N12+Q12+(N12*S12)+U12,0) -> 0 | Y12: =IF(K12="Yes",O12+R12+(O12*S12)+V12,0) -> 0 | Z12: Provisional — parametric | AA12: Pending baseline | AB12: BM-08
A13: ADD-09 | B13: Six-month operations sensitivity | C13: Schedule permits only six live months or sponsor chooses shorter evidence period | D13: Reduce recurring operations, support, reporting, and evaluation cycles; preserve fixed implementation cost | E13: All funded organizations | F13: Monthly run-rate × 6 instead of × 9 | G13: Operations months; reporting cycles; evaluation cycles | H13: Recurring run-rate estimate | I13: Approved evaluation plan and revised schedule | J13: Not a simple 33% reduction of total project cost because fixed costs remain | K13: No | L13: All | M13: -180000 | N13: -320000 | O13: -520000 | P13: -60000 | Q13: -120000 | R13: -220000 | S13: 0.3 | T13: =IF(K13="Yes",(M13+P13)*VLOOKUP("IN-34",'Assumptions & Inputs'!$A$31:$F$69,3,FALSE),0) -> 0 | U13: =IF(K13="Yes",(N13+Q13)*VLOOKUP("IN-34",'Assumptions & Inputs'!$A$31:$F$69,4,FALSE),0) -> 0 | V13: =IF(K13="Yes",(O13+R13)*VLOOKUP("IN-34",'Assumptions & Inputs'!$A$31:$F$69,5,FALSE),0) -> 0 | W13: =IF(K13="Yes",M13+P13+(M13*S13)+T13,0) -> 0 | X13: =IF(K13="Yes",N13+Q13+(N13*S13)+U13,0) -> 0 | Y13: =IF(K13="Yes",O13+R13+(O13*S13)+V13,0) -> 0 | Z13: Schedule sensitivity | AA13: Decision required | AB13: BM-13
A14: ADD-10 | B14: Formal security authorization or penetration testing | C14: PHA/intermediary requires ATO-equivalent approval, independent assessment, or new control documentation | D14: Security plan; control evidence; assessment coordination; remediation; authorization package | E14: PHA; intermediary/HCCN; providers/vendors as needed | F14: Fixed authorization effort + systems × evidence hours + external assessment fee | G14: Systems; environments; findings/remediation cycles | H14: Vendor quote; bottom-up security labor | I14: Security authority requirements and environment inventory | J14: Excluded from base standard connection review | K14: No | L14: All | M14: 80000 | N14: 180000 | O14: 400000 | P14: 50000 | Q14: 150000 | R14: 400000 | S14: 0.3 | T14: =IF(K14="Yes",(M14+P14)*VLOOKUP("IN-34",'Assumptions & Inputs'!$A$31:$F$69,3,FALSE),0) -> 0 | U14: =IF(K14="Yes",(N14+Q14)*VLOOKUP("IN-34",'Assumptions & Inputs'!$A$31:$F$69,4,FALSE),0) -> 0 | V14: =IF(K14="Yes",(O14+R14)*VLOOKUP("IN-34",'Assumptions & Inputs'!$A$31:$F$69,5,FALSE),0) -> 0 | W14: =IF(K14="Yes",M14+P14+(M14*S14)+T14,0) -> 0 | X14: =IF(K14="Yes",N14+Q14+(N14*S14)+U14,0) -> 0 | Y14: =IF(K14="Yes",O14+R14+(O14*S14)+V14,0) -> 0 | Z14: Provisional — vendor quote needed | AA14: Security decision required | AB14: BM-04
A15: ADD-11 | B15: New environment or software license | C15: Existing environment capacity or licenses are insufficient | D15: Provision environment; deploy/configure; security review; testing; backup/monitoring; recurring licenses | E15: PHA; intermediary/HCCN | F15: Environments × setup hours + monthly cloud/license fee × months | G15: Environment count; license units; months | H15: Public rate schedule; vendor quote; cloud calculator | I15: Architecture, security requirements, licensing terms | J15: Avoid allocating sunk enterprise costs unless full-economic-cost view is requested | K15: No | L15: All | M15: 50000 | N15: 110000 | O15: 250000 | P15: 60000 | Q15: 150000 | R15: 400000 | S15: 0.35 | T15: =IF(K15="Yes",(M15+P15)*VLOOKUP("IN-34",'Assumptions & Inputs'!$A$31:$F$69,3,FALSE),0) -> 0 | U15: =IF(K15="Yes",(N15+Q15)*VLOOKUP("IN-34",'Assumptions & Inputs'!$A$31:$F$69,4,FALSE),0) -> 0 | V15: =IF(K15="Yes",(O15+R15)*VLOOKUP("IN-34",'Assumptions & Inputs'!$A$31:$F$69,5,FALSE),0) -> 0 | W15: =IF(K15="Yes",M15+P15+(M15*S15)+T15,0) -> 0 | X15: =IF(K15="Yes",N15+Q15+(N15*S15)+U15,0) -> 0 | Y15: =IF(K15="Yes",O15+R15+(O15*S15)+V15,0) -> 0 | Z15: Provisional — vendor quote needed | AA15: Technical validation required | AB15: BM-13
A16: ADD-12 | B16: High-intensity technical assistance | C16: Readiness validation identifies material participant capability gaps | D16: Additional readiness sessions; documentation support; hands-on mapping/testing; repeated training | E16: PHA; intermediary/HCCN; providers | F16: Organizations × additional TA hours per organization | G16: Organizations; TA intensity; months | H16: Bottom-up labor; historical internal estimate | I16: Specific gap-resolution plan | J16: Does not include net-new platform development | K16: No | L16: All | M16: 40000 | N16: 90000 | O16: 200000 | P16: 5000 | Q16: 15000 | R16: 40000 | S16: 0.3 | T16: =IF(K16="Yes",(M16+P16)*VLOOKUP("IN-34",'Assumptions & Inputs'!$A$31:$F$69,3,FALSE),0) -> 0 | U16: =IF(K16="Yes",(N16+Q16)*VLOOKUP("IN-34",'Assumptions & Inputs'!$A$31:$F$69,4,FALSE),0) -> 0 | V16: =IF(K16="Yes",(O16+R16)*VLOOKUP("IN-34",'Assumptions & Inputs'!$A$31:$F$69,5,FALSE),0) -> 0 | W16: =IF(K16="Yes",M16+P16+(M16*S16)+T16,0) -> 0 | X16: =IF(K16="Yes",N16+Q16+(N16*S16)+U16,0) -> 0 | Y16: =IF(K16="Yes",O16+R16+(O16*S16)+V16,0) -> 0 | Z16: Provisional — bottom-up | AA16: Readiness validation required | AB16: BM-12
